Workbook

Sheet SNTDR 2169
A1: FECHA | B1: M | C1: S | D1: C | E1: # | F1: PROVEEDOR | G1: F VTA | H1: RETIRO | I1: DEPOSITO | J1: SALDO
A2: 46024 | B2: G | D2: 612 | F2: EMISION DE CHEQUERA LIBRAMIENTO DE CHEQU | H2: 1460 | J2: 526.71 | K2: =J2+H2-I2 -> 1986.71
A3: 46024 | B3: G | D3: 147 | F3: IVA | H3: 233.6 | J3: =J2-H3+I3 -> 293.11
A4: 46024 | B4: I | C4: 42 | D4: 102 | F4: TARJETALA PIEDAD ABASTOS | G4: 46022 | I4: 3940.04 | J4: =J3-H4+I4 -> 4233.15
A5: 46024 | B5: I | C5: 50 | D5: 102 | F5: VENTAS CANINDO TARJETA | G5: 46022 | I5: 7274.8 | J5: =J4-H5+I5 -> 11507.95
A6: 46024 | B6: I | C6: 10 | D6: 102 | F6: VENTAS PADRE HIDALGO | G6: AA | I6: 11119.7 | J6: =J5-H6+I6 -> 22627.65
A7: 46024 | B7: I | C7: V | D7: 102 | F7: VENTAS PADRE HIDALGO | G7: AA | I7: 3082.59 | J7: =J6-H7+I7 -> 25710.24
A8: 46024 | B8: I | C8: 10 | D8: 102 | F8: VENTAS PADRE HIDALGO | G8: AA | I8: 16282.05 | J8: =J7-H8+I8 -> 41992.29
A9: 46024 | B9: I | C9: 10 | D9: 102 | F9: TARJETA VTA PADRE HIDALGO | G9: 01//01/26 | I9: 9951.69 | J9: =J8-H9+I9 -> 51943.98
A10: 46024 | B10: I | C10: 10 | D10: 102 | F10: VENTAS PADRE HIDALGO | G10: AA | I10: 27173.82 | J10: =J9-H10+I10 -> 79117.8
A11: 46024 | B11: I | C11: 10 | D11: 102 | F11: VENTAS PADRE HIDALGO | G11: AA | I11: 19794.23 | J11: =J10-H11+I11 -> 98912.03
A12: 46024 | B12: I | C12: 50 | D12: 102 | F12: VENTAS CANINDO TARJETA | G12: 46022 | I12: 3115.38 | J12: =J11-H12+I12 -> 102027.41
A13: 46024 | B13: I | C13: 42 | D13: 102 | F13: TARJETALA PIEDAD ABASTOS | I13: 16757.4 | J13: =J12-H13+I13 -> 118784.81
A14: 46024 | B14: G | D14: 612 | F14: Comision | H14: 150 | J14: =J13-H14+I14 -> 118634.81
A15: 46024 | B15: G | D15: 147 | F15: Iva | H15: 24 | J15: =J14-H15+I15 -> 118610.81
A16: 46024 | B16: G | D16: 612 | F16: Comision | H16: 68.86 | J16: =J15-H16+I16 -> 118541.95
A17: 46024 | B17: G | D17: 147 | F17: Iva | H17: 11.02 | J17: =J16-H17+I17 -> 118530.93
A18: 46024 | B18: G | D18: 612 | F18: Comision | H18: 200 | J18: =J17-H18+I18 -> 118330.93
A19: 46024 | B19: G | D19: 147 | F19: Iva | H19: 32 | J19: =J18-H19+I19 -> 118298.93
A20: 46024 | B20: G | D20: 612 | F20: Comision | H20: 137.11 | J20: =J19-H20+I20 -> 118161.82
A21: 46024 | B21: G | D21: 147 | F21: Iva | H21: 21.94 | J21: =J20-H21+I21 -> 118139.88
A22: 46024 | B22: G | D22: 612 | F22: Comision | H22: 200 | J22: =J21-H22+I22 -> 117939.88
A23: 46024 | B23: G | D23: 147 | F23: Iva | H23: 32 | J23: =J22-H23+I23 -> 117907.88
A24: 46024 | B24: G | D24: 612 | F24: Comision | H24: 196.59 | J24: =J23-H24+I24 -> 117711.29
A25: 46024 | B25: G | D25: 147 | F25: Iva | H25: 31.45 | J25: =J24-H25+I25 -> 117679.84
... A45: 46024 | B45: G | D45: 147 | F45: Iva | H45: 32 | J45: =J44-H45+I45 -> 114873.19
A46: 46024 | B46: G | D46: 612 | E46: 1 | F46: Tdc American Express | H46: 9 | J46: =J45-H46+I46 -> 114864.19
A47: 46024 | B47: I | D47: 102 | F47: Dep. Efectivo | I47: 106.5 | J47: =J46-H47+I47 -> 114970.69
A48: 46024 | B48: I | C48: 10 | D48: 102 | F48: VENTAS PADRE HIDALGO | G48: 46023 | I48: 34776 | J48: =J47-H48+I48 -> 149746.69
A49: 46024 | B49: G | C49: 40 | D49: 610 | E49: 2 | F49: Nomina 01 | H49: 35088.8 | J49: =J48-H49+I49 -> 114657.89
A50: 46024 | B50: G | C50: 42 | D50: 610 | E50: 3 | F50: Nomina 01 | H50: 18889.6 | J50: =J49-H50+I50 -> 95768.29
A51: 46024 | B51: I | C51: 10 | D51: 102 | F51: VENTAS PADRE HIDALGO | I51: 225800.5 | J51: =J50-H51+I51 -> 321568.79
A52: 46024 | B52: I | C52: 42 | D52: 102 | F52: VENTAS LA PIEDAD ABASTOS | G52: 46022 | I52: 110943 | J52: =J51-H52+I52 -> 432511.79
A53: 46024 | B53: I | C53: 10 | D53: 102 | F53: VENTAS PADRE HIDALGO | I53: 34651.5 | J53: =J52-H53+I53 -> 467163.29
A54: 46024 | B54: I | C54: 10 | D54: 102 | F54: VENTAS PADRE HIDALGO | I54: 517.5 | J54: =J53-H54+I54 -> 467680.79
A55: 46024 | B55: I | C55: 10 | D55: 102 | F55: VENTAS PADRE HIDALGO | I55: 47 | J55: =J54-H55+I55 -> 467727.79
A56: 46024 | B56: I | C56: 10 | D56: 102 | F56: VENTAS PADRE HIDALGO | I56: 23988 | J56: =J55-H56+I56 -> 491715.79
A57: 46024 | B57: I | C57: 10 | D57: 102 | F57: VENTAS PADRE HIDALGO | I57: 3350 | J57: =J56-H57+I57 -> 495065.79
A58: 46024 | B58: I | C58: 10 | D58: 102 | F58: VENTAS PADRE HIDALGO | I58: 9918 | J58: =J57-H58+I58 -> 504983.79
A59: 46024 | B59: I | C59: 10 | D59: 102 | F59: VENTAS PADRE HIDALGO | I59: 401 | J59: =J58-H59+I59 -> 505384.79
A60: 46024 | B60: I | C60: 10 | D60: 102 | F60: VENTAS PADRE HIDALGO | I60: 4030 | J60: =J59-H60+I60 -> 509414.79
A61: 46024 | B61: I | C61: 42 | D61: 102 | F61: VENTAS LA PIEDAD ABASTOS | G61: 46022 | I61: 10261 | J61: =J60-H61+I61 -> 519675.79
A62: 46024 | B62: I | C62: 10 | D62: 102 | F62: VENTAS PADRE HIDALGO | I62: 3836 | J62: =J61-H62+I62 -> 523511.79
A63: 46024 | B63: I | C63: 10 | D63: 102 | F63: VENTAS PADRE HIDALGO | I63: 460 | J63: =J62-H63+I63 -> 523971.79
A64: 46024 | B64: I | C64: 10 | D64: 102 | F64: VENTAS PADRE HIDALGO | I64: 5800 | J64: =J63-H64+I64 -> 529771.79
A65: 46024 | B65: TE | D65: - | F65: TRASPASO A BB 4166 | H65: 450000 | J65: =J64-H65+I65 -> 79771.79
A66: 46027 | B66: I | C66: 42 | D66: 102 | F66: TARJETALA PIEDAD ABASTOS | I66: 7189.98 | J66: =J65-H66+I66 -> 86961.77
A67: 46027 | B67: I | C67: 42 | D67: 102 | F67: tARJETA LA PIEDAD ABASTOS | G67: 46025 | I67: 2753.32 | J67: =J66-H67+I67 -> 89715.09
A68: 46027 | B68: I | C68: 42 | D68: 102 | F68: tARJETA LA PIEDAD ABASTOS | G68: 46026 | I68: 8686.99 | J68: =J67-H68+I68 -> 98402.08
A69: 46027 | B69: I | C69: 50 | D69: 102 | F69: VENTAS CANINDO TARJETA | G69: 46024 | I69: 84.99 | J69: =J68-H69+I69 -> 98487.07
A70: 46027 | B70: I | C70: 50 | D70: 102 | F70: VENTAS CANINDO TARJETA | G70: 46025 | I70: 18415.04 | J70: =J69-H70+I70 -> 116902.11
A71: 46027 | B71: I | C71: 50 | D71: 102 | F71: VENTAS CANINDO TARJETA | G71: 46026 | I71: 18159.44 | J71: =J70-H71+I71 -> 135061.55
A72: 46027 | B72: I | C72: 40 | D72: 102 | F72: VTA TARJETA 8E | G72: 45659 | I72: 36613.74 | J72: =J71-H72+I72 -> 171675.29
A73: 46027 | B73: I | C73: 40 | D73: 102 | F73: TARJETA vta 8 esquinas | G73: 46027 | I73: 4141.24 | J73: =J72-H73+I73 -> 175816.53
A74: 46027 | B74: I | C74: 40 | D74: 102 | F74: TARJETA vta 8 esquinas | G74: 46027 | I74: 7015.27 | J74: =J73-H74+I74 -> 182831.8
A75: 46027 | B75: I | C75: 10 | D75: 102 | F75: VTA TARJETA PH | G75: 46024 | I75: 31363.29 | J75: =J74-H75+I75 -> 214195.09
A76: 46027 | B76: I | C76: 10 | D76: 102 | F76: VTA TARJETA PH | G76: 45660 | I76: 17949.97 | J76: =J75-H76+I76 -> 232145.06
A77: 46027 | B77: I | C77: 10 | D77: 102 | F77: VTA TARJETA PH | G77: 45660 | I77: 18254.92 | J77: =J76-H77+I77 -> 250399.98
A78: 46027 | B78: I | C78: 10 | D78: 102 | F78: VTA TARJETA PH | G78: 46024 | I78: 6722.15 | J78: =J77-H78+I78 -> 257122.13
... A88: 46027 | B88: I | C88: 42 | D88: 102 | F88: TARJETALA PIEDAD ABASTOS | G88: 46026 | I88: 1709.67 | J88: =J87-H88+I88 -> 356868.15
A89: 46027 | B89: G | D89: 612 | F89: Comision | H89: 137.18 | J89: =J88-H89+I89 -> 356730.97
A90: 46027 | B90: G | D90: 147 | F90: Iva | H90: 21.95 | J90: =J89-H90+I90 -> 356709.02
A91: 46027 | B91: G | D91: 612 | F91: Comision | H91: 51.82 | J91: =J90-H91+I91 -> 356657.2
A92: 46027 | B92: G | D92: 147 | F92: Iva | H92: 8.29 | J92: =J91-H92+I92 -> 356648.91
A93: 46027 | B93: G | D93: 612 | F93: Comision | H93: 147.92 | J93: =J92-H93+I93 -> 356500.99
A94: 46027 | B94: G | D94: 147 | F94: Iva | H94: 23.67 | J94: =J93-H94+I94 -> 356477.32
A95: 46027 | B95: G | D95: 612 | F95: Comision | H95: 1.3 | J95: =J94-H95+I95 -> 356476.02
A96: 46027 | B96: G | D96: 147 | F96: Iva | H96: 0.21 | J96: =J95-H96+I96 -> 356475.81
A97: 46027 | B97: G | D97: 612 | F97: Comision | H97: 300.57 | J97: =J96-H97+I97 -> 356175.24
A98: 46027 | B98: G | D98: 147 | F98: Iva | H98: 48.09 | J98: =J97-H98+I98 -> 356127.15
A99: 46027 | B99: G | D99: 612 | F99: Comision | H99: 337.42 | J99: =J98-H99+I99 -> 355789.73
A100: 46027 | B100: G | D100: 147 | F100: Iva | H100: 53.99 | J100: =J99-H100+I100 -> 355735.74
... A134: 46027 | B134: G | D134: 147 | F134: Iva | H134: 5.05 | J134: =J133-H134+I134 -> 350887.69
A135: 46027 | B135: I | C135: 10 | D135: 102 | F135: VENTAS PH | G135: 46030 | I135: 24939 | J135: =J134-H135+I135 -> 375826.69
A136: 46027 | B136: I | C136: 42 | D136: 102 | F136: VENTAS LA PIEDAD ABASTOS | I136: 385 | J136: =J135-H136+I136 -> 376211.69
A137: 46027 | B137: I | C137: 42 | D137: 102 | F137: VENTAS LA PIEDAD ABASTOS | I137: 57.47 | J137: =J136-H137+I137 -> 376269.16
A138: 46027 | B138: I | C138: 42 | D138: 102 | F138: VENTAS LA PIEDAD ABASTOS | I138: 16.49 | J138: =J137-H138+I138 -> 376285.65
A139: 46027 | B139: I | C139: 10 | D139: 102 | F139: VTA PADRE HIDALGO | I139: 87.64 | J139: =J138-H139+I139 -> 376373.29
A140: 46027 | B140: I | C140: 42 | D140: 102 | F140: VENTAS LA PIEDAD ABASTOS | I140: 135.36 | J140: =J139-H140+I140 -> 376508.65
A141: 46027 | B141: I | C141: 42 | D141: 102 | F141: VENTAS LA PIEDAD ABASTOS | I141: 337.56 | J141: =J140-H141+I141 -> 376846.21
A142: 46027 | B142: I | C142: 42 | D142: 102 | F142: VENTAS LA PIEDAD ABASTOS | I142: 503.48 | J142: =J141-H142+I142 -> 377349.69
A143: 46027 | B143: I | C143: 42 | D143: 102 | F143: VENTAS LA PIEDAD ABASTOS | I143: 18.24 | J143: =J142-H143+I143 -> 377367.93
A144: 46027 | B144: I | C144: 42 | D144: 102 | F144: VENTAS LA PIEDAD ABASTOS | I144: 16.49 | J144: =J143-H144+I144 -> 377384.42
A145: 46027 | B145: I | C145: 42 | D145: 102 | F145: VENTAS LA PIEDAD ABASTOS | I145: 200.01 | J145: =J144-H145+I145 -> 377584.43
A146: 46027 | B146: I | C146: 42 | D146: 102 | F146: VENTAS LA PIEDAD ABASTOS | I146: 149.98 | J146: =J145-H146+I146 -> 377734.41
A147: 46027 | B147: I | C147: 42 | D147: 102 | F147: VENTAS LA PIEDAD ABASTOS | I147: 893.06 | J147: =J146-H147+I147 -> 378627.47
... A153: 46027 | B153: I | C153: 42 | D153: 102 | F153: VENTAS LA PIEDAD ABASTOS | I153: 1590 | J153: =J152-H153+I153 -> 388175.92
A154: 46027 | B154: I | C154: 30 | D154: 102 | F154: VENTAS MORELIA ABASTOS | G154: 46025 | I154: 10787.5 | J154: =J153-H154+I154 -> 398963.42
A155: 46027 | B155: I | C155: 30 | D155: 102 | F155: VENTAS MORELIA ABASTOS | G155: 46025 | I155: 6447 | J155: =J154-H155+I155 -> 405410.42
A156: 46027 | B156: I | C156: 30 | D156: 102 | F156: VENTAS MORELIA ABASTOS | G156: 46025 | I156: 1124 | J156: =J155-H156+I156 -> 406534.42
A157: 46027 | B157: I | C157: 30 | D157: 102 | F157: VENTAS MORELIA ABASTOS | G157: 46025 | I157: 5194.5 | J157: =J156-H157+I157 -> 411728.92
A158: 46027 | B158: I | C158: 10 | D158: 102 | F158: VENTAS PADRE HIDALGO | I158: 1486.5 | J158: =J157-H158+I158 -> 413215.42
A159: 46027 | B159: I | C159: 10 | D159: 102 | F159: VENTAS PADRE HIDALGO | I159: 116693 | J159: =J158-H159+I159 -> 529908.42
A160: 46027 | B160: I | C160: 42 | D160: 102 | F160: VENTAS LA PIEDAD ABASTOS | G160: 46026 | I160: 57005.5 | J160: =J159-H160+I160 -> 586913.92
A161: 46027 | B161: I | C161: 73 | D161: 102 | F161: Vta.Tlmk Morelia Jose Almanza | G161: 45994 | I161: 16126 | J161: =J160-H161+I161 -> 603039.92
A162: 46027 | B162: I | C162: 42 | D162: 102 | F162: VENTAS LA PIEDAD ABASTOS | G162: 46024 | I162: 60828.5 | J162: =J161-H162+I162 -> 663868.42
A163: 46027 | B163: I | C163: 42 | D163: 102 | F163: VENTAS LA PIEDAD ABASTOS | G163: 46025 | I163: 71466.5 | J163: =J162-H163+I163 -> 735334.92
A164: 46027 | B164: G | C164: 54 | D164: 610 | E164: 16650 | F164: NOM 1 BENJAMIN ALONZO ZARAGOZA DAMAZO | H164: 2093.8 | J164: =J163-H164+I164 -> 733241.12
A165: 46027 | B165: G | C165: 90 | D165: 613 | E165: 16644 | F165: NOM 1 FINIQUITO PEDRO ALFONSO RODRIGUEZ G. YURECUARO | H165: 6920.27 | J165: =J164-H165+I165 -> 726320.85
A166: 46027 | B166: G | C166: 75 | D166: 610 | E166: 16649 | F166: NOM 1 LUIS FRANCISCO LOPEZ GUTIERREZ CAN-TLMK | H166: 4187.8 | J166: =J165-H166+I166 -> 722133.05
...

Sheet BNMX 1463
A1: FECHA | B1: M | C1: S | D1: C | E1: # | F1: PROVEEDOR | G1: F VTA | H1: RETIRO | I1: DEPOSITO | J1: SALDO
A2: 46028 | B2: I | C2: 70 | D2: 102 | F2: VTA TLMK PH ELIZABETH RUIZ MIRAMONTES | G2: 46007 | I2: 12149.37 | J2: 28921.26 | K2: =J2+H2-I2 -> 16771.89
A3: 46029 | B3: I | C3: N/A | D3: 102 | F3: 3010172 | I3: 0 | J3: =J2-H3+I3 -> 28921.26
A4: 46029 | B4: I | C4: 73 | D4: 102 | F4: Vta.Tlmk Morelia Mariana Jacinto | G4: 46020 | I4: 10452.04 | J4: =J3-H4+I4 -> 39373.3
A5: 46029 | B5: I | C5: N/A | D5: 102 | F5: 3010172 | I5: 0 | J5: =J4-H5+I5 -> 39373.3
A6: 46029 | B6: I | C6: 73 | D6: 102 | F6: Vta.Tlmk Morelia Mariana Jacinto | G6: 45986 | I6: 4480.58 | J6: =J5-H6+I6 -> 43853.88
A7: 46030 | B7: I | C7: 90 | D7: 102 | F7: VTA. YURECUARO | G7: 46028 | I7: 15212 | J7: =J6-H7+I7 -> 59065.88
A8: 46030 | B8: I | C8: 90 | D8: 102 | F8: VTA. YURECUARO | G8: 46027 | I8: 28201 | J8: =J7-H8+I8 -> 87266.88
A9: 46031 | B9: G | C9: 72 | D9: 612 | F9: ADMINISTRACION PAQUETE DE SERVICIOS PYME | H9: 490 | J9: =J8-H9+I9 -> 86776.88
A10: 46031 | B10: G | C10: 72 | D10: 147 | F10: IVA | H10: 78.4 | J10: =J9-H10+I10 -> 86698.48
A11: 46031 | B11: C | D11: 102 | E11: 1 | F11: Dulces Las Delicias Sa de CV | H11: 37285.39 | J11: =J10-H11+I11 -> 49413.09
A12: 46031 | B12: C | D12: 102 | E12: 2 | F12: Dulces Las Delicias Sa de CV | H12: 48740.08 | J12: =J11-H12+I12 -> 673.01
A13: 46034 | B13: I | C13: 70 | D13: 102 | F13: Vta.Tlmk Ph Wendy Maria | G13: 46017 | I13: 7186 | J13: =J12-H13+I13 -> 7859.01
A14: 46034 | B14: I | C14: N/A | D14: 102 | F14: 70880 | I14: 0 | J14: =J13-H14+I14 -> 7859.01
A15: 46037 | B15: I | C15: 70 | D15: 102 | F15: VTA TLMK MORELIA EDUARDO SAMANO SCHUENEMANN | G15: 46005 | I15: 2239.07 | J15: =J14-H15+I15 -> 10098.08
A16: 46038 | B16: I | C16: 70 | D16: 102 | F16: KAREN JANETH AYALA RODRIGUEZ | I16: 1265.43 | J16: =J15-H16+I16 -> 11363.51
A17: 46041 | B17: I | C17: N/A | D17: 102 | F17: 303056 | I17: 0 | J17: =J16-H17+I17 -> 11363.51
A18: 46041 | B18: I | C18: 73 | D18: 102 | F18: Vta.Tlmk Morelia Maria luisa | G18: 46015 | I18: 4037.18 | J18: =J17-H18+I18 -> 15400.69
A19: 46041 | B19: I | C19: N/A | D19: 102 | F19: 303056 | I19: 0 | J19: =J18-H19+I19 -> 15400.69
A20: 46041 | B20: I | C20: 73 | D20: 102 | F20: Vta.Tlmk Morelia Maria Luisa | G20: 46015 | I20: 9339.36 | J20: =J19-H20+I20 -> 24740.05
A21: 46041 | B21: I | C21: 73 | D21: 102 | F21: Vta.Tlmk Morelia Ruben Pantoja | G21: 46024 | I21: 3395.98 | J21: =J20-H21+I21 -> 28136.03
A22: 46043 | B22: I | C22: 70 | D22: 102 | F22: VTA TLMK PH ELIZABETH RUIZ MIRAMONTES | G22: 13/01/2026 Y 06/01/2026 | I22: 2440.11 | J22: =J21-H22+I22 -> 30576.14
A23: 46043 | B23: I | C23: 73 | D23: 102 | F23: Vta.Tlmk Morelia Silvia Mendoza | G23: 46022 | I23: 11970.67 | J23: =J22-H23+I23 -> 42546.81
A24: 46043 | B24: I | C24: 73 | D24: 102 | F24: Vta.Tlmk Morelia Silvia Mendoza | G24: 46030 | I24: 15244.61 | J24: =J23-H24+I24 -> 57791.42
A25: 46043 | B25: I | C25: 73 | D25: 102 | F25: Vta.Tlmk Morelia Silvia Mendoza | G25: 46038 | I25: 9781.57 | J25: =J24-H25+I25 -> 67572.99
A26: 46045 | B26: TE | D26: - | F26: TRASPASO A SNTDRD 2169 | H26: 65000 | J26: =J25-H26+I26 -> 2572.99
A27: 46051 | B27: I | C27: 10 | D27: 102 | F27: SUPER LOS PANCHOS SA DE CV Tlmk Ph | I27: 25443.76 | J27: =J26-H27+I27 -> 28016.75
A28: 46051 | B28: I | C28: 10 | D28: 102 | F28: VIVIANA ITZEL JAIMES MADRIZ | I28: 12470 | J28: =J27-H28+I28 -> 40486.75
A29: 46052 | B29: TE | D29: - | F29: TRASPASO A BTE 7744 | H29: 40000 | J29: =J28-H29+I29 -> 486.75
H31: =SUM(H2:H29) -> 191593.87 | I31: =SUM(I2:I29)+K2 -> 192080.62
I32: =I31-H31 -> 486.75

Sheet BTE 3041
A1: FECHA | B1: M | C1: S | D1: C | E1: # | F1: PROVEEDOR | G1: F VTA | H1: RETIRO | I1: DEPOSITO | J1: SALDO
A2: 46024 | B2: I | C2: 70 | D2: 102 | F2: Vta.Tlmk Ph Andrea Angelica | G2: 45994 | I2: 10000 | J2: 11094.18 | K2: =J2+H2-I2 -> 1094.18
A3: 46027 | B3: I | C3: 70 | D3: 102 | F3: Vta.Tlmk Ph Anahi Elizabeth | G3: 46007 | I3: 7087.01 | J3: =J2+I3-H3 -> 18181.19
A4: 46027 | B4: I | C4: 70 | D4: 102 | F4: Vta.Tlmk Ph Rocio Pimentel | G4: 46009 | I4: 20000 | J4: =J3+I4-H4 -> 38181.19
A5: 46027 | B5: I | C5: 70 | D5: 102 | F5: Vta.Tlmk Ph Cecy Fruta | G5: 46021 | I5: 3920 | J5: =J4+I5-H5 -> 42101.19
A6: 46027 | B6: I | C6: 70 | D6: 102 | F6: Vta.Tlmk Ph Cecy Fruta | G6: 46002 | I6: 1548 | J6: =J5+I6-H6 -> 43649.19
A7: 46027 | B7: I | C7: 70 | D7: 102 | F7: Vta.Tlmk Ph Castillo Uribe | G7: 46021 | I7: 7731 | J7: =J6+I7-H7 -> 51380.19
A8: 46027 | B8: I | C8: 70 | D8: 102 | F8: Vta.Tlmk Ph Ismael Arias | G8: 45993 | I8: 2153 | J8: =J7+I8-H8 -> 53533.19
A9: 46027 | B9: I | C9: 70 | D9: 102 | F9: Vta.Tlmk Ph Adrian Ornelas | G9: 46007 | I9: 9750 | J9: =J8+I9-H9 -> 63283.19
A10: 46027 | B10: I | C10: 70 | D10: 102 | F10: Vta.Tlmk Ph Cueritos Lupita | G10: 45979 | I10: 15000 | J10: =J9+I10-H10 -> 78283.19
A11: 46027 | B11: I | C11: 70 | D11: 102 | F11: Vta.Tlmk Ph Ismael Rodriguez | G11: 46022 | I11: 20311 | J11: =J10+I11-H11 -> 98594.19
A12: 46027 | B12: I | C12: 70 | D12: 102 | F12: Vta.Tlmk Ph Miguel Angel Servin | G12: 46022 | I12: 8811 | J12: =J11+I12-H12 -> 107405.19
A13: 46027 | B13: I | C13: 70 | D13: 102 | F13: Vta.Tlmk Ph Delia Govea | G13: 46022 | I13: 10696 | J13: =J12+I13-H13 -> 118101.19
A14: 46027 | B14: I | C14: 70 | D14: 102 | F14: Vta.Tlmk Ph Rocio Sanchez | G14: 46022 | I14: 334 | J14: =J13+I14-H14 -> 118435.19
... A18: 46027 | B18: I | C18: 70 | D18: 102 | F18: Vta.Tlmk Ph Camarena Jacinto | G18: 46024 | I18: 5643 | J18: =J17+I18-H18 -> 140968.19
A19: 46027 | B19: C | C19: 0 | D19: 510 | E19: 1 | F19: Comercializadora Gonac SA de CV | H19: 120323.17 | J19: =J18+I19-H19 -> 20645.02
A20: 46027 | B20: C | C20: 10 | D20: 510 | E20: 2 | F20: Abarrotes del Centro Guerrero | H20: 13065.01 | J20: =J19+I20-H20 -> 7580.01
A21: 46029 | B21: I | C21: 70 | D21: 102 | F21: Vta.Tlmk Ph Gutierrez Lara | G21: 46014 | I21: 21572 | J21: =J20+I21-H21 -> 29152.01
A22: 46029 | B22: I | C22: 70 | D22: 102 | F22: Vta.Tlmk Ph Andrea Angelica | G22: 45994 | I22: 10000 | J22: =J21+I22-H22 -> 39152.01
A23: 46029 | B23: I | C23: 70 | D23: 102 | F23: Vta.Tlmk Ph Carniceria Duran | G23: 46003 | I23: 300 | J23: =J22+I23-H23 -> 39452.01
A24: 46029 | B24: I | C24: 70 | D24: 102 | F24: Vta.Tlmk Ph Luis Felipe torres | G24: 46020 | I24: 1145 | J24: =J23+I24-H24 -> 40597.01
A25: 46029 | B25: I | C25: 70 | D25: 102 | F25: Vta.Tlmk Ph Gastos Tlmk | G25: 46029 | I25: 204 | J25: =J24+I25-H25 -> 40801.01
A26: 46029 | B26: I | C26: 70 | D26: 102 | F26: Vta.Tlmk Ph Lourdes Encino | G26: 45992 | I26: 14783.44 | J26: =J25+I26-H26 -> 55584.45
A27: 46029 | B27: I | C27: 70 | D27: 102 | F27: Vta.Tlmk Ph Lourdes Encino | G27: 45985 | I27: 16918.7 | J27: =J26+I27-H27 -> 72503.15
A28: 46029 | B28: I | C28: 70 | D28: 102 | F28: Vta.Tlmk Ph Ma. Lourdes Encino | G28: 46027 | I28: 1010.19 | J28: =J27+I28-H28 -> 73513.34
A29: 46029 | B29: I | C29: 70 | D29: 102 | F29: Vta.Tlmk Ph Ma. Lourdes Encino | G29: 46027 | I29: 1498.76 | J29: =J28+I29-H29 -> 75012.1
A30: 46029 | B30: I | C30: 70 | D30: 102 | F30: Vta.Tlmk Ph Ma. Lourdes Encino | G30: 46027 | I30: 1864.08 | J30: =J29+I30-H30 -> 76876.18
A31: 46029 | B31: i | C31: 70 | D31: 102 | F31: Vta.Tlmk Ph Lourdes Encino | G31: 45996 | I31: 4521 | J31: =J30+I31-H31 -> 81397.18
A32: 46029 | B32: I | C32: 70 | D32: 102 | F32: Vta.Tlmk Ph Lourdes Encino | G32: 45996 | I32: 17334.25 | J32: =J31+I32-H32 -> 98731.43
... A45: 46029 | B45: I | C45: 70 | D45: 102 | F45: Vta.Tlmk Ph Sergio Ochoa | G45: 46027 | I45: 3470 | J45: =J44+I45-H45 -> 204714.01
A46: 46029 | B46: C | C46: 50 | D46: 510 | E46: 3 | F46: Salsas Don Vasco | H46: 9891.4 | J46: =J45+I46-H46 -> 194822.61
A47: 46029 | B47: C | C47: 30 | D47: 510 | E47: 4 | F47: Salsas Don Vasco | H47: 88922.85 | J47: =J46+I47-H47 -> 105899.76
A48: 46029 | B48: TE | D48: - | F48: TRASPASO A BBVA 5712 | H48: 100000 | J48: =J47+I48-H48 -> 5899.76
A49: 46030 | B49: I | C49: 70 | D49: 102 | F49: Vta.Tlmk Ph Margarita Sanchez | G49: 46000 | I49: 8691 | J49: =J48+I49-H49 -> 14590.76
A50: 46030 | B50: I | C50: 70 | D50: 102 | F50: Vta.Tlmk Ph Ma. Trinidad Vargas | G50: 46014 | I50: 3410 | J50: =J49+I50-H50 -> 18000.76
A51: 46030 | B51: I | C51: 70 | D51: 102 | F51: Vta.Tlmk Ph Margarita Rodriguez | G51: 46028 | I51: 665 | J51: =J50+I51-H51 -> 18665.76
A52: 46030 | B52: I | C52: 70 | D52: 102 | F52: Vta.Tlmk Ph Heriberto Andrade | G52: 6/1//2026 | I52: 1438 | J52: =J51+I52-H52 -> 20103.76
A53: 46030 | B53: I | C53: 70 | D53: 102 | F53: Vta.Tlmk Ph Ismael Arias | G53: 46007 | I53: 4677 | J53: =J52+I53-H53 -> 24780.76
A54: 46030 | B54: I | C54: 70 | D54: 102 | F54: Vta.Tlmk Ph Armando Rea | G54: 46001 | I54: 19000 | J54: =J53+I54-H54 -> 43780.76
A55: 46030 | B55: I | C55: 70 | D55: 102 | F55: Vta.Tlmk Ph Farfan Vazquez | G55: 45988 | I55: 61350 | J55: =J54+I55-H55 -> 105130.76
A56: 46030 | B56: TE | D56: - | F56: TRASPASO ENTRE CTAS 7744 | H56: 100000 | J56: =J55+I56-H56 -> 5130.76
A57: 46031 | B57: I | C57: 70 | D57: 102 | F57: Vta.Tlmk Ph Chava Valadez | G57: 45663 | I57: 70.5 | J57: =J56+I57-H57 -> 5201.26
A58: 46031 | B58: I | C58: 70 | D58: 102 | F58: Vta.Tlmk Ph Armando Rea | G58: 46029 | I58: 224 | J58: =J57+I58-H58 -> 5425.26
A59: 46031 | B59: I | C59: 70 | D59: 102 | F59: Vta.Tlmk Ph Andrea Angelica | G59: 46029 | I59: 3003 | J59: =J58+I59-H59 -> 8428.26
A60: 46031 | B60: I | C60: 70 | D60: 102 | F60: Vta.Tlmk Ph Andrea Angelica | G60: 46029 | I60: 495 | J60: =J59+I60-H60 -> 8923.26
A61: 46031 | B61: I | C61: 70 | D61: 102 | F61: Vta.tlmk Ph Antonio Meza | G61: 46028 | I61: 74196 | J61: =J60+I61-H61 -> 83119.26
A62: 46031 | B62: I | C62: 70 | D62: 102 | F62: Vta.Tlmk Ph Manuel Rios | G62: 46002 | I62: 6641.47 | J62: =J61+I62-H62 -> 89760.73
A63: 46031 | B63: I | C63: 70 | D63: 102 | F63: Vta.Tlmk Ph Manuel Rios | G63: 46009 | I63: 8449.16 | J63: =J62+I63-H63 -> 98209.89
A64: 46034 | B64: I | C64: 70 | D64: 102 | F64: Vta.Tlmk Ph Delia Govea | G64: 46002 | I64: 28910 | J64: =J63+I64-H64 -> 127119.89
A65: 46034 | B65: I | C65: 70 | D65: 102 | F65: Vta.Tlmk Ph Ismael Rodriguez | G65: 45988 | I65: 19873 | J65: =J64+I65-H65 -> 146992.89
A66: 46034 | B66: I | C66: 70 | D66: 102 | F66: Vta.Tlmk Ph Miguel Angel Servin | G66: 46030 | I66: 2818 | J66: =J65+I66-H66 -> 149810.89
A67: 46034 | B67: I | C67: 70 | D67: 102 | F67: Vta.tlmk Ph Azucena Bravo | G67: 46030 | I67: 9867.5 | J67: =J66+I67-H67 -> 159678.39
A68: 46034 | B68: I | C68: 70 | D68: 102 | F68: Vta.Tlmk Ph Super Farmacia C | G68: 46030 | I68: 15535 | J68: =J67+I68-H68 -> 175213.39
... A77: 46034 | B77: I | C77: 70 | D77: 102 | F77: Vta.Tlmk Ph Andrea Angelica | G77: 45994 | I77: 5000 | J77: =J76+I77-H77 -> 377576.89
A78: 46034 | B78: C | C78: 50 | D78: - | E78: 5 | F78: Distribuidora de la Rosa | H78: 192235.49 | J78: =J77+I78-H78 -> 185341.4
A79: 46034 | B79: C | C79: 30 | D79: - | E79: 6 | F79: Comercializadora Dulcera de Abastos | H79: 184325.69 | J79: =J78+I79-H79 -> 1015.71
A80: 46036 | B80: I | C80: 70 | D80: 102 | F80: Vta.Tlmk Ph Andrea Angelica | G80: 45994 | I80: 1870 | J80: =J79+I80-H80 -> 2885.71
A81: 46036 | B81: I | C81: 70 | D81: 102 | F81: Vta.Tlmk Ph Gastos Tlmk | G81: 46035 | I81: 256 | J81: =J80+I81-H81 -> 3141.71
A82: 46036 | B82: I | C82: 70 | D82: 102 | F82: Vta.Tlmk Ph Carniceria Duran | G82: 46003 | I82: 150 | J82: =J81+I82-H82 -> 3291.71
A83: 46036 | B83: I | C83: 70 | D83: 102 | F83: Vta.Tlmk Ph Monica Mejia | G83: 45925 | I83: 2270 | J83: =J82+I83-H83 -> 5561.71
A84: 46036 | B84: I | C84: 70 | D84: 102 | F84: Vta.Tlmk Ph Lucas | G84: 46024 | I84: 2000 | J84: =J83+I84-H84 -> 7561.71
A85: 46036 | B85: I | C85: 70 | D85: 102 | F85: Vta.Tlmk Ph Alicia Hernandez | G85: 46007 | I85: 1900 | J85: =J84+I85-H85 -> 9461.71
A86: 46036 | B86: I | C86: 70 | D86: 102 | F86: Vta.Tlmk Ph Olivia Hernandez | G86: 46002 | I86: 3005 | J86: =J85+I86-H86 -> 12466.71
A87: 46036 | B87: I | C87: 70 | D87: 102 | F87: Vta.Tlmk Ph Abarrotes Guillen | G87: 45989 | I87: 3826 | J87: =J86+I87-H87 -> 16292.71
A88: 46036 | B88: I | C88: 70 | D88: 102 | F88: Vta.Tlmk Ph Jose Horacio | G88: 45978 | I88: 3780 | J88: =J87+I88-H88 -> 20072.71
A89: 46036 | B89: I | C89: 70 | D89: 102 | F89: Vta.Tlmk Ph Lourdes Encino | G89: 46034 | I89: 10062.84 | J89: =J88+I89-H89 -> 30135.55
A90: 46036 | B90: I | C90: 70 | D90: 102 | F90: Vta.Tlmk Ph Ma. Lourdes Encino | G90: 46034 | I90: 1848.7 | J90: =J89+I90-H90 -> 31984.25
A91: 46036 | B91: I | C91: 70 | D91: 102 | F91: Vta.Tlmk Ph Ma. Lourdes Encino | G91: 46034 | I91: 1239.8 | J91: =J90+I91-H91 -> 33224.05
... A98: 46036 | B98: I | C98: 70 | D98: 102 | F98: Vta.Tlmk Ph Maria Cristina L | G98: 46034 | I98: 4193 | J98: =J97+I98-H98 -> 71601.74
A99: 46036 | B99: I | C99: 70 | D99: 102 | F99: Vta.Tlmk Ph Mini Super | G99: 12//1/2026 | I99: 9953 | J99: =J98+I99-H99 -> 81554.74
A100: 46036 | B100: I | C100: 70 | D100: 102 | F100: Vta.Tlmk Ph Ricardo Aldana | G100: 46034 | I100: 6270 | J100: =J99+I100-H100 -> 87824.74
A101: 46036 | B101: I | C101: 70 | D101: 102 | F101: Vta.Tlmk Ph Himelda Aguilar | G101: 46034 | I101: 300 | J101: =J100+I101-H101 -> 88124.74
A102: 46036 | B102: I | C102: 70 | D102: 102 | F102: Vta.Tlmk Ph Sergio Ochoa | G102: 46034 | I102: 4372 | J102: =J101+I102-H102 -> 92496.74
A103: 46036 | B103: I | C103: 70 | D103: 102 | F103: Vta.Tlmk Ph Maria Xochitl | G103: 46034 | I103: 310 | J103: =J102+I103-H103 -> 92806.74
A104: 46036 | B104: I | C104: 70 | D104: 102 | F104: Vta.Tlmk Ph Cecilia Hernandez | G104: 46034 | I104: 2822 | J104: =J103+I104-H104 -> 95628.74
A105: 46036 | B105: TE | D105: - | F105: TRASPASO A BB 4166 | H105: 95000 | J105: =J104+I105-H105 -> 628.74
A106: 46037 | B106: I | C106: 70 | D106: 102 | F106: Vta.Tlmk Ph Armando Rea | G106: 46022 | I106: 10000 | J106: =J105+I106-H106 -> 10628.74
A107: 46037 | B107: I | C107: 70 | D107: 102 | F107: Vta.Tlmk Ph Margarita Sanchez | G107: 46007 | I107: 28803 | J107: =J106+I107-H107 -> 39431.74
A108: 46037 | B108: I | C108: 70 | D108: 102 | F108: Vta.Tlmk Ph Heriberto Andrade | G108: 46035 | I108: 1065 | J108: =J107+I108-H108 -> 40496.74
A109: 46037 | B109: I | C109: 70 | D109: 102 | F109: Vta.Tlmk Ph Patricia Mireles | G109: 46035 | I109: 5213 | J109: =J108+I109-H109 -> 45709.74
A110: 46037 | B110: TE | D110: - | F110: TRASPASO BBVA 5712 | H110: 45000 | J110: =J109+I110-H110 -> 709.74
A111: 46038 | B111: I | C111: 70 | D111: 102 | F111: Vta.Tlmk Ph Cinthya Estrada | G111: 45992 | I111: 8146 | J111: =J110+I111-H111 -> 8855.74
A112: 46038 | B112: I | C112: 10 | D112: 102 | F112: VTA PADRE HIDALGO | G112: 46034 | I112: 12.55 | J112: =J111+I112-H112 -> 8868.29
A113: 46038 | B113: I | C113: 10 | D113: 102 | F113: VTA PADRE HIDALGO | G113: 46034 | I113: 22.66 | J113: =J112+I113-H113 -> 8890.95
A114: 46038 | B114: I | C114: 10 | D114: 102 | F114: VTA PADRE HIDALGO | G114: 46038 | I114: 14.7 | J114: =J113+I114-H114 -> 8905.65
A115: 46038 | B115: I | C115: 10 | D115: 102 | F115: VTA PADRE HIDALGO | G115: 46031 | I115: 61 | J115: =J114+I115-H115 -> 8966.65
A116: 46038 | B116: I | D116: 102 | F116: Dep. Efectivo | I116: 343 | J116: =J115+I116-H116 -> 9309.65
A117: 46041 | B117: I | C117: 70 | D117: 102 | F117: Vta.Tlmk Ph Jose Alberto Saldaña | G117: 45672 | I117: 43398 | J117: =J116+I117-H117 -> 52707.65
A118: 46041 | B118: I | C118: 70 | D118: 102 | F118: Vta.Tlmk Ph Armando Rea | G118: 46036 | I118: 641 | J118: =J117+I118-H118 -> 53348.65
A119: 46041 | B119: I | C119: 70 | D119: 102 | F119: Vta.Tlmk Ph Maria Teresa Rocha | G119: 45974 | I119: 2208 | J119: =J118+I119-H119 -> 55556.65
A120: 46041 | B120: I | C120: 70 | D120: 102 | F120: Vta.Tlmk Ph Lucas | G120: 46024 | I120: 2000 | J120: =J119+I120-H120 -> 57556.65
A121: 46041 | B121: I | C121: 70 | D121: 102 | F121: Vta.Tlmk Ph Olivia Hernandez | G121: 46009 | I121: 2580 | J121: =J120+I121-H121 -> 60136.65
A122: 46041 | B122: I | C122: 70 | D122: 102 | F122: Vta.Tlmk Ph Plasticos Reyes | G122: 46003 | I122: 6404 | J122: =J121+I122-H122 -> 66540.65
A123: 46041 | B123: I | C123: 70 | D123: 102 | F123: Vta.Tlmk Ph Geraldine Laguna | G123: 45999 | I123: 7500 | J123: =J122+I123-H123 -> 74040.65
A124: 46041 | B124: I | C124: 70 | D124: 102 | F124: Vta.Tlmk Ph Delia Govea | G124: 46009 | I124: 38807 | J124: =J123+I124-H124 -> 112847.65
A125: 46041 | B125: I | C125: 70 | D125: 102 | F125: Vta.tlmk Ph Azucena Bravo | G125: 46037 | I125: 1682 | J125: =J124+I125-H125 -> 114529.65
A126: 46041 | B126: I | C126: 70 | D126: 102 | F126: Vta.Tlmk Ph Super Farmacia C | G126: 46037 | I126: 8756 | J126: =J125+I126-H126 -> 123285.65
A127: 46041 | B127: I | C127: 70 | D127: 102 | F127: Vta.Tlmk Ph Ismael Rodriguez | G127: 46002 | I127: 26901 | J127: =J126+I127-H127 -> 150186.65
A128: 46041 | B128: I | C128: 70 | D128: 102 | F128: Vta.Tlmk Ph Panaderia Machuca | G128: 46037 | I128: 1426 | J128: =J127+I128-H128 -> 151612.65
... A148: 46043 | B148: I | C148: 75 | D148: 102 | F148: Vta.Tlmk Canindo Karla Paulna | G148: 46000 | I148: 100000 | J148: =J147+I148-H148 -> 419621.65
...

Sheet BB 3660
A1: FECHA | B1: M | C1: S | D1: C | E1: # | F1: PROVEEDOR | G1: F VTA | H1: RETIRO | I1: DEPOSITO | J1: SALDO
A2: 46024 | B2: I | C2: 75 | D2: 102 | F2: Vta.Tlmk Canindo Teresa Manzo | G2: 258/11/2025 | I2: 36569.5 | J2: 37708.16 | K2: =J2+H2-I2 -> 1138.66
A3: 46024 | B3: TE | D3: - | F3: TRASPASO ENTRE CTAS 4166 | H3: 35000 | J3: =J2-H3+I3 -> 2708.16
A4: 46028 | B4: I | C4: 75 | D4: 102 | F4: VTA. TLMKT CANINDO JORGE ALBERTO MANZO | G4: 46025 | I4: 814.92 | J4: =J3-H4+I4 -> 3523.08
A5: 46028 | B5: I | C5: 75 | D5: 102 | F5: Vta.Tlmk Canindo Luis Ibarra | G5: 45989 | I5: 11497 | J5: =J4-H5+I5 -> 15020.08
A6: 46028 | B6: I | C6: 75 | D6: 102 | F6: Vta.Tlmk Canindo Cristina Noeli | G6: 46001 | I6: 21770 | J6: =J5-H6+I6 -> 36790.08
A7: 46028 | B7: I | C7: 75 | D7: 102 | F7: Vta.Tlmk Canindo Claudia Pantoja | G7: 45988 | I7: 9193 | J7: =J6-H7+I7 -> 45983.08
A8: 46028 | B8: I | C8: 75 | D8: 102 | F8: Vta.Tlmk Canindo Virginia Amezcua | G8: 46011 | I8: 16582 | J8: =J7-H8+I8 -> 62565.08
A9: 46028 | B9: I | C9: 75 | D9: 102 | F9: Vta.Tlmk Canindo Nicolas Morillon | G9: 45992 | I9: 22200 | J9: =J8-H9+I9 -> 84765.08
A10: 46028 | B10: I | C10: 75 | D10: 102 | F10: Vta.Tlmk Canindo Francisco Orozco | G10: 45962 | I10: 36600 | J10: =J9-H10+I10 -> 121365.08
A11: 46028 | B11: I | C11: 75 | D11: 102 | F11: Vta.Tlmk Canindo Alexis Amezcua | G11: 46001 | I11: 5862 | J11: =J10-H11+I11 -> 127227.08
A12: 46028 | B12: I | C12: 75 | D12: 102 | F12: Vta.Tlmk Canindo Beatriz guadalupe | G12: 46011 | I12: 8500 | J12: =J11-H12+I12 -> 135727.08
A13: 46028 | B13: I | C13: 75 | D13: 102 | F13: Vta.Tlmk Canindo Aurora Rios | G13: 45972 | I13: 34686 | J13: =J12-H13+I13 -> 170413.08
A14: 46028 | B14: I | C14: 75 | D14: 102 | F14: Vta.Tlmk Canindo Rafael Lopez | G14: 46001 | I14: 9129 | J14: =J13-H14+I14 -> 179542.08
A15: 46028 | B15: I | C15: 75 | D15: 102 | F15: VTA TLMKT CANINDO JAIME RAMIREZ | G15: 46027 | I15: 13236 | J15: =J14-H15+I15 -> 192778.08
A16: 46028 | B16: I | C16: 75 | D16: 102 | F16: VTA TLMKT CANINDO JUAN CARLOS DELGADO | G16: 05-01--26 | I16: 10429 | J16: =J15-H16+I16 -> 203207.08
A17: 46028 | B17: I | C17: 75 | D17: 102 | F17: VTA TLMKT CANINDO TANARI CERNA | G17: 46027 | I17: 2475 | J17: =J16-H17+I17 -> 205682.08
A18: 46028 | B18: TE | D18: - | F18: TRASPASO ENTRE CTAS 4166 | H18: 205000 | J18: =J17-H18+I18 -> 682.08
A19: 46030 | B19: I | C19: 75 | D19: 102 | F19: VTA. TLMKT CANINDO FELIPE DE JESUS GALVEZ | G19: 46028 | I19: 151870 | J19: =J18-H19+I19 -> 152552.08
A20: 46030 | B20: I | C20: 75 | D20: 102 | F20: VTA. TLMKT CANINDO J. GUADALUPE TORRES | G20: 46028 | I20: 4248 | J20: =J19-H20+I20 -> 156800.08
A21: 46030 | B21: I | C21: 75 | D21: 102 | F21: VTA. TLMKT CANINDO JAIME EDUARDO M. | G21: 46028 | I21: 4802.77 | J21: =J20-H21+I21 -> 161602.85
A22: 46030 | B22: I | C22: 75 | D22: 102 | F22: VTA TLMKT CANINDO JORGE ALBERTO MANZO | G22: 46029 | I22: 34862 | J22: =J21-H22+I22 -> 196464.85
A23: 46030 | B23: TE | D23: - | F23: TRASPASO ENTRE CTAS 854 | H23: 195000 | J23: =J22-H23+I23 -> 1464.85
A24: 46031 | B24: I | C24: 75 | D24: 102 | F24: VTA TLMKT CANINDO | G24: 46030 | I24: 11097 | J24: =J23-H24+I24 -> 12561.85
A25: 46032 | B25: I | C25: 70 | D25: 102 | F25: Vta.Tlmk Ph Fredy Arroyo | G25: 46020 | I25: 4384.64 | J25: =J24-H25+I25 -> 16946.49
A26: 46034 | B26: I | C26: 75 | D26: 102 | F26: VTA TLMKT CANINDO GERARDO DANIEL A. | G26: 46032 | I26: 8084 | J26: =J25-H26+I26 -> 25030.49
A27: 46034 | B27: I | C27: 75 | D27: 102 | F27: VTA TLMKT CANINDO MARIA GUADAUPE A. | G27: 46031 | I27: 1121 | J27: =J26-H27+I27 -> 26151.49
A28: 46034 | B28: I | C28: 75 | D28: 102 | F28: VTA TLMKT CANINDO LEONARDO IBARRA | G28: 46031 | I28: 14415 | J28: =J27-H28+I28 -> 40566.49
A29: 46034 | B29: I | C29: 75 | D29: 102 | F29: VTA TLMTK CANINDO OCTAVIO MORALES | G29: 46031 | I29: 10778.5 | J29: =J28-H29+I29 -> 51344.99
A30: 46034 | B30: TE | D30: - | F30: TRSAPASO ENTRE CTAS 854 | H30: 30000 | J30: =J29-H30+I30 -> 21344.99
A31: 46035 | B31: I | C31: 75 | D31: 102 | F31: Vta.Tlmk Canindo Luis Ibarra | G31: 46011 | I31: 46260 | J31: =J30-H31+I31 -> 67604.99
A32: 46035 | B32: I | C32: 75 | D32: 102 | F32: Vta.Tlmk Canindo Virginia Amezcua | G32: 46011 | I32: 18000 | J32: =J31-H32+I32 -> 85604.99
A33: 46035 | B33: I | C33: 75 | D33: 102 | F33: Vta.Tlmk Canindo Octaviano Morales | G33: 46011 | I33: 54308 | J33: =J32-H33+I33 -> 139912.99
A34: 46035 | B34: I | C34: 75 | D34: 102 | F34: Vta.Tlmk Canindo Beatriz guadalupe | G34: 46018 | I34: 6450 | J34: =J33-H34+I34 -> 146362.99
A35: 46035 | B35: I | C35: 75 | D35: 102 | F35: Vta.Tlmk Canindo Alberto Perez | G35: 46018 | I35: 3196 | J35: =J34-H35+I35 -> 149558.99
A36: 46035 | B36: I | C36: 75 | D36: 102 | F36: Vta.Tlmk Canindo Fernando Alberto | G36: 46008 | I36: 92005 | J36: =J35-H36+I36 -> 241563.99
A37: 46035 | B37: I | C37: 75 | D37: 102 | F37: Vta.Tlmk Canindo Nicolas Morillon | G37: 46001 | I37: 37915 | J37: =J36-H37+I37 -> 279478.99
A38: 46035 | B38: I | C38: 75 | D38: 102 | F38: Vta.Tlmk Canindo Guadalupe Torres | G38: 45964 | I38: 12500 | J38: =J37-H38+I38 -> 291978.99
A39: 46035 | B39: I | C39: 75 | D39: 102 | F39: Vta.Tlmk Canindo Guadalupe Torres | G39: 45964 | I39: 17500 | J39: =J38-H39+I39 -> 309478.99
A40: 46035 | B40: I | C40: 75 | D40: 102 | F40: Vta.Tlmk Canindo Francisco Orozco | G40: 45978 | I40: 24650 | J40: =J39-H40+I40 -> 334128.99
A41: 46035 | B41: I | C41: 75 | D41: 102 | F41: Vta.Tlmk Canindo Ladislao Galvez | G41: 45976 | I41: 10000 | J41: =J40-H41+I41 -> 344128.99
A42: 46035 | B42: I | C42: 75 | D42: 102 | F42: Vta.Tlmk Canindo Ladislao Galvez | G42: 45999 | I42: 18520 | J42: =J41-H42+I42 -> 362648.99
... A47: 46035 | B47: I | C47: 75 | D47: 102 | F47: Vta.Tlmk Canindo Teresa Manzo | G47: 46003 | I47: 47353.5 | J47: =J46-H47+I47 -> 447835.49
A48: 46035 | B48: TE | D48: - | F48: TRASPASO ENTRE CTAS 4166 | H48: 45000 | J48: =J47-H48+I48 -> 402835.49
A49: 46035 | B49: TE | D49: - | F49: TRASPASO A BBVA 5712 | H49: 400000 | J49: =J48-H49+I49 -> 2835.49
A50: 46035 | B50: G | D50: 612 | F50: Comision | H50: 0 | J50: =J49-H50+I50 -> 2835.49
A51: 46035 | B51: G | D51: 147 | F51: Iva | H51: 0 | J51: =J50-H51+I51 -> 2835.49
A52: 46036 | B52: I | C52: 75 | D52: 102 | F52: VTA TLMKT CANINDO LADISLAO GALVEZ A. | G52: 46035 | I52: 3137 | J52: =J51-H52+I52 -> 5972.49
A53: 46036 | B53: I | C53: 75 | D53: 102 | F53: VTA TLMKT CANINDO FELIPE DE JESUS G. | G53: 46035 | I53: 30882 | J53: =J52-H53+I53 -> 36854.49
A54: 46036 | B54: I | C54: 70 | D54: 102 | F54: Vta.Tlmk Ph Jousi Vanesa | G54: 46021 | I54: 18869.5 | J54: =J53-H54+I54 -> 55723.99
A55: 46036 | B55: I | C55: 70 | D55: 102 | F55: Vta.Tlmk Ph Jousi Vanesa | G55: 46028 | I55: 18058 | J55: =J54-H55+I55 -> 73781.99
A56: 46036 | B56: TE | D56: - | F56: TRASPASO ENTRE CTAS 4166 | H56: 70000 | J56: =J55-H56+I56 -> 3781.99
A57: 46037 | B57: I | C57: 75 | D57: 102 | F57: Vta.Tlmk Canindo Ramiro M | G57: 46004 | I57: 34116 | J57: =J56-H57+I57 -> 37897.99
A58: 46037 | B58: I | C58: 75 | D58: 102 | F58: Vta.Tlmk Canindo Octaviano Morales | G58: 46011 | I58: 2834 | J58: =J57-H58+I58 -> 40731.99
A59: 46037 | B59: I | C59: 75 | D59: 102 | F59: Vta.Tlmk Canindo Cirenia Margarita | G59: 45985 | I59: 7000 | J59: =J58-H59+I59 -> 47731.99
A60: 46037 | B60: I | C60: 75 | D60: 102 | F60: Vta.Tlmk Canindo Francisco Hernandez | G60: 45996 | I60: 40752 | J60: =J59-H60+I60 -> 88483.99
A61: 46037 | B61: TE | D61: - | F61: TRASPASO ENTRE CTAS 4166 | H61: 85000 | J61: =J60-H61+I61 -> 3483.99
A62: 46041 | B62: I | C62: 90 | D62: 102 | F62: VTA. YURECUARO | I62: 14695 | J62: =J61-H62+I62 -> 18178.99
A63: 46041 | B63: I | C63: 75 | D63: 102 | F63: Vta.Tlmk Canindo Cicindela | G63: 46039 | I63: 69170.91 | J63: =J62-H63+I63 -> 87349.9
A64: 46041 | B64: I | C64: 75 | D64: 102 | F64: Vta.Tlmk Canindo TEresa Manzo | G64: 46013 | I64: 146111.5 | J64: =J63-H64+I64 -> 233461.4
A65: 46041 | B65: I | C65: 75 | D65: 102 | F65: Vta.Tlmk Canindo Super Abarrotes | G65: 46041 | I65: 2382.37 | J65: =J64-H65+I65 -> 235843.77
A66: 46041 | B66: I | C66: 75 | D66: 102 | F66: Vta.Tlmk Canindo Super Abarrotes | G66: 46041 | I66: 3174.82 | J66: =J65-H66+I66 -> 239018.59
A67: 46041 | B67: I | C67: 75 | D67: 102 | F67: Vta.Tlmk Canindo Super Abarrotes | G67: 46041 | I67: 3673.02 | J67: =J66-H67+I67 -> 242691.61
A68: 46041 | B68: C | D68: 510 | E68: 1 | F68: Dulces Las Delicias | H68: 178983.65 | J68: =J67-H68+I68 -> 63707.96
A69: 46041 | B69: TE | D69: - | F69: TRASPASO A BBVA 5712 | H69: 60000 | J69: =J68-H69+I69 -> 3707.96
A70: 46041 | B70: G | D70: 612 | F70: Comision | H70: 0 | J70: =J69-H70+I70 -> 3707.96
A71: 46041 | B71: G | D71: 147 | F71: Iva | H71: 0 | J71: =J70-H71+I71 -> 3707.96
A72: 46042 | B72: I | C72: 75 | D72: 102 | F72: VENTAS TLMKT CANINDO LEONARDO IBARRA | G72: 46038 | I72: 10719.34 | J72: =J71-H72+I72 -> 14427.3
A73: 46042 | B73: I | C73: 75 | D73: 102 | F73: VENTAS TLMKT CANINDO MARIA GUADALUPE A. | G73: 46038 | I73: 1566.29 | J73: =J72-H73+I73 -> 15993.59
A74: 46043 | B74: I | C74: 75 | D74: 102 | F74: Vta.Tlmk Canindo Raunel Gama | G74: 45989 | I74: 27078 | J74: =J73-H74+I74 -> 43071.59
A75: 46043 | B75: I | C75: 75 | D75: 102 | F75: Vta.Tlmk Canindo Raunel Gama | G75: 45965 | I75: 97202 | J75: =J74-H75+I75 -> 140273.59
A76: 46043 | B76: I | C76: 75 | D76: 102 | F76: Vta.Tlmk Canindo Blanca Estela | G76: 45996 | I76: 35828 | J76: =J75-H76+I76 -> 176101.59
A77: 46043 | B77: I | C77: 75 | D77: 102 | F77: Vta.Tlmk Canindo Salvador Lopez | G77: 46008 | I77: 11367 | J77: =J76-H77+I77 -> 187468.59 | K77: RAFAEL LOPEZ ESTRADA
A78: 46043 | B78: I | C78: 75 | D78: 102 | F78: Vta.Tlmk Canindo Nicolas Morillon | G78: 46001 | I78: 10000 | J78: =J77-H78+I78 -> 197468.59
A79: 46043 | B79: I | C79: 75 | D79: 102 | F79: Vta.Tlmk Canindo Beatriz guadalupe | G79: 46018 | I79: 10000 | J79: =J78-H79+I79 -> 207468.59
A80: 46043 | B80: I | C80: 75 | D80: 102 | F80: VENTAS CANINDO TLMKT CANINDO SERGIO L. | G80: 46030 | I80: 55453.69 | J80: =J79-H80+I80 -> 262922.28
A81: 46043 | B81: I | C81: 75 | D81: 102 | F81: VENTAS CANINDO TLMKT CANINDO JUAN CARLOS | G81: 46039 | I81: 8984.98 | J81: =J80-H81+I81 -> 271907.26
A82: 46043 | B82: TE | D82: - | F82: TRASPASO A BBVA 5712 | H82: 270000 | J82: =J81-H82+I82 -> 1907.26
A83: 46043 | B83: G | D83: 612 | F83: Comision | H83: 0 | J83: =J82-H83+I83 -> 1907.26
A84: 46043 | B84: G | D84: 147 | F84: Iva | H84: 0 | J84: =J83-H84+I84 -> 1907.26
A85: 46044 | B85: I | C85: 40 | D85: 102 | F85: VENTAS 8 ESQUINAS | I85: 7593 | J85: =J84-H85+I85 -> 9500.26
A86: 46044 | B86: I | C86: 75 | D86: 102 | F86: VTA. TLMKT CANINDO JAIME EDUARDO M. | G86: 46041 | I86: 9455 | J86: =J85-H86+I86 -> 18955.26
A87: 46044 | B87: I | C87: 75 | D87: 102 | F87: VTA TLMKT CANINDO FELIPE DE JESUS G. | G87: 46041 | I87: 57870 | J87: =J86-H87+I87 -> 76825.26
A88: 46044 | B88: I | C88: 70 | D88: 102 | F88: Vta.Tlmk Ph Jousi Vanesa | G88: 46035 | I88: 8645.5 | J88: =J87-H88+I88 -> 85470.76
A89: 46044 | B89: I | C89: 70 | D89: 102 | F89: Vta.Tlmk Ph Veronica Ivette | G89: 46000 | I89: 10000 | J89: =J88-H89+I89 -> 95470.76
A90: 46044 | B90: TE | D90: - | F90: TRASPASO ENTRE CTAS 4166 | H90: 95000 | J90: =J89-H90+I90 -> 470.76
A91: 46046 | B91: I | C91: 75 | D91: 102 | F91: Vta.Tlmk Canindo Super Abarrotes | G91: 46045 | I91: 5027.75 | J91: =J90-H91+I91 -> 5498.51
A92: 46046 | B92: I | C92: 75 | D92: 102 | F92: Vta.Tlmk Canindo Super Abarrotes | G92: 46045 | I92: 2354.32 | J92: =J91-H92+I92 -> 7852.83
A93: 46046 | B93: I | C93: 75 | D93: 102 | F93: Vta.Tlmk Canindo Super Abarrotes | G93: 46045 | I93: 5911.25 | J93: =J92-H93+I93 -> 13764.08
A94: 46048 | B94: I | C94: 75 | D94: 102 | F94: VTA. TLMKT CANINDO RAFAEL LOPEZ ESTRADA | G94: 46043 | I94: 968.62 | J94: =J93-H94+I94 -> 14732.7
A95: 46048 | B95: I | C95: 75 | D95: 102 | F95: VTA. TLMKT CANINDO JORGE GONZALEZ G. | G95: 46044 | I95: 5471.26 | J95: =J94-H95+I95 -> 20203.96
A96: 46048 | B96: I | C96: 75 | D96: 102 | F96: VTA TLMKT CANINDO JORGE ALBERTO MANZO | G96: 46044 | I96: 30024.67 | J96: =J95-H96+I96 -> 50228.63
A97: 46048 | B97: I | C97: 75 | D97: 102 | F97: VTA TLMKT CANINDO KARINA ESCALERA B. | G97: 46044 | I97: 14155 | J97: =J96-H97+I97 -> 64383.63
A98: 46048 | B98: TE | D98: - | F98: TRASPASO ENTRE CTAS 4166 | H98: 60000 | J98: =J97-H98+I98 -> 4383.63
A99: 46049 | B99: I | C99: 75 | D99: 102 | F99: VTA TLMKT SERGIO L ESQUIVEL | G99: 46039 | I99: 38107.5 | J99: =J98-H99+I99 -> 42491.13
A100: 46049 | B100: I | C100: 75 | D100: 102 | F100: VTA TLMKT CANINDO JAIME RAMIREZ | G100: 46045 | I100: 10919.33 | J100: =J99-H100+I100 -> 53410.46
A101: 46049 | B101: TE | D101: - | F101: TRASPASO A SNTDR 2169 | H101: 50000 | J101: =J100-H101+I101 -> 3410.46
A102: 46049 | B102: G | D102: 612 | F102: Comision | H102: 0 | J102: =J101-H102+I102 -> 3410.46
A103: 46049 | B103: G | D103: 147 | F103: Iva | H103: 0 | J103: =J102-H103+I103 -> 3410.46
A104: 46051 | B104: I | C104: 75 | D104: 102 | F104: Vta.Tlmk Canindo Super Abarrotes | G104: 46049 | I104: 11787.13 | J104: =J103-H104+I104 -> 15197.59
...

Sheet BTE 7744
A1: FECHA | B1: M | C1: S | D1: C | E1: # | F1: PROVEEDOR | G1: F VTA | H1: RETIRO | I1: DEPOSITO | J1: SALDO
A2: 46024 | B2: I | C2: 30 | D2: 102 | F2: VENTAS MORELIA ABASTOS | G2: 46022 | I2: 11747.49 | J2: 45451.75 | K2: =J2+H2-I2 -> 33704.26
A3: 46024 | B3: G | C3: 30 | D3: 612 | F3: Comision | H3: 88.09 | J3: =J2-H3+I3 -> 45363.66
A4: 46024 | B4: G | C4: 30 | D4: 147 | F4: Iva | H4: 14.11 | J4: =J3-H4+I4 -> 45349.55
A5: 46024 | B5: I | C5: 30 | D5: 102 | F5: VENTAS MORELIA ABASTOS | G5: 46022 | I5: 18847.82 | J5: =J4-H5+I5 -> 64197.37
A6: 46024 | B6: G | C6: 30 | D6: 612 | F6: Comision | H6: 141.32 | J6: =J5-H6+I6 -> 64056.05
A7: 46024 | B7: G | C7: 30 | D7: 147 | F7: Iva | H7: 22.63 | J7: =J6-H7+I7 -> 64033.42
A8: 46024 | B8: I | C8: 10 | D8: 102 | F8: VENTAS PADRE HIDALGO | I8: 290.85 | J8: =J7-H8+I8 -> 64324.27
A9: 46024 | B9: G | D9: 612 | F9: Comision | H9: 9.92 | J9: =J8-H9+I9 -> 64314.35
A10: 46024 | B10: G | D10: 147 | F10: Iva | H10: 1.59 | J10: =J9-H10+I10 -> 64312.76
A11: 46024 | B11: I | C11: 10 | D11: 102 | F11: VENTAS PADRE HIDALGO | I11: 412.54 | J11: =J10-H11+I11 -> 64725.3
A12: 46024 | B12: G | D12: 612 | F12: Comision | H12: 3.1 | J12: =J11-H12+I12 -> 64722.2
A13: 46024 | B13: G | D13: 147 | F13: Iva | H13: 0.5 | J13: =J12-H13+I13 -> 64721.7
A14: 46024 | B14: TI | D14: - | F14: TRASPASO ENTRE CTAS 7133 | I14: 200000 | J14: =J13-H14+I14 -> 264721.7
A15: 46024 | B15: I | D15: 102 | F15: Dep. Practicaja | I15: 215700 | J15: =J14-H15+I15 -> 480421.7
A16: 46024 | B16: TI | D16: - | F16: TRASPASO DE BB 4166 | I16: 100000 | J16: =J15-H16+I16 -> 580421.7
A17: 46024 | B17: G | D17: 610 | E17: 1 | F17: Nomina 01 | H17: 29045 | J17: =J16-H17+I17 -> 551376.7
A18: 46024 | B18: G | C18: 90 | D18: 610 | E18: 2 | F18: Nomina 01 | H18: 8221.4 | J18: =J17-H18+I18 -> 543155.3
A19: 46024 | B19: G | D19: 610 | E19: 3 | F19: Nomina 01 | H19: 1717.6 | J19: =J18-H19+I19 -> 541437.7
A20: 46024 | B20: G | C20: 10 | D20: 610 | E20: 4 | F20: Nomina 01 | H20: 65098.2 | J20: =J19-H20+I20 -> 476339.5
A21: 46024 | B21: G | C21: 20 | D21: 610 | E21: 5 | F21: Nomina 01 | H21: 28296.2 | J21: =J20-H21+I21 -> 448043.3
A22: 46024 | B22: G | C22: 0 | D22: 610 | E22: 6 | F22: Nomina 01 | H22: 43745.2 | J22: =J21-H22+I22 -> 404298.1
A23: 46024 | B23: G | C23: 50 | D23: 610 | E23: 7 | F23: Nomina 01 | H23: 55317.8 | J23: =J22-H23+I23 -> 348980.3
A24: 46024 | B24: G | C24: 54 | D24: 610 | E24: 8 | F24: Nomina 01 | H24: 10742.8 | J24: =J23-H24+I24 -> 338237.5
A25: 46024 | B25: G | C25: 30 | D25: 610 | E25: 9 | F25: Nomina 01 | H25: 68393.2 | J25: =J24-H25+I25 -> 269844.3
A26: 46024 | B26: G | C26: 32 | D26: 610 | E26: 10 | F26: Nomina 01 | H26: 31170.8 | J26: =J25-H26+I26 -> 238673.5
A27: 46024 | B27: C | C27: 50 | D27: 510 | E27: 11 | F27: Distribuidora de la Rosa | H27: 227932.43 | J27: =J26-H27+I27 -> 10741.07
A28: 46024 | B28: I | C28: 70 | D28: 102 | F28: VTA TLMK PH COMERCIALIZADORA LORO LORA | G28: 46024 | I28: 2547.08 | J28: =J27-H28+I28 -> 13288.15
A29: 46024 | B29: G | C29: 72 | D29: 612 | F29: SEGUROS BANORTE SA DE CV GRUPO FINANCIERA CARGO COBRANZA DOMICILIADA | H29: 3790 | J29: =J28-H29+I29 -> 9498.15
A30: 46025 | B30: I | C30: 10 | D30: 102 | F30: VENTAS PADRE HIDALGO | I30: 202840 | J30: =J29-H30+I30 -> 212338.15
A31: 46027 | B31: I | C31: 90 | D31: 102 | F31: VTA. YURECUARO | G31: 46024 | I31: 263.2 | J31: =J30-H31+I31 -> 212601.35
A32: 46027 | B32: G | D32: 612 | F32: Comision | H32: 1.97 | J32: =J31-H32+I32 -> 212599.38
A33: 46027 | B33: G | D33: 147 | F33: Iva | H33: 0.32 | J33: =J32-H33+I33 -> 212599.06
A34: 46027 | B34: I | C34: 30 | D34: 102 | F34: VENTAS MORELIA ABASTOS | G34: 02 Y 03/01/2025 | I34: 6917.64 | J34: =J33-H34+I34 -> 219516.7
A35: 46027 | B35: G | C35: 30 | D35: 612 | F35: Comision | H35: 51.89 | J35: =J34-H35+I35 -> 219464.81
A36: 46027 | B36: G | C36: 30 | D36: 147 | F36: Iva | H36: 8.31 | J36: =J35-H36+I36 -> 219456.5
A37: 46027 | B37: I | C37: 30 | D37: 102 | F37: VENTAS MORELIA ABASTOS | G37: 02 Y 03/01/2025 | I37: 35172.81 | J37: =J36-H37+I37 -> 254629.31
A38: 46027 | B38: G | C38: 30 | D38: 612 | F38: Comision | H38: 296.94 | J38: =J37-H38+I38 -> 254332.37
A39: 46027 | B39: G | C39: 30 | D39: 147 | F39: Iva | H39: 47.53 | J39: =J38-H39+I39 -> 254284.84
A40: 46027 | B40: I | C40: 10 | D40: 102 | F40: VTA PADRE HIDALGO | G40: 46025 | I40: 106620 | J40: =J39-H40+I40 -> 360904.84
A41: 46027 | B41: I | C41: 10 | D41: 102 | F41: VTA PADRE HIDALGO | G41: 46027 | I41: 826.4 | J41: =J40-H41+I41 -> 361731.24
A42: 46027 | B42: TE | D42: - | F42: TRASPASO ENTRE CUENTAS 7133 | H42: 90000 | J42: =J41-H42+I42 -> 271731.24
A43: 46027 | B43: G | C43: 72 | D43: 147 | F43: PAGO DE IVA 087710424 | H43: 2618.2 | J43: =J42-H43+I43 -> 269113.04
A44: 46027 | B44: G | C44: 72 | D44: 612 | F44: PAGO DE CAPITAL 087710424 | H44: 83333.33 | J44: =J43-H44+I44 -> 185779.71
A45: 46027 | B45: G | C45: 72 | D45: 612 | F45: PAGO DE INTERESES 087710424 | H45: 16455.24 | J45: =J44-H45+I45 -> 169324.47
A46: 46027 | B46: G | C46: 72 | D46: 612 | F46: INTERESES NO REALES 087710424 | H46: 11064.44 | J46: =J45-H46+I46 -> 158260.03
A47: 46027 | B47: G | C47: 72 | D47: 147 | F47: PAGO DE IVA 089386050 | H47: 3723.87 | J47: =J46-H47+I47 -> 154536.16
A48: 46027 | B48: G | C48: 72 | D48: 612 | F48: PAGO DE CAPITAL 089386050 | H48: 110611.11 | J48: =J47-H48+I48 -> 43925.05
A49: 46027 | B49: G | C49: 72 | D49: 612 | F49: PAGO DE INTERESES 089386050 | H49: 23396.45 | J49: =J48-H49+I49 -> 20528.6
A50: 46027 | B50: G | C50: 72 | D50: 613 | F50: INTERESES NO REALES 089386050 | H50: 10698.69 | J50: =J49-H50+I50 -> 9829.91
A51: 46028 | B51: I | C51: 30 | D51: 102 | F51: VENTAS MORELIA ABASTOS | G51: 45662 | I51: 30381.3 | J51: =J50-H51+I51 -> 40211.21
A52: 46028 | B52: G | C52: 30 | D52: 612 | F52: Comision | H52: 227.86 | J52: =J51-H52+I52 -> 39983.35
A53: 46028 | B53: G | C53: 30 | D53: 147 | F53: Iva | H53: 36.46 | J53: =J52-H53+I53 -> 39946.89
A54: 46028 | B54: I | C54: 30 | D54: 102 | F54: VENTAS MORELIA ABASTOS | G54: 45662 | I54: 12749.59 | J54: =J53-H54+I54 -> 52696.48
A55: 46028 | B55: G | C55: 30 | D55: 612 | F55: Comision | H55: 95.62 | J55: =J54-H55+I55 -> 52600.86
A56: 46028 | B56: G | C56: 30 | D56: 147 | F56: Iva | H56: 15.3 | J56: =J55-H56+I56 -> 52585.56
A57: 46028 | B57: I | C57: 90 | D57: 102 | F57: VTA. YURECUARO | G57: 46027 | I57: 402.1 | J57: =J56-H57+I57 -> 52987.66
A58: 46028 | B58: G | D58: 612 | F58: Comision | H58: 3.02 | J58: =J57-H58+I58 -> 52984.64
A59: 46028 | B59: G | D59: 147 | F59: Iva | H59: 0.48 | J59: =J58-H59+I59 -> 52984.16
A60: 46028 | B60: I | C60: 10 | D60: 102 | F60: VENTAS PADRE HIDALGO | G60: 46027 | I60: 167000 | J60: =J59-H60+I60 -> 219984.16
A61: 46028 | B61: I | C61: 10 | D61: 102 | F61: VENTAS PADRE HIDALGO | G61: 46027 | I61: 55000 | J61: =J60-H61+I61 -> 274984.16
A62: 46028 | B62: TI | D62: - | F62: TRASPASO ENTRE CTAS 7133 | I62: 400000 | J62: =J61-H62+I62 -> 674984.16
A63: 46028 | B63: TE | D63: - | F63: TRASPASO A BBVA 5712 | H63: 670000 | J63: =J62-H63+I63 -> 4984.16
A64: 46028 | B64: I | C64: 70 | D64: 102 | F64: Vta.Tlmk Ph Miguel Angel Bribiesca | G64: 45989 | I64: 1875.2 | J64: =J63-H64+I64 -> 6859.36
A65: 46029 | B65: I | C65: 90 | D65: 102 | F65: VTA. YURECUARO | G65: 46028 | I65: 1896 | J65: =J64-H65+I65 -> 8755.36
A66: 46029 | B66: G | D66: 612 | F66: Comision | H66: 14.22 | J66: =J65-H66+I66 -> 8741.14
A67: 46029 | B67: G | D67: 147 | F67: Iva | H67: 2.28 | J67: =J66-H67+I67 -> 8738.86
A68: 46029 | B68: I | C68: 90 | D68: 102 | F68: VTA. YURECUARO | G68: 46028 | I68: 560.34 | J68: =J67-H68+I68 -> 9299.2
A69: 46029 | B69: G | D69: 612 | F69: Comision | H69: 4.2 | J69: =J68-H69+I69 -> 9295
A70: 46029 | B70: G | D70: 147 | F70: Iva | H70: 0.67 | J70: =J69-H70+I70 -> 9294.33
A71: 46029 | B71: I | C71: 30 | D71: 102 | F71: VENTAS MORELIA ABASTOS | G71: 45663 | I71: 19891.47 | J71: =J70-H71+I71 -> 29185.8
A72: 46029 | B72: G | D72: 612 | F72: Comision | H72: 149.2 | J72: =J71-H72+I72 -> 29036.6
A73: 46029 | B73: G | D73: 147 | F73: Iva | H73: 23.88 | J73: =J72-H73+I73 -> 29012.72
A74: 46029 | B74: I | C74: 30 | D74: 102 | F74: VENTAS MORELIA ABASTOS | G74: 45663 | I74: 14206.07 | J74: =J73-H74+I74 -> 43218.79
A75: 46029 | B75: G | D75: 612 | F75: Comision | H75: 106.55 | J75: =J74-H75+I75 -> 43112.24
A76: 46029 | B76: G | D76: 147 | F76: Iva | H76: 17.05 | J76: =J75-H76+I76 -> 43095.19
A77: 46029 | B77: I | C77: 10 | D77: 102 | F77: VTA TARJETA PH | G77: 46362 | I77: 179290 | J77: =J76-H77+I77 -> 222385.19
A78: 46029 | B78: I | C78: 10 | D78: 102 | F78: MAYRA HERNANDEZ GUZMAN | I78: 3000 | J78: =J77-H78+I78 -> 225385.19
A79: 46029 | B79: C | D79: 510 | E79: 12 | F79: TDC BTE -ABARROTES EL ZORRO | H79: 186436.91 | J79: =J78-H79+I79 -> 38948.28
A80: 46030 | B80: I | C80: 90 | D80: 102 | F80: VTA. YURECUARO | G80: 46029 | I80: 1973.51 | J80: =J79-H80+I80 -> 40921.79
A81: 46030 | B81: G | D81: 612 | F81: Comision | H81: 27.27 | J81: =J80-H81+I81 -> 40894.52
A82: 46030 | B82: G | D82: 147 | F82: Iva | H82: 4.36 | J82: =J81-H82+I82 -> 40890.16
A83: 46030 | B83: I | C83: 10 | D83: 102 | F83: VENTAS PADRE HIDALGO | I83: 20.1 | J83: =J82-H83+I83 -> 40910.26
A84: 46030 | B84: G | D84: 612 | F84: Comision | H84: 0.15 | J84: =J83-H84+I84 -> 40910.11
A85: 46030 | B85: G | D85: 147 | F85: Iva | H85: 0.02 | J85: =J84-H85+I85 -> 40910.09
A86: 46030 | B86: I | C86: 30 | D86: 102 | F86: VENTAS MORELIA ABASTOS | G86: 46029 | I86: 13353.23 | J86: =J85-H86+I86 -> 54263.32
A87: 46030 | B87: G | D87: 612 | F87: Comision | H87: 100.16 | J87: =J86-H87+I87 -> 54163.16
A88: 46030 | B88: G | D88: 147 | F88: Iva | H88: 16.01 | J88: =J87-H88+I88 -> 54147.15
A89: 46030 | B89: I | C89: 30 | D89: 102 | F89: VENTAS MORELIA ABASTOS | G89: 46029 | I89: 11810.02 | J89: =J88-H89+I89 -> 65957.17
A90: 46030 | B90: G | D90: 612 | F90: Comision | H90: 88.58 | J90: =J89-H90+I90 -> 65868.59
A91: 46030 | B91: G | D91: 147 | F91: Iva | H91: 14.17 | J91: =J90-H91+I91 -> 65854.42
A92: 46030 | B92: I | C92: 10 | D92: 102 | F92: VENTA PADRE HIDALGO | G92: 6706956 | I92: 70000 | J92: =J91-H92+I92 -> 135854.42
A93: 46030 | B93: I | C93: 10 | D93: 102 | F93: VENTA PADRE HIDALGO | G93: 46029 | I93: 92210 | J93: =J92-H93+I93 -> 228064.42
A94: 46031 | B94: I | C94: 90 | D94: 102 | F94: VTA. YURECUARO | G94: 46030 | I94: 1050.48 | J94: =J93-H94+I94 -> 229114.9
A95: 46031 | B95: G | D95: 612 | F95: Comision | H95: 7.88 | J95: =J94-H95+I95 -> 229107.02
A96: 46031 | B96: G | D96: 147 | F96: Iva | H96: 1.26 | J96: =J95-H96+I96 -> 229105.76
A97: 46031 | B97: I | C97: 90 | D97: 102 | F97: VTA. YURECUARO | G97: 46030 | I97: 191.71 | J97: =J96-H97+I97 -> 229297.47
A98: 46031 | B98: G | D98: 612 | F98: Comision | H98: 1.44 | J98: =J97-H98+I98 -> 229296.03
A99: 46031 | B99: G | D99: 147 | F99: Iva | H99: 0.23 | J99: =J98-H99+I99 -> 229295.8
A100: 46031 | B100: I | C100: 30 | D100: 102 | F100: VENTAS MORELIA ABASTOS | G100: 46030 | I100: 14610.59 | J100: =J99-H100+I100 -> 243906.39
...

Sheet BTE 7133
A1: FECHA | B1: M | C1: S | D1: C | E1: # | F1: PROVEEDOR | G1: F VTA | H1: RETIRO | I1: DEPOSITO | J1: SALDO
A2: 46024 | B2: I | C2: 50 | D2: 102 | F2: VENTAS CANINDO | G2: 46021 | I2: 70000 | J2: 73606.31 | K2: =J2+H2-I2 -> 3606.31
A3: 46024 | B3: I | C3: 50 | D3: 102 | F3: VENTAS CANINDO | G3: 46021 | I3: 790 | J3: =J2-H3+I3 -> 74396.31
A4: 46024 | B4: I | C4: 50 | D4: 102 | F4: VENTAS CANINDO | G4: 46022 | I4: 125790 | J4: =J3-H4+I4 -> 200186.31
A5: 46024 | B5: TE | D5: - | F5: TRASPASO ENTRE CTAS 7744 | H5: 200000 | J5: =J4-H5+I5 -> 186.31
A6: 46024 | B6: I | C6: 75 | D6: 102 | F6: Vta.Tlmk Canindo Super Abarrotes | G6: 46021 | I6: 14682.04 | J6: =J5-H6+I6 -> 14868.35
A7: 46024 | B7: I | C7: 75 | D7: 102 | F7: Vta.Tlmk Canindo Super Abarrotes | G7: 46021 | I7: 2626.16 | J7: =J6-H7+I7 -> 17494.51
A8: 46025 | B8: I | C8: 50 | D8: 102 | F8: VENTAS CANINDO | G8: 46022 | I8: 82600 | J8: =J7-H8+I8 -> 100094.51
A9: 46025 | B9: I | C9: 50 | D9: 102 | F9: VENTAS CANINDO | G9: 46024 | I9: 125690 | J9: =J8-H9+I9 -> 225784.51
A10: 46025 | B10: I | C10: 50 | D10: 102 | F10: VENTAS CANINDO | G10: 46024 | I10: 1050 | J10: =J9-H10+I10 -> 226834.51
A11: 46025 | B11: I | C11: 50 | D11: 102 | F11: VENTAS CANINDO | G11: 46024 | I11: 5310 | J11: =J10-H11+I11 -> 232144.51
A12: 46025 | B12: I | C12: 50 | D12: 102 | F12: VENTAS CANINDO | G12: 46024 | I12: 35000 | J12: =J11-H12+I12 -> 267144.51
A13: 46025 | B13: I | C13: 50 | D13: 102 | F13: VENTAS CANINDO | G13: 46024 | I13: 80330 | J13: =J12-H13+I13 -> 347474.51
A14: 46027 | B14: I | C14: 73 | D14: 102 | F14: VENTAS TLMKT MORELIA | I14: 172800 | J14: =J13-H14+I14 -> 520274.51
A15: 46027 | B15: I | C15: 50 | D15: 102 | F15: VENTAS CANINDO | G15: 46026 | I15: 36150 | J15: =J14-H15+I15 -> 556424.51
A16: 46027 | B16: TI | D16: - | F16: TRASPASO ENTRE CTAS 7744 | I16: 90000 | J16: =J15-H16+I16 -> 646424.51
A17: 46027 | B17: C | C17: 10 | D17: 510 | E17: 1 | F17: Distribuidora de la Rosa | H17: 640408.42 | J17: =J16-H17+I17 -> 6016.09
A18: 46028 | B18: I | C18: 50 | D18: 102 | F18: VENTAS CANINDO | G18: 46026 | I18: 25560 | J18: =J17-H18+I18 -> 31576.09
A19: 46028 | B19: I | C19: 50 | D19: 102 | F19: VENTAS CANINDO | G19: 46027 | I19: 295520 | J19: =J18-H19+I19 -> 327096.09
A20: 46028 | B20: I | C20: 50 | D20: 102 | F20: VENTAS CANINDO | G20: 46026 | I20: 3234 | J20: =J19-H20+I20 -> 330330.09
A21: 46028 | B21: I | C21: 50 | D21: 102 | F21: VENTAS CANINDO | G21: 46027 | I21: 5020 | J21: =J20-H21+I21 -> 335350.09
A22: 46028 | B22: I | C22: 75 | D22: 102 | F22: Vta.Tlmk Canindo Maria Leonidez | G22: 46021 | I22: 68172.18 | J22: =J21-H22+I22 -> 403522.27
A23: 46028 | B23: TE | D23: - | F23: TRASPASO ENTRE CTAS 7744 | H23: 400000 | J23: =J22-H23+I23 -> 3522.27
A24: 46029 | B24: I | C24: 50 | D24: 102 | F24: VENTAS CANINDO | G24: 46027 | I24: 26250 | J24: =J23-H24+I24 -> 29772.27
A25: 46029 | B25: I | C25: 50 | D25: 102 | F25: VENTAS CANINDO | G25: 46028 | I25: 71500 | J25: =J24-H25+I25 -> 101272.27
A26: 46029 | B26: I | C26: 50 | D26: 102 | F26: VENTAS CANINDO | G26: 46028 | I26: 81300 | J26: =J25-H26+I26 -> 182572.27 | M26: .
A27: 46029 | B27: I | C27: 50 | D27: 102 | F27: VENTAS CANINDO | G27: 46028 | I27: 37330 | J27: =J26-H27+I27 -> 219902.27
A28: 46029 | B28: I | C28: 75 | D28: 102 | F28: Vta.Tlmk Canindo Guadalupe Torres | G28: 45957 | I28: 42886 | J28: =J27-H28+I28 -> 262788.27
A29: 46029 | B29: I | C29: 75 | D29: 102 | F29: Vta.Tlmk Canindo Guadalupe Torres | G29: 45950 | I29: 38000 | J29: =J28-H29+I29 -> 300788.27
A30: 46029 | B30: G | C30: 71 | D30: 613 | E30: 2 | F30: TDC BANORTE -ML | H30: 1165.14 | J30: =J29-H30+I30 -> 299623.13
A31: 46029 | B31: G | C31: 72 | D31: 610 | E31: 3 | F31: TDC BANORTE -SEGUROS BANORTE | H31: 189 | J31: =J30-H31+I31 -> 299434.13
A32: 46029 | B32: C | D32: 510 | E32: 4 | F32: TDC BANORTE - ABARROTES EL ZORRO | H32: 56486.55 | J32: =J31-H32+I32 -> 242947.58
A33: 46029 | B33: G | C33: 54 | D33: 613 | E33: 5 | F33: TDC BANORTE -BARRADAS | H33: 14876.025 | J33: =J32-H33+I33 -> 228071.55
A34: 46029 | B34: TE | D34: - | F34: TRASPASO A BBVA 5712 | H34: 225000 | J34: =J33-H34+I34 -> 3071.555
A35: 46030 | B35: I | C35: 50 | D35: 102 | F35: VENTAS CANINDO | G35: 46028 | I35: 27120 | J35: =J34-H35+I35 -> 30191.555
A36: 46030 | B36: I | C36: 50 | D36: 102 | F36: VENTAS CANINDO | G36: 46029 | I36: 153550 | J36: =J35-H36+I36 -> 183741.55
A37: 46030 | B37: I | C37: 50 | D37: 102 | F37: VENTAS CANINDO | G37: 46028 | I37: 3811.5 | J37: =J36-H37+I37 -> 187553.05
A38: 46030 | B38: I | C38: 75 | D38: 102 | F38: Vta.Tlmk Canindo Francisco Hernandez | G38: 45975 | I38: 48000 | J38: =J37-H38+I38 -> 235553.05
A39: 46030 | B39: I | C39: 75 | D39: 102 | F39: Vta.Tlmk Canindo Arturo Reynoso | G39: 46015 | I39: 49080 | J39: =J38-H39+I39 -> 284633.05
A40: 46030 | B40: I | C40: 75 | D40: 102 | F40: Vta.Tlmk Canindo Super Abarrotes | G40: 46028 | I40: 2796.61 | J40: =J39-H40+I40 -> 287429.66
A41: 46030 | B41: I | C41: 75 | D41: 102 | F41: Vta.Tlmk Canindo Super Abarrotes | G41: 46028 | I41: 12775.16 | J41: =J40-H41+I41 -> 300204.83
A42: 46030 | B42: TE | D42: - | F42: TRASPASO A BBVA 5712 | H42: 300000 | J42: =J41-H42+I42 -> 204.825
A43: 46031 | B43: I | C43: 50 | D43: 102 | F43: VENTAS CANINDO | G43: 46029 | I43: 21380 | J43: =J42-H43+I43 -> 21584.825
A44: 46031 | B44: I | C44: 50 | D44: 102 | F44: VENTAS CANINDO | G44: 46030 | I44: 36500 | J44: =J43-H44+I44 -> 58084.825
A45: 46031 | B45: I | C45: 50 | D45: 102 | F45: VENTAS CANINDO | G45: 46030 | I45: 140490 | J45: =J44-H45+I45 -> 198574.83
A46: 46031 | B46: I | C46: 50 | D46: 102 | F46: VENTAS CANINDO | G46: 46030 | I46: 1670 | J46: =J45-H46+I46 -> 200244.83
A47: 46031 | B47: TE | D47: - | F47: TRASPASO ENTRE CTAS 7744 | H47: 200000 | J47: =J46-H47+I47 -> 244.825
A48: 46032 | B48: I | C48: 50 | D48: 102 | F48: VENTAS CANINDO | G48: 46030 | I48: 24580 | J48: =J47-H48+I48 -> 24824.825
A49: 46032 | B49: I | C49: 50 | D49: 102 | F49: VENTAS CANINDO | G49: 46031 | I49: 102500 | J49: =J48-H49+I49 -> 127324.82
A50: 46032 | B50: I | C50: 50 | D50: 102 | F50: VENTAS CANINDO | G50: 46031 | I50: 21600 | J50: =J49-H50+I50 -> 148924.83
A51: 46032 | B51: I | C51: 50 | D51: 102 | F51: VENTAS CANINDO | G51: 46031 | I51: 230 | J51: =J50-H51+I51 -> 149154.83
A52: 46032 | B52: I | C52: 50 | D52: 102 | F52: VENTAS CANINDO | G52: 46025 | I52: 1100 | J52: =J51-H52+I52 -> 150254.83
A53: 46034 | B53: I | C53: 50 | D53: 102 | F53: VENTAS CANINDO | G53: 46031 | I53: 35000 | J53: =J52-H53+I53 -> 185254.83
A54: 46034 | B54: I | C54: 50 | D54: 102 | F54: VENTAS CANINDO | G54: 46031 | I54: 19180 | J54: =J53-H54+I54 -> 204434.83
A55: 46034 | B55: I | C55: 50 | D55: 102 | F55: VENTAS CANINDO | G55: 46032 | I55: 225420 | J55: =J54-H55+I55 -> 429854.83
A56: 46034 | B56: I | C56: 50 | D56: 102 | F56: VENTAS CANINDO | G56: 46033 | I56: 17410 | J56: =J55-H56+I56 -> 447264.83
A57: 46034 | B57: I | C57: 50 | D57: 102 | F57: VENTAS CANINDO | G57: 46033 | I57: 3530 | J57: =J56-H57+I57 -> 450794.83
A58: 46034 | B58: I | C58: 50 | D58: 102 | F58: VENTAS CANINDO | G58: 46033 | I58: 2220 | J58: =J57-H58+I58 -> 453014.83
A59: 46034 | B59: I | C59: 75 | D59: 102 | F59: Vta.Tlmk Canindo Maria Martha | G59: 45985 | I59: 20487 | J59: =J58-H59+I59 -> 473501.83
... A65: 46034 | B65: I | C65: 75 | D65: 102 | F65: Vta.Tlmk Canindo Yolanda Barragan | G65: 45999 | I65: 7891 | J65: =J64-H65+I65 -> 606168.82
A66: 46034 | B66: TI | D66: - | F66: TRASPASO ENTRE CTAS 7744 | I66: 100000 | J66: =J65-H66+I66 -> 706168.82
A67: 46034 | B67: TI | D67: - | F67: TRASPASO ENTRE CTAS 7744 | I67: 20000 | J67: =J66-H67+I67 -> 726168.82
A68: 46034 | B68: C | C68: 30 | D68: 510 | E68: 6 | F68: Distribuidora de la Rosa Sa de Cv | H68: 704211.16 | J68: =J67-H68+I68 -> 21957.665
A69: 46035 | B69: I | C69: 50 | D69: 102 | F69: VENTAS CANINDO | G69: 46033 | I69: 33120 | J69: =J68-H69+I69 -> 55077.665
A70: 46035 | B70: I | C70: 50 | D70: 102 | F70: VENTAS CANINDO | G70: 46034 | I70: 127690 | J70: =J69-H70+I70 -> 182767.67
A71: 46035 | B71: I | C71: 50 | D71: 102 | F71: VENTAS CANINDO | G71: 46033 | I71: 5098.5 | J71: =J70-H71+I71 -> 187866.17
A72: 46036 | B72: I | C72: 50 | D72: 102 | F72: VENTAS CANINDO | G72: 46034 | I72: 34040 | J72: =J71-H72+I72 -> 221906.17
A73: 46036 | B73: I | C73: 50 | D73: 102 | F73: VENTAS CANINDO | G73: 46034 | I73: 1500 | J73: =J72-H73+I73 -> 223406.17
A74: 46036 | B74: I | C74: 50 | D74: 102 | F74: VENTAS CANINDO | G74: 46035 | I74: 97610 | J74: =J73-H74+I74 -> 321016.16
A75: 46036 | B75: I | C75: 50 | D75: 102 | F75: VENTAS CANINDO | G75: 46035 | I75: 1529 | J75: =J74-H75+I75 -> 322545.16
A76: 46036 | B76: C | C76: 0 | D76: 510 | E76: 7 | F76: Dart de Mexico | H76: 247622.62 | J76: =J75-H76+I76 -> 74922.545
A77: 46036 | B77: C | C77: 50 | D77: 510 | E77: 8 | F77: Embotelladora Aga del Centro | H77: 9327 | J77: =J76-H77+I77 -> 65595.545
A78: 46036 | B78: C | C78: 42 | D78: 510 | E78: 9 | F78: Embotelladora Aga del Centro | H78: 24590 | J78: =J77-H78+I78 -> 41005.545
A79: 46036 | B79: C | C79: 10 | D79: 510 | E79: 10 | F79: Embotelladora Aga del Centro | H79: 13946 | J79: =J78-H79+I79 -> 27059.545
A80: 46036 | B80: C | C80: 40 | D80: 510 | E80: 11 | F80: Embotelladora Aga del Centro | H80: 15146 | J80: =J79-H80+I80 -> 11913.545
A81: 46036 | B81: C | C81: 0 | D81: 510 | E81: 12 | F81: Enrique Villegas Manrique | H81: 10040.07 | J81: =J80-H81+I81 -> 1873.475
A82: 46036 | B82: I | C82: 75 | D82: 102 | F82: Vta.Tlmk Canindo Nicolas Morillon | G82: 45992 | I82: 1000 | J82: =J81-H82+I82 -> 2873.475
A83: 46037 | B83: I | C83: 50 | D83: 102 | F83: VENTAS CANINDO | G83: 46035 | I83: 36040 | J83: =J82-H83+I83 -> 38913.475
A84: 46037 | B84: I | C84: 50 | D84: 102 | F84: VENTAS CANINDO | G84: 46036 | I84: 103430 | J84: =J83-H84+I84 -> 142343.48
A85: 46037 | B85: I | C85: 75 | D85: 102 | F85: Vta.Tlmk Canindo Julio Cesar J | G85: 46008 | I85: 24127 | J85: =J84-H85+I85 -> 166470.48
A86: 46037 | B86: I | C86: 50 | D86: 102 | F86: VENTAS CANINDO | G86: 46035 | I86: 2111 | J86: =J85-H86+I86 -> 168581.48
A87: 46037 | B87: I | C87: 75 | D87: 102 | F87: Vta.Tlmk Canindo Omar Daniel | G87: 46015 | I87: 2800 | J87: =J86-H87+I87 -> 171381.48
A88: 46037 | B88: I | C88: 75 | D88: 102 | F88: Vta.Tlmk Canindo Francisco Prado | G88: 46017 | I88: 64780 | J88: =J87-H88+I88 -> 236161.48
A89: 46037 | B89: I | C89: 75 | D89: 102 | F89: Vta.Tlmk Canindo Francisco Hernandez | G89: 45999 | I89: 12947 | J89: =J88-H89+I89 -> 249108.48
A90: 46037 | B90: I | C90: 75 | D90: 102 | F90: Vta.Tlmk Canindo Alberto perez | G90: 46018 | I90: 2000 | J90: =J89-H90+I90 -> 251108.48
A91: 46037 | B91: C | C91: 0 | D91: 510 | E91: 13 | F91: DART DE MEXICO, S DE RL DE CV | H91: 18035.8 | J91: =J90-H91+I91 -> 233072.67
A92: 46037 | B92: C | C92: 29 | D92: 613 | E92: 14 | F92: MTS Tours Travel SA de Cv | H92: 14160 | J92: =J91-H92+I92 -> 218912.67
A93: 46037 | B93: C | C93: 12 | D93: 613 | E93: 15 | F93: Carro Motriz Diesel | H93: 2789.79 | J93: =J92-H93+I93 -> 216122.89
A94: 46038 | B94: I | C94: 50 | D94: 102 | F94: VENTAS CANINDO | G94: 46036 | I94: 27850 | J94: =J93-H94+I94 -> 243972.89
A95: 46038 | B95: I | C95: 75 | D95: 102 | F95: Vta.Tlmk Canindo Nicolas Morillon | G95: 46001 | I95: 1000 | J95: =J94-H95+I95 -> 244972.89
A96: 46038 | B96: I | C96: 75 | D96: 102 | F96: Vta.Tlmk Canindo Alberto perez | G96: 46029 | I96: 5896 | J96: =J95-H96+I96 -> 250868.89
A97: 46038 | B97: I | C97: 75 | D97: 102 | F97: Vta.Tlmk Canindo Francisco Orozco | G97: 45978 | I97: 24 | J97: =J96-H97+I97 -> 250892.89
A98: 46038 | B98: I | C98: 75 | D98: 102 | F98: Vta.Tlmk Canindo Nicolas Morillon | G98: 46001 | I98: 16 | J98: =J97-H98+I98 -> 250908.89
A99: 46038 | B99: I | C99: 75 | D99: 102 | F99: Vta.Tlmk Canindo Beatriz Guadalupe | G99: 46018 | I99: 8 | J99: =J98-H99+I99 -> 250916.89
A100: 46038 | B100: I | C100: 50 | D100: 102 | F100: VENTAS CANINDO | G100: 46037 | I100: 142440 | J100: =J99-H100+I100 -> 393356.89
A101: 46038 | B101: I | C101: 50 | D101: 102 | F101: VENTAS CANINDO | G101: 46036 | I101: 2075.5 | J101: =J100-H101+I101 -> 395432.39
A102: 46038 | B102: TE | D102: - | F102: TRASPASO ENTRE CTAS 7744 | H102: 300000 | J102: =J101-H102+I102 -> 95432.385
A103: 46038 | B103: I | C103: 75 | D103: 102 | F103: Vta.Tlmk Canindo Maria Leonidez | G103: 46028 | I103: 20862 | J103: =J102-H103+I103 -> 116294.38
A104: 46038 | B104: I | C104: 75 | D104: 102 | F104: Vta.Tlmk Canindo Miguel Galvez A | G104: 46007 | I104: 49438.26 | J104: =J103-H104+I104 -> 165732.64
A105: 46038 | B105: TE | D105: - | F105: TRSPASO A BBVA 5712 | H105: 165000 | J105: =J104-H105+I105 -> 732.645
...

Sheet BBVA 5712
A1: FECHA | B1: M | C1: S | D1: C | E1: # | F1: PROVEEDOR | G1: F VTA | H1: RETIRO | I1: DEPOSITO | J1: SALDO
A2: 46024 | B2: G | C2: 12 | D2: 613 | E2: 1 | F2: Toyocamiones SA de Cv | H2: 19400 | J2: 17877.06 | K2: =J2+H2-I2 -> 37277.06
A3: 46024 | B3: I | C3: 10 | D3: 102 | F3: VENTA PADRE HIDALGO | G3: 46024 | I3: 6719.65 | J3: =J2-H3+I3 -> 24596.71
A4: 46024 | B4: I | C4: 73 | D4: 102 | F4: Vta.Tlmk Morelia Bernaldo Garcia | G4: 46011 | I4: 3350 | J4: =J3-H4+I4 -> 27946.71
A5: 46024 | B5: I | C5: 10 | D5: 102 | F5: VENTA PADRE HIDALGO | G5: 46024 | I5: 6677.85 | J5: =J4-H5+I5 -> 34624.56
A6: 46024 | B6: C | C6: 50 | D6: 510 | E6: 2 | F6: Jose Alfonso Gonzalez | H6: 4557.6 | J6: =J5-H6+I6 -> 30066.96
A7: 46024 | B7: G | C7: 10 | D7: 610 | E7: 3 | F7: CFE | H7: 16551 | J7: =J6-H7+I7 -> 13515.96
A8: 46027 | B8: I | C8: 73 | D8: 102 | F8: Vta.Tlmk Morelia Leonila Ledezma | G8: 46021 | I8: 2639.39 | J8: =J7-H8+I8 -> 16155.35
A9: 46027 | B9: I | C9: 10 | D9: 102 | F9: VENTA PADRE HIDALGO | G9: 46027 | I9: 870 | J9: =J8-H9+I9 -> 17025.35
A10: 46027 | B10: I | C10: 10 | D10: 102 | F10: VENTA PADRE HIDALGO | G10: 46027 | I10: 870 | J10: =J9-H10+I10 -> 17895.35
A11: 46027 | B11: I | C11: 30 | D11: 102 | F11: VENTAS MORELIA ABASTOS Tlmk M | G11: 45662 | I11: 4418.23 | J11: =J10-H11+I11 -> 22313.58
A12: 46027 | B12: S | C12: 54 | D12: 102 | F12: VENTA ZAMORA CENTRO | I12: 4640 | J12: =J11-H12+I12 -> 26953.58 | L12: devolucion lilia edith
A13: 46027 | B13: I | C13: 40 | D13: 102 | F13: vtas 8 esquinas | G13: 46027 | I13: 1102 | J13: =J12-H13+I13 -> 28055.58
A14: 46027 | B14: TI | D14: - | F14: TRASPASO DE STDR | I14: 700000 | J14: =J13-H14+I14 -> 728055.58
A15: 46027 | B15: TI | D15: - | F15: TRASPASO DE STDR | I15: 150000 | J15: =J14-H15+I15 -> 878055.58
A16: 46027 | B16: C | C16: 30 | D16: 510 | E16: 4 | F16: Alcaruzz S de RL de CV | H16: 89002.58 | J16: =J15-H16+I16 -> 789053
A17: 46027 | B17: C | C17: 50 | D17: 510 | E17: 5 | F17: Alcaruzz S de RL de CV | H17: 22951.64 | J17: =J16-H17+I17 -> 766101.36
A18: 46027 | B18: C | C18: 10 | D18: 510 | E18: 6 | F18: Alcaruzz S de RL de CV | H18: 16978.2 | J18: =J17-H18+I18 -> 749123.16
A19: 46027 | B19: C | C19: 0 | D19: 510 | E19: 7 | F19: Azteca Confiteria | H19: 39972.53 | J19: =J18-H19+I19 -> 709150.63
A20: 46027 | B20: C | C20: 30 | D20: 510 | E20: 8 | F20: Comercializadora Galfra | H20: 37598.04 | J20: =J19-H20+I20 -> 671552.59
A21: 46027 | B21: C | C21: 0 | D21: 510 | E21: 9 | F21: Conservas La Costeña | H21: 308816.73 | J21: =J20-H21+I21 -> 362735.86
A22: 46027 | B22: C | C22: 0 | D22: 510 | E22: 10 | F22: Brenda Jaqueline Avila | H22: 64037.79 | J22: =J21-H22+I22 -> 298698.07
A23: 46027 | B23: G | C23: 1 | D23: 613 | E23: 11 | F23: Gustavo Rodriguez Ramirez | H23: 134649.93 | J23: =J22-H23+I23 -> 164048.14
A24: 46027 | B24: G | C24: 72 | D24: 612 | F24: STM FINANCIAL S.A.P.13663/FFS1512071T1 | H24: 27072.95 | J24: =J23-H24+I24 -> 136975.19
A25: 46028 | B25: I | C25: 90 | D25: 102 | F25: VTA. YURECUARO | G25: 46024 | I25: 28070 | J25: =J24-H25+I25 -> 165045.19
A26: 46028 | B26: I | C26: 10 | D26: 102 | F26: VENTAS PADRE HIDALGO | I26: 28483 | J26: =J25-H26+I26 -> 193528.19
A27: 46028 | B27: I | C27: 10 | D27: 102 | F27: VENTAS PADRE HIDALGO | I27: 34940 | J27: =J26-H27+I27 -> 228468.19
A28: 46028 | B28: I | C28: 90 | D28: 102 | F28: VTA. YURECUARO | G28: 46026 | I28: 17755 | J28: =J27-H28+I28 -> 246223.19
A29: 46028 | B29: I | C29: 90 | D29: 102 | F29: VTA. YURECUARO | G29: 46025 | I29: 16691 | J29: =J28-H29+I29 -> 262914.19
A30: 46028 | B30: I | C30: 10 | D30: 102 | F30: VENTAS PADRE HIDALGO | I30: 19320 | J30: =J29-H30+I30 -> 282234.19
A31: 46028 | B31: I | C31: 10 | D31: 102 | F31: VENTAS PADRE HIDALGO | I31: 4718 | J31: =J30-H31+I31 -> 286952.19
A32: 46028 | B32: TI | D32: - | F32: TRASPASO DE BB | I32: 700000 | J32: =J31-H32+I32 -> 986952.19
A33: 46028 | B33: TI | D33: - | F33: TRASPASO DE SNTDR | I33: 495000 | J33: =J32-H33+I33 -> 1481952.2
A34: 46028 | B34: TI | D34: - | F34: TRASPASO DE BTE 7744 | I34: 670000 | J34: =J33-H34+I34 -> 2151952.2
A35: 46028 | B35: C | C35: 0 | D35: 510 | E35: 13 | F35: Comercializadora Saramel | H35: 301904.75 | J35: =J34-H35+I35 -> 1850047.4
A36: 46028 | B36: C | C36: 50 | D36: 501 | E36: 14 | F36: Tecnica Mexicana de Alimentacion | H36: 135674.31 | J36: =J35-H36+I36 -> 1714373.1
A37: 46028 | B37: I | C37: 10 | D37: 102 | F37: VENTAS PADRE HIDALGO | I37: 18500 | J37: =J36-H37+I37 -> 1732873.1
A38: 46028 | B38: I | C38: 10 | D38: 102 | F38: VENTAS PADRE HIDALGO | I38: 14688 | J38: =J37-H38+I38 -> 1747561.1
A39: 46029 | B39: G | C39: 72 | D39: 612 | F39: SERV BANCA INTERNET/SERV BCA IN 01-31 | H39: 250 | J39: =J38-H39+I39 -> 1747311.1
A40: 46029 | B40: G | C40: 72 | D40: 612 | F40: SERV BANCA INTERNET/OPS SERV BCA IN 01-31 | H40: 1202.5 | J40: =J39-H40+I40 -> 1746108.6
A41: 46029 | B41: G | C41: 72 | D41: 147 | F41: IVA | H41: 232.4 | J41: =J40-H41+I41 -> 1745876.2
A42: 46029 | B42: I | C42: 70 | D42: 102 | F42: Vta.Tlmk Ph Rosa Lopez | G42: 46021 | I42: 13235.65 | J42: =J41-H42+I42 -> 1759111.9
A43: 46029 | B43: I | C43: 70 | D43: 102 | F43: Vta.tlmk Ph Blanca Andrea | G43: 45981 | I43: 100000 | J43: =J42-H43+I43 -> 1859111.9
A44: 46029 | B44: I | C44: 10 | D44: 102 | F44: VENTAS PADRE HIDALGO | I44: 56986.51 | J44: =J43-H44+I44 -> 1916098.4
A45: 46029 | B45: I | C45: 10 | D45: 102 | F45: VENTAS PADRE HIDALGO | I45: 11225.53 | J45: =J44-H45+I45 -> 1927323.9
A46: 46029 | B46: TI | D46: - | F46: TRASPASO DE BTE | I46: 225000 | J46: =J45-H46+I46 -> 2152323.9
A47: 46029 | B47: TI | D47: - | F47: TRASPASO DE BTE | I47: 100000 | J47: =J46-H47+I47 -> 2252323.9
A48: 46029 | B48: TI | D48: - | F48: TRASPASO DE SNTDR 1604 | I48: 45000 | J48: =J47-H48+I48 -> 2297323.9
A49: 46029 | B49: TI | D49: - | F49: TRASPASO DE SNTDR 2169 | I49: 180000 | J49: =J48-H49+I49 -> 2477323.9
A50: 46029 | B50: C | C50: 30 | D50: 510 | E50: 15 | F50: Distribuidora de la Rosa | H50: 804263.39 | J50: =J49-H50+I50 -> 1673060.5
A51: 46029 | B51: C | C51: 10 | D51: 510 | E51: 16 | F51: Distribuidora de la Rosa | H51: 823044.92 | J51: =J50-H51+I51 -> 850015.61
A52: 46029 | B52: C | C52: 10 | D52: 510 | E52: 17 | F52: Distribuidora de la Rosa | H52: 621093.72 | J52: =J51-H52+I52 -> 228921.89
A53: 46029 | B53: C | C53: 30 | D53: 510 | E53: 18 | F53: Agroalimentos Santoyo | H53: 94306.74 | J53: =J52-H53+I53 -> 134615.15
A54: 46029 | B54: G | C54: 40 | D54: 610 | E54: 19 | F54: Enrique Garcia Leon | H54: 7568.36 | J54: =J53-H54+I54 -> 127046.79
A55: 46029 | B55: G | C55: 42 | D55: 610 | E55: 20 | F55: Jose Sotelo Llamas | H55: 16602.2 | J55: =J54-H55+I55 -> 110444.59
A56: 46029 | B56: G | C56: 10 | D56: 610 | E56: 21 | F56: Juan Carlos Saldaña Castillo | H56: 60262 | J56: =J55-H56+I56 -> 50182.59
A57: 46029 | B57: S | F57: Lilia Devolucion | H57: 4640 | J57: =J56-H57+I57 -> 45542.59
A58: 46029 | B58: I | C58: 70 | D58: 102 | F58: Vta.Tlmk Ph Eloy Monterrosas | G58: 45992 | I58: 11400 | J58: =J57-H58+I58 -> 56942.59
A59: 46030 | B59: C | C59: 10 | D59: 510 | E59: 23 | F59: Natural de Alimentos | H59: 2471.64 | J59: =J58-H59+I59 -> 54470.95
A60: 46030 | B60: I | C60: 70 | D60: 102 | F60: Vta.Tlmk Ph Gildardo Meza | G60: 45873 | I60: 2319 | J60: =J59-H60+I60 -> 56789.95
A61: 46030 | B61: TI | D61: - | F61: TRASPASO DE SNTDR | I61: 50000 | J61: =J60-H61+I61 -> 106789.95
A62: 46030 | B62: TI | D62: - | F62: TRASPASO DE BTE | I62: 300000 | J62: =J61-H62+I62 -> 406789.95
A63: 46030 | B63: TI | D63: - | F63: TRASPASO ENTRE CTAS 6586 | I63: 440000 | J63: =J62-H63+I63 -> 846789.95
A64: 46030 | B64: C | C64: 40 | D64: 510 | E64: 24 | F64: Distribuidora de la Rosa SA de CV | H64: 835874.98 | J64: =J63-H64+I64 -> 10914.97
A65: 46031 | B65: I | C65: 73 | D65: 102 | F65: Vta.Tlmk Morelia Marco Antonio M | G65: 45994 | I65: 28000 | J65: =J64-H65+I65 -> 38914.97
A66: 46031 | B66: ID | D66: - | F66: Dev Spei- Gustavo Rodriguez | I66: 92828.25 | J66: =J65-H66+I66 -> 131743.22
A67: 46031 | B67: TI | D67: - | F67: TRASPASO DE BB | I67: 250000 | J67: =J66-H67+I67 -> 381743.22
A68: 46031 | B68: G | C68: 30 | D68: 613 | E68: 25 | F68: Agelica Maria Rubio Lopez | H68: 1102 | J68: =J67-H68+I68 -> 380641.22
A69: 46031 | B69: G | C69: 12 | D69: 613 | E69: 26 | F69: Arrendamex | H69: 3229.44 | J69: =J68-H69+I69 -> 377411.78
A70: 46031 | B70: C | C70: 30 | D70: 510 | E70: 27 | F70: Sweets Dimension | H70: 334357.36 | J70: =J69-H70+I70 -> 43054.42
A71: 46031 | B71: I | D71: 102 | F71: Dep. Efectivo | I71: 0.01 | J71: =J70-H71+I71 -> 43054.43
A72: 46034 | B72: G | C72: 72 | D72: 612 | F72: PAGO FAMILIA SEGURA/P01356600JZB RECIBO NO.x | H72: 1565.51 | J72: =J71-H72+I72 -> 41488.92
A73: 46034 | B73: I | C73: 10 | D73: 102 | F73: VENTAS PADRE HIDALGO Tlmk Morelia | I73: 46827.78 | J73: =J72-H73+I73 -> 88316.7
A74: 46034 | B74: I | C74: 30 | D74: 102 | F74: VENTAS MORELIA ABASTOS | G74: 46034 | I74: 10329.14 | J74: =J73-H74+I74 -> 98645.84
A75: 46034 | B75: TI | D75: - | F75: TRASPASO DE SNTDR | I75: 95000 | J75: =J74-H75+I75 -> 193645.84
A76: 46034 | B76: I | C76: 70 | D76: 102 | F76: Vta.Tlmk Ph Eloy Monterrosas | G76: 46013 | I76: 20000 | J76: =J75-H76+I76 -> 213645.84
A77: 46034 | B77: I | C77: 70 | D77: 102 | F77: Vta.Tlmk Ph Eloy Monterrosas | G77: 46013 | I77: 11800 | J77: =J76-H77+I77 -> 225445.84
A78: 46034 | B78: I | C78: 70 | D78: 102 | F78: Vta.Tlmk Ph Eloy Monterrosas | G78: 46013 | I78: 2030 | J78: =J77-H78+I78 -> 227475.84
A79: 46034 | B79: I | C79: 70 | D79: 102 | F79: Vta.Tlmk Ph Cristobal Haro | G79: 46034 | I79: 7928.09 | J79: =J78-H79+I79 -> 235403.93
A80: 46035 | B80: G | C80: 72 | D80: 621 | F80: PAGO TARJETA DE CREDITO/99038502751682 DOMICILIACION | H80: 7500 | J80: =J79-H80+I80 -> 227903.93
A81: 46035 | B81: I | C81: 70 | D81: 102 | F81: Vta.tlmk Ph Blanca Andrea | G81: 45996 | I81: 30000 | J81: =J80-H81+I81 -> 257903.93
A82: 46035 | B82: I | C82: 90 | D82: 102 | F82: VTA. YURECUARO | G82: 46029 | I82: 16007 | J82: =J81-H82+I82 -> 273910.93
A83: 46035 | B83: I | C83: 90 | D83: 102 | F83: VTA. YURECUARO | G83: 46033 | I83: 16252 | J83: =J82-H83+I83 -> 290162.93
A84: 46035 | B84: I | C84: 90 | D84: 102 | F84: VTA. YURECUARO | G84: 6620395 | I84: 27480 | J84: =J83-H84+I84 -> 317642.93
A85: 46035 | B85: I | C85: 90 | D85: 102 | F85: VTA. YURECUARO | G85: 46034 | I85: 19594 | J85: =J84-H85+I85 -> 337236.93
A86: 46035 | B86: I | C86: 90 | D86: 102 | F86: VTA. YURECUARO | G86: 46031 | I86: 17499 | J86: =J85-H86+I86 -> 354735.93
A87: 46035 | B87: I | C87: 90 | D87: 102 | F87: VTA. YURECUARO | G87: 46032 | I87: 21580 | J87: =J86-H87+I87 -> 376315.93
A88: 46035 | B88: I | C88: 10 | D88: 102 | F88: VENTAS PADRE HIDALGO | I88: 18244.98 | J88: =J87-H88+I88 -> 394560.91
A89: 46035 | B89: TI | D89: - | F89: TRASPASO DE BB | I89: 400000 | J89: =J88-H89+I89 -> 794560.91
A90: 46035 | B90: TI | D90: - | F90: TRASPASO DE SNTDR | I90: 80000 | J90: =J89-H90+I90 -> 874560.91
A91: 46035 | B91: TI | D91: - | F91: TRASPASO DE SNTDR | I91: 400000 | J91: =J90-H91+I91 -> 1274560.9
A92: 46035 | B92: C | C92: 10 | D92: 510 | E92: 28 | F92: Ferrero de Mexico | H92: 4763.91 | J92: =J91-H92+I92 -> 1269797
A93: 46035 | B93: C | C93: 0 | D93: 510 | E93: 29 | F93: Effem Mexico Inc y Compañia | H93: 303192.89 | J93: =J92-H93+I93 -> 966604.11
A94: 46035 | B94: C | C94: 0 | D94: 510 | E94: 30 | F94: Effem Mexico Inc y Compañia | H94: 741142.29 | J94: =J93-H94+I94 -> 225461.82
A95: 46035 | B95: C | C95: 10 | D95: 510 | E95: 31 | F95: Effem Mexico Inc y Compañia | H95: 73857.54 | J95: =J94-H95+I95 -> 151604.28
A96: 46036 | B96: I | C96: 10 | D96: 102 | F96: VENTAS PADRE HIDALGO | I96: 20000 | J96: =J95-H96+I96 -> 171604.28
A97: 46036 | B97: G | C97: 54 | D97: 610 | E97: 33 | F97: Maria Guadalupe Anaya | H97: 2600 | J97: =J96-H97+I97 -> 169004.28
A98: 46036 | B98: TI | D98: - | F98: TRASPASO DE SNTDR 1621 | I98: 440000 | J98: =J97-H98+I98 -> 609004.28
A99: 46036 | B99: C | C99: 0 | D99: 510 | E99: 34 | F99: Comercializadora Eloro SA de Cv | H99: 109064.61 | J99: =J98-H99+I99 -> 499939.67
A100: 46036 | B100: C | C100: 0 | D100: 510 | E100: 35 | F100: Israel Rodriguez Gomez | H100: 118459.8 | J100: =J99-H100+I100 -> 381479.87
...

Sheet BBVA 6586
A1: FECHA | B1: M | C1: S | D1: C | E1: # | F1: PROVEEDOR | G1: F VTA | H1: RETIRO | I1: DEPOSITO | J1: SALDO
A2: 46024 | B2: I | C2: 75 | D2: 102 | F2: vta tlmkt canindo alfonso arroyo | I2: 9000 | J2: 157475.6 | K2: =J2+H2-I2 -> 148475.6
A3: 46024 | B3: I | C3: 75 | D3: 102 | F3: vta tlmkt canindo alfonso arroyo | I3: 9000 | J3: =J2-H3+I3 -> 166475.6
A4: 46024 | B4: I | C4: 75 | D4: 102 | F4: vta tlmkt canindo alfonso arroyo | I4: 5000 | J4: =J3-H4+I4 -> 171475.6
A5: 46024 | B5: C | C5: 30 | D5: 510 | E5: 1 | F5: Hersheys Mexico | H5: 146226.19 | J5: =J4-H5+I5 -> 25249.41
A6: 46024 | B6: TE | D6: - | F6: TRASPASO ENTRE CTAS 6721 | H6: 20000 | J6: =J5-H6+I6 -> 5249.41
A7: 46024 | B7: I | C7: 75 | D7: 102 | F7: Vta.Tlmk Canindo Teresa Manzo | G7: 45994 | I7: 22500 | J7: =J6-H7+I7 -> 27749.41
A8: 46024 | B8: I | C8: 75 | D8: 102 | F8: Vta.Tlmk Canindo Teresa Manzo | G8: 45994 | I8: 16200 | J8: =J7-H8+I8 -> 43949.41
A9: 46024 | B9: I | C9: 75 | D9: 102 | F9: Vta.Tlmk Canindo Teresa Manzo | G9: 45994 | I9: 3300 | J9: =J8-H9+I9 -> 47249.41
A10: 46024 | B10: I | C10: 75 | D10: 102 | F10: vta tlmkt canindo alfonso arroyo | I10: 760 | J10: =J9-H10+I10 -> 48009.41
A11: 46027 | B11: I | C11: 75 | D11: 102 | F11: Vta Tlmt Canindo Maria Elena Alvarez | G11: 46020 | I11: 10282.76 | J11: =J10-H11+I11 -> 58292.17
A12: 46027 | B12: I | C12: 75 | D12: 102 | F12: VTA TLMLKT CANINDO MARIA ELENA ALVAREZ | G12: 45992 | I12: 39695.1 | J12: =J11-H12+I12 -> 97987.27
A13: 46028 | B13: I | C13: 75 | D13: 102 | F13: Vta.Tlmk Canindo Victor Hugo | G13: 45996 | I13: 40000 | J13: =J12-H13+I13 -> 137987.27
A14: 46028 | B14: I | C14: 75 | D14: 102 | F14: Vta.Tlmk Canindo Laura Efigenia | G14: 46021 | I14: 51384.85 | J14: =J13-H14+I14 -> 189372.12
A15: 46028 | B15: I | C15: 75 | D15: 102 | F15: Vta.Tlmk Canindo Juan Manuel M | G15: 45997 | I15: 90000 | J15: =J14-H15+I15 -> 279372.12
A16: 46028 | B16: I | C16: 75 | D16: 102 | F16: Vta.Tlmk Canindo Brenda Arredondo | G16: 45989 | I16: 24313 | J16: =J15-H16+I16 -> 303685.12
A17: 46028 | B17: I | C17: 75 | D17: 102 | F17: Vta.Tlmk Canindo Ana Laura | G17: 46009 | I17: 52230 | J17: =J16-H17+I17 -> 355915.12
A18: 46028 | B18: C | C18: 0 | D18: 510 | E18: 2 | F18: Qualamex | H18: 169132.12 | J18: =J17-H18+I18 -> 186783
A19: 46028 | B19: C | C19: 30 | D19: 510 | E19: 3 | F19: Mario Alberto Rodriguez | H19: 56408.4 | J19: =J18-H19+I19 -> 130374.6
A20: 46028 | B20: C | C20: 10 | D20: 510 | E20: 4 | F20: Mario Alberto Rodriguez | H20: 76631.2 | J20: =J19-H20+I20 -> 53743.4
A21: 46029 | B21: I | C21: 75 | D21: 102 | F21: Vta.Tlmk Canindo Manuel Camarena | G21: 46004 | I21: 55576.88 | J21: =J20-H21+I21 -> 109320.28
A22: 46029 | B22: C | C22: 0 | D22: 510 | E22: 5 | F22: Ma Soledad Gutierrez | H22: 64012.03 | J22: =J21-H22+I22 -> 45308.25
A23: 46029 | B23: G | C23: 12 | D23: 610 | E23: 6 | F23: Maria del Carmen Heredia Navarro | H23: 11252 | J23: =J22-H23+I23 -> 34056.25
A24: 46029 | B24: G | C24: 12 | D24: 613 | E24: 7 | F24: America Alejandra Lopez | H24: 29587.5 | J24: =J23-H24+I24 -> 4468.75
A25: 46029 | B25: I | C25: 75 | D25: 102 | F25: Vta.Tlmk Canindo Maria del Rosario | G25: 45996 | I25: 43044.87 | J25: =J24-H25+I25 -> 47513.62
A26: 46030 | B26: I | C26: 75 | D26: 102 | F26: Vta.Tlmk Canindo Dalia Morales | G26: 46003 | I26: 15000 | J26: =J25-H26+I26 -> 62513.62
A27: 46030 | B27: I | C27: 75 | D27: 102 | F27: Vta.Tlmk Canindo Cirenia Margarita | G27: 45982 | I27: 10000 | J27: =J26-H27+I27 -> 72513.62
A28: 46030 | B28: I | C28: 75 | D28: 102 | F28: Vta.Tlmk Canindo Alan Vazquez | G28: 46017 | I28: 21762.5 | J28: =J27-H28+I28 -> 94276.12
A29: 46030 | B29: I | C29: 75 | D29: 102 | F29: Vta.Tlmk Canindo Bernardo Vazquez | G29: 46017 | I29: 39274.5 | J29: =J28-H29+I29 -> 133550.62
A30: 46030 | B30: I | C30: 75 | D30: 102 | F30: Vta.Tlmk Canindo Alan Vazquez | G30: 45996 | I30: 32064 | J30: =J29-H30+I30 -> 165614.62
A31: 46030 | B31: I | C31: 75 | D31: 102 | F31: Vta.Tlmk Canindo Bernardo Vazquez | G31: 46004 | I31: 47424.5 | J31: =J30-H31+I31 -> 213039.12
A32: 46030 | B32: I | C32: 75 | D32: 102 | F32: Vta.Tlmk Canindo Alan Vazquez | G32: 46003 | I32: 39318.5 | J32: =J31-H32+I32 -> 252357.62
A33: 46030 | B33: I | C33: 54 | D33: 102 | F33: VENTA ZAMORA CENTRO | I33: 34710 | J33: =J32-H33+I33 -> 287067.62
A34: 46030 | B34: I | C34: 75 | D34: 102 | F34: Vta.Tlmk Canindo Juan de la Peña | G34: 45982 | I34: 2033 | J34: =J33-H34+I34 -> 289100.62
A35: 46030 | B35: I | D35: 102 | F35: DEV SDO A FAVOR FACT 9949 | I35: 6320.38 | J35: =J34-H35+I35 -> 295421
A36: 46030 | B36: ID | D36: 102 | F36: DEV. JORGE ALBERTO CONTRERAS BAUTISTA MAXIFUM | I36: 32016 | J36: =J35-H36+I36 -> 327437
A37: 46030 | B37: I | C37: 75 | D37: 102 | F37: Vta.Tlmk Canindo Sandra Araceli | G37: 46003 | I37: 120000 | J37: =J36-H37+I37 -> 447437
A38: 46030 | B38: TE | D38: - | F38: TRASPASO ENTRE CTAS 5712 | H38: 440000 | J38: =J37-H38+I38 -> 7437
A39: 46031 | B39: I | D39: 102 | F39: DEV FACTS | I39: 4920 | J39: =J38-H39+I39 -> 12357
A40: 46031 | B40: I | C40: 75 | D40: 102 | F40: Vta.Tlmk Canindo Maria Dolores | G40: 45999 | I40: 140947 | J40: =J39-H40+I40 -> 153304
A41: 46031 | B41: I | C41: 75 | D41: 102 | F41: Vta.Tlmk Canindo Yolanda Barragan | G41: 45985 | I41: 3150 | J41: =J40-H41+I41 -> 156454
A42: 46031 | B42: C | C42: 0 | D42: 510 | E42: 8 | F42: Cuetara Distribuciones | H42: 128000 | J42: =J41-H42+I42 -> 28454
A43: 46032 | B43: I | C43: 75 | D43: 102 | F43: Vta.Tlmk Canindo Julio Cesar | G43: 46001 | I43: 21998 | J43: =J42-H43+I43 -> 50452
A44: 46032 | B44: I | C44: 75 | D44: 102 | F44: Vta.Tlmk Canindo Aurora Rios | G44: 45972 | I44: 35572 | J44: =J43-H44+I44 -> 86024
A45: 46032 | B45: I | C45: 75 | D45: 102 | F45: Vta.Tlmk Canindo Alexis Amezcua | G45: 46008 | I45: 24550 | J45: =J44-H45+I45 -> 110574
A46: 46032 | B46: I | C46: 75 | D46: 102 | F46: Vta.Tlmk Canindo Alejandro Mondragon | G46: 45978 | I46: 19324 | J46: =J45-H46+I46 -> 129898
A47: 46034 | B47: I | C47: 75 | D47: 102 | F47: Vta.Tlmk Canindo Maria Elena | G47: 46027 | I47: 41371.69 | J47: =J46-H47+I47 -> 171269.69
A48: 46034 | B48: I | C48: 75 | D48: 102 | F48: Vta.Tlmk Canindo Alfonso Arroyo | G48: 45979 | I48: 14405 | J48: =J47-H48+I48 -> 185674.69
A49: 46035 | B49: I | C49: 75 | D49: 102 | F49: Vta.Tlmk Canindo Ramon Medina | G49: 46022 | I49: 16600 | J49: =J48-H49+I49 -> 202274.69
A50: 46035 | B50: I | C50: 75 | D50: 102 | F50: Vta.Tlmk Canindo Ramon Medina | G50: 46022 | I50: 29715 | J50: =J49-H50+I50 -> 231989.69
A51: 46035 | B51: I | C51: 75 | D51: 102 | F51: Vta.Tlmk Canindo Ana Laura | G51: 46009 | I51: 49200 | J51: =J50-H51+I51 -> 281189.69
A52: 46035 | B52: I | C52: 75 | D52: 102 | F52: Vta.Tlmk Canindo Juan Manuel M | G52: 45997 | I52: 40000 | J52: =J51-H52+I52 -> 321189.69
A53: 46035 | B53: TE | D53: - | F53: TRASPASO ENTRE CTAS 6721 | H53: 170000 | J53: =J52-H53+I53 -> 151189.69
A54: 46036 | B54: I | C54: 75 | D54: 102 | F54: Vta.Tlmk Canindo Cristina Noeli | G54: 46018 | I54: 26656.71 | J54: =J53-H54+I54 -> 177846.4
A55: 46036 | B55: C | C55: 50 | D55: 510 | E55: 9 | F55: Productos Garzeta | H55: 110770.6 | J55: =J54-H55+I55 -> 67075.8
A56: 46037 | B56: G | C56: 7 | D56: 613 | E56: 10 | F56: Jose Antonio Manzo Tamayo | H56: 5278 | J56: =J55-H56+I56 -> 61797.8
A57: 46037 | B57: G | C57: 30 | D57: 613 | E57: 11 | F57: Central Logistica y de Abasto Michoacan | H57: 1000 | J57: =J56-H57+I57 -> 60797.8
A58: 46037 | B58: TE | D58: - | F58: TRASPASO ENTRE CTAS 6721 | H58: 50000 | J58: =J57-H58+I58 -> 10797.8
A59: 46038 | B59: C | C59: 0 | D59: 510 | E59: 12 | F59: Tairecel | H59: 9500 | J59: =J58-H59+I59 -> 1297.8
A60: 46038 | B60: I | C60: 75 | D60: 102 | F60: Vta.Tlmk Canindo Francisco Orozco | G60: 46014 | I60: 99933 | J60: =J59-H60+I60 -> 101230.8
A61: 46038 | B61: I | C61: 75 | D61: 102 | F61: Vta.Tlmk Canindo Cinthia Ramirez | G61: 46007 | I61: 40265 | J61: =J60-H61+I61 -> 141495.8
A62: 46038 | B62: I | C62: 75 | D62: 102 | F62: Vta.Tlmk Canindo Yolanda Barragan | G62: 45999 | I62: 4322 | J62: =J61-H62+I62 -> 145817.8
A63: 46038 | B63: G | C63: 29 | D63: 613 | E63: 13 | F63: Automotores Flosol | H63: 119871.01 | J63: =J62-H63+I63 -> 25946.79
A64: 46039 | B64: I | C64: 75 | D64: 102 | F64: Vta.Tlmk Canindo Comercial Jm | G64: 46011 | I64: 15280 | J64: =J63-H64+I64 -> 41226.79
A65: 46039 | B65: I | C65: 75 | D65: 102 | F65: Vta.Tlmk Canindo Virginia Amezcua | G65: 46018 | I65: 12123 | J65: =J64-H65+I65 -> 53349.79
A66: 46039 | B66: I | C66: 75 | D66: 102 | F66: Vta.Tlmk Canindo Cristofer Ibarra | G66: 45955 | I66: 10000 | J66: =J65-H66+I66 -> 63349.79
A67: 46039 | B67: I | C67: 75 | D67: 102 | F67: Vta.Tlmk Canindo Octaviano Morales | G67: 46018 | I67: 23300 | J67: =J66-H67+I67 -> 86649.79
A68: 46039 | B68: I | C68: 75 | D68: 102 | F68: Vta.Tlmk Canindo Francisco Orozco | G68: 45990 | I68: 22768 | J68: =J67-H68+I68 -> 109417.79
A69: 46039 | B69: I | C69: 75 | D69: 102 | F69: Vta.Tlmk Canindo Macorra Gilberto | G69: 45990 | I69: 9338 | J69: =J68-H69+I69 -> 118755.79
A70: 46039 | B70: I | C70: 75 | D70: 102 | F70: Vta.Tlmk Canindo Karla Paulina | G70: 45993 | I70: 5820 | J70: =J69-H70+I70 -> 124575.79
A71: 46041 | B71: I | D71: 102 | F71: Dep. Efectivo | I71: 31907.25 | J71: =J70-H71+I71 -> 156483.04
A72: 46041 | B72: I | C72: 75 | D72: 102 | F72: Vta.Tlmk Canindo Brenda Arredondo | G72: 46010 | I72: 8500 | J72: =J71-H72+I72 -> 164983.04
A73: 46041 | B73: I | C73: 75 | D73: 102 | F73: Vta.Tlmk Canindo Brenda Arredondo | G73: 46010 | I73: 15000 | J73: =J72-H73+I73 -> 179983.04
A74: 46041 | B74: I | C74: 75 | D74: 102 | F74: Vta.Tlmk Canindo Brenda Arredondo | G74: 46010 | I74: 13000 | J74: =J73-H74+I74 -> 192983.04
A75: 46041 | B75: I | C75: 75 | D75: 102 | F75: Vta.Tlmk Canindo Brenda Arredondo | G75: 46010 | I75: 7700 | J75: =J74-H75+I75 -> 200683.04
A76: 46041 | B76: I | C76: 75 | D76: 102 | F76: Vta.Tlmk Canindo Brenda Arredondo | G76: 46010 | I76: 5900 | J76: =J75-H76+I76 -> 206583.04
A77: 46042 | B77: I | C77: 75 | D77: 102 | F77: Vta.Tlmk Canindo Manuel Camarena | G77: 46004 | I77: 38612.05 | J77: =J76-H77+I77 -> 245195.09
A78: 46042 | B78: I | C78: 75 | D78: 102 | F78: Vta.Tlmk Canindo Salvador Lopez | G78: 46008 | I78: 11000 | J78: =J77-H78+I78 -> 256195.09
A79: 46042 | B79: I | C79: 75 | D79: 102 | F79: Vta.Tlmk Canindo Guadalupe Torres | G79: 45972 | I79: 30000 | J79: =J78-H79+I79 -> 286195.09
A80: 46042 | B80: I | C80: 75 | D80: 102 | F80: Vta.Tlmk Canindo Alexis Amezcua | G80: 46008 | I80: 5980 | J80: =J79-H80+I80 -> 292175.09
A81: 46042 | B81: C | C81: 10 | D81: 510 | E81: 14 | F81: Conservas LA Costeña | H81: 155116.72 | J81: =J80-H81+I81 -> 137058.37
A82: 46042 | B82: I | C82: 75 | D82: 102 | F82: Vta.Tlmk Canindo Maria Guadalupe O | G82: 46041 | I82: 3442.53 | J82: =J81-H82+I82 -> 140500.9
A83: 46043 | B83: I | D83: 102 | F83: Dep. Efectivo | I83: 18386 | J83: =J82-H83+I83 -> 158886.9 | K83: ALFONSO ARROYO GUILLEN
A84: 46043 | B84: I | C84: 75 | D84: 102 | F84: Vta.Tlmk Canindo Macorra Gilberto | G84: 46007 | I84: 22218 | J84: =J83-H84+I84 -> 181104.9
A85: 46043 | B85: I | C85: 75 | D85: 102 | F85: Vta.Tlmk Canindo Brenda Arredondo | G85: 46010 | I85: 3600 | J85: =J84-H85+I85 -> 184704.9
A86: 46043 | B86: C | C86: 30 | D86: 510 | E86: 15 | F86: La Granja Organica | H86: 10400 | J86: =J85-H86+I86 -> 174304.9
A87: 46043 | B87: C | C87: 32 | D87: 510 | E87: 16 | F87: Jose Uriel Guerrero | H87: 7519.33 | J87: =J86-H87+I87 -> 166785.57
A88: 46043 | B88: C | C88: 50 | D88: 510 | E88: 17 | F88: Jose Uriel Guerrero | H88: 39534.1 | J88: =J87-H88+I88 -> 127251.47
A89: 46043 | B89: C | C89: 40 | D89: 510 | E89: 18 | F89: Jose Uriel Guerrero | H89: 16429.53 | J89: =J88-H89+I89 -> 110821.94
A90: 46043 | B90: C | C90: 10 | D90: 510 | E90: 19 | F90: Jose Uriel Guerrero | H90: 7629.67 | J90: =J89-H90+I90 -> 103192.27
A91: 46044 | B91: I | C91: 75 | D91: 102 | F91: Vta.Tlmk Canindo Victor Hugo | G91: 45996 | I91: 30000 | J91: =J90-H91+I91 -> 133192.27
A92: 46044 | B92: C | C92: 30 | D92: 510 | E92: 20 | F92: Grupo Zorro Abarrotero | H92: 45424.7 | J92: =J91-H92+I92 -> 87767.57
A93: 46044 | B93: G | C93: 30 | D93: 613 | E93: 21 | F93: Yolanda Macedo | H93: 3587.85 | J93: =J92-H93+I93 -> 84179.72
A94: 46044 | B94: G | C94: 02 | D94: 610 | E94: 22 | F94: Servicios Globales | H94: 23100.01 | J94: =J93-H94+I94 -> 61079.71
A95: 46044 | B95: G | C95: 7 | D95: 613 | E95: 23 | F95: Guillermo Garcia villalobos | H95: 39646.43 | J95: =J94-H95+I95 -> 21433.28
A96: 46045 | B96: I | C96: 75 | D96: 102 | F96: Vta.Tlmk Canindo Sandra Araceli | G96: 46022 | I96: 46848.56 | J96: =J95-H96+I96 -> 68281.84
A97: 46045 | B97: I | C97: 75 | D97: 102 | F97: Vta.Tlmk Canindo Maria Dolores | G97: 46007 | I97: 75000 | J97: =J96-H97+I97 -> 143281.84
A98: 46045 | B98: I | C98: 75 | D98: 102 | F98: Vta.Tlmk Canindo Maria Salcido | G98: 46018 | I98: 135350 | J98: =J97-H98+I98 -> 278631.84
A99: 46045 | B99: C | C99: 0 | D99: 510 | E99: 24 | F99: Gamahubin | H99: 242177.17 | J99: =J98-H99+I99 -> 36454.67
A100: 46045 | B100: TE | C100: - | D100: - | F100: traspaso de bbva 6586 a bbva 4176 | H100: 30000 | J100: =J99-H100+I100 -> 6454.67
...

Sheet BBVA 4176
A1: FECHA | B1: M | C1: S | D1: C | E1: # | F1: PROVEEDOR | G1: F VTA | H1: RETIRO | I1: DEPOSITO | J1: SALDO
A2: 46024 | B2: I | C2: 73 | D2: 102 | F2: Vta.Tlmk Morelia Andrea Silva | G2: 46017 | I2: 1403.59 | J2: 4524.65 | K2: =J2+H2-I2 -> 3121.06
A3: 46024 | B3: I | C3: 73 | D3: 102 | F3: Vta.Tlmk Morelia Jose Ma. leyva | G3: 45995 | I3: 30357.54 | J3: =J2-H3+I3 -> 34882.19
A4: 46024 | B4: I | C4: 32 | D4: 102 | F4: VENTAS MORELIA MADERO | G4: 46024 | I4: 1500 | J4: =J3-H4+I4 -> 36382.19
A5: 46024 | B5: TE | D5: - | F5: TRASPASO ENTRE CTAS 6721 | H5: 30000 | J5: =J4-H5+I5 -> 6382.19
A6: 46024 | B6: G | C6: 30 | D6: 610 | E6: 1 | F6: Nom 01 Pension | H6: 735.51 | J6: =J5-H6+I6 -> 5646.68
A7: 46024 | B7: I | C7: 30 | D7: 102 | F7: VENTAS MORELIA ABASTOS | G7: 46030 | I7: 3669.75 | J7: =J6-H7+I7 -> 9316.43
A8: 46024 | B8: I | C8: 30 | D8: 102 | F8: VENTAS MORELIA ABASTOS | G8: 46030 | I8: 4000 | J8: =J7-H8+I8 -> 13316.43
A9: 46026 | B9: I | C9: 30 | D9: 102 | F9: VENTAS MORELIA ABASTOS | G9: 46030 | I9: 6287.63 | J9: =J8-H9+I9 -> 19604.06
A10: 46027 | B10: I | C10: 73 | D10: 102 | F10: Vta.Tlmk Morelia Norma Isela | G10: 46014 | I10: 2656 | J10: =J9-H10+I10 -> 22260.06
A11: 46027 | B11: I | C11: 73 | D11: 102 | F11: Vta.Tlmk Morelia Manuel Alejandro | G11: 46011 | I11: 8797.05 | J11: =J10-H11+I11 -> 31057.11
A12: 46027 | B12: I | C12: 73 | D12: 102 | F12: Vta.Tlmk Morelia Maria Domitila | G12: 46000 | I12: 62753.63 | J12: =J11-H12+I12 -> 93810.74
A13: 46027 | B13: I | C13: 73 | D13: 102 | F13: Vta.Tlmk Morelia Maria Domitila | G13: 46007 | I13: 29394.98 | J13: =J12-H13+I13 -> 123205.72
A14: 46028 | B14: G | C14: 12 | D14: 613 | E14: 2 | F14: Juan Manuel Espinoza | H14: 2450 | J14: =J13-H14+I14 -> 120755.72
A15: 46028 | B15: I | C15: 73 | D15: 102 | F15: Vta.Tlmk Morelia Paola Lopez | G15: 46001 | I15: 44507 | J15: =J14-H15+I15 -> 165262.72
A16: 46028 | B16: C | C16: 10 | D16: 510 | E16: 3 | F16: Miguel Angel Bribiesca | H16: 11901.6 | J16: =J15-H16+I16 -> 153361.12
A17: 46028 | B17: C | C17: 30 | D17: 510 | E17: 4 | F17: Vidis SA de CV | H17: 84600.28 | J17: =J16-H17+I17 -> 68760.84
A18: 46028 | B18: I | C18: 73 | D18: 102 | F18: Vta.Tlmk Morelia Seferina Garcia | G18: 46025 | I18: 3938 | J18: =J17-H18+I18 -> 72698.84
A19: 46028 | B19: I | C19: 73 | D19: 102 | F19: Vta.Tlmk Morelia Seferina Garcia | G19: 46018 | I19: 2333 | J19: =J18-H19+I19 -> 75031.84
A20: 46028 | B20: I | C20: 32 | D20: 102 | F20: VENTAS MORELIA MADERO | G20: 46028 | I20: 2299.37 | J20: =J19-H20+I20 -> 77331.21
A21: 46029 | B21: I | C21: 30 | D21: 102 | F21: VENTAS MORELIA ABASTOS | G21: 46031 | I21: 3600 | J21: =J20-H21+I21 -> 80931.21
A22: 46029 | B22: C | C22: 50 | D22: 510 | E22: 5 | F22: Botanas y Cereales de Zamora | H22: 52278.97 | J22: =J21-H22+I22 -> 28652.24
A23: 46029 | B23: G | C23: 30 | D23: 613 | E23: 6 | F23: FONACOT | H23: 6812.74 | J23: =J22-H23+I23 -> 21839.5
A24: 46029 | B24: G | C24: 90 | D24: 610 | E24: 7 | F24: Ma Eugenia Campos Moya | H24: 17400 | J24: =J23-H24+I24 -> 4439.5
A25: 46030 | B25: I | C25: 73 | D25: 102 | F25: Vta.Tlmk Morelia Rosario Morales | G25: 46013 | I25: 31232.5 | J25: =J24-H25+I25 -> 35672
A26: 46030 | B26: I | C26: 73 | D26: 102 | F26: Vta.Tlmk Morelia Francisco Garcia | G26: 46011 | I26: 11159.25 | J26: =J25-H26+I26 -> 46831.25
A27: 46030 | B27: I | C27: 73 | D27: 102 | F27: Vta.Tlmk Morelia Leonel Silva | G27: 46024 | I27: 24868.36 | J27: =J26-H27+I27 -> 71699.61
A28: 46030 | B28: I | C28: 73 | D28: 102 | F28: Vta.Tlmk Morelia Leonel Silva | G28: 46024 | I28: 27516.6 | J28: =J27-H28+I28 -> 99216.21
A29: 46030 | B29: I | C29: 73 | D29: 102 | F29: Vta.Tlmk Morelia Jesus Sanchez | G29: 46020 | I29: 11526 | J29: =J28-H29+I29 -> 110742.21
A30: 46030 | B30: I | C30: 30 | D30: 102 | F30: VENTAS MORELIA ABASTOS | G30: 46030 | I30: 12644 | J30: =J29-H30+I30 -> 123386.21
A31: 46030 | B31: I | C31: 73 | D31: 102 | F31: Vta.Tlmk Morelia Jesus Sanchez | G31: 46013 | I31: 8807 | J31: =J30-H31+I31 -> 132193.21
A32: 46030 | B32: TI | D32: - | F32: TRASPASO ENTRE CTAS 6721 | I32: 60000 | J32: =J31-H32+I32 -> 192193.21
A33: 46030 | B33: C | D33: 510 | E33: 8 | F33: Cuetara Distribuciones | H33: 14254.43 | J33: =J32-H33+I33 -> 177938.78
A34: 46030 | B34: S | F34: Spei Cuetara | H34: 128000 | J34: =J33-H34+I34 -> 49938.78
A35: 46030 | B35: DS | F35: Dev Spei Cuetara | I35: 128000 | J35: =J34-H35+I35 -> 177938.78
A36: 46031 | B36: S | F36: Spei Cuetara | H36: 128000 | J36: =J35-H36+I36 -> 49938.78
A37: 46031 | B37: DS | F37: Dev Spei Cuetara | I37: 128000 | J37: =J36-H37+I37 -> 177938.78
A38: 46031 | B38: I | C38: 73 | D38: 102 | F38: Vta.Tlmk Morelia Crisanto Bautista | G38: 46031 | I38: 20486.81 | J38: =J37-H38+I38 -> 198425.59
A39: 46031 | B39: G | C39: 30 | D39: 610 | E39: 9 | F39: Nom 02 pension | H39: 882.62 | J39: =J38-H39+I39 -> 197542.97
A40: 46031 | B40: C | C40: 30 | D40: 510 | E40: 10 | F40: Abarrotes La Violeta | H40: 86827.03 | J40: =J39-H40+I40 -> 110715.94
A41: 46031 | B41: C | C41: 32 | D41: 510 | E41: 11 | F41: abarrotes La Violeta | H41: 29050 | J41: =J40-H41+I41 -> 81665.94
A42: 46032 | B42: I | C42: 73 | D42: 102 | F42: Vta. Tlmk Morelia Carla Monserrath | G42: 46021 | I42: 13657 | J42: =J41-H42+I42 -> 95322.94
A43: 46032 | B43: I | C43: 73 | D43: 102 | F43: Vta.Tlmk Morelia Carla Monserrath | G43: 46030 | I43: 7249 | J43: =J42-H43+I43 -> 102571.94
A44: 46033 | B44: I | D44: 102 | F44: Dep. Efectivo | I44: 1 | J44: =J43-H44+I44 -> 102572.94
A45: 46033 | B45: I | C45: 73 | D45: 102 | F45: Vta.Tlmk Morelia Adriana Diaz | G45: 46030 | I45: 6360 | J45: =J44-H45+I45 -> 108932.94
A46: 46033 | B46: I | C46: 73 | D46: 102 | F46: Vta.Tlmk Morelia Adriana Diaz | G46: 46021 | I46: 5126 | J46: =J45-H46+I46 -> 114058.94
A47: 46033 | B47: I | C47: 73 | D47: 102 | F47: Dep. Efectivo | I47: 3927 | J47: =J46-H47+I47 -> 117985.94 | K47: ADRIANA DIAZ MALDONADO
A48: 46034 | B48: I | C48: 30 | D48: 102 | F48: VENTAS MORELIA ABASTOS | G48: 46034 | I48: 2245.09 | J48: =J47-H48+I48 -> 120231.03
A49: 46034 | B49: I | C49: 73 | D49: 102 | F49: Vta.Tlmk Morelia Francisco Garcia | G49: 46017 | I49: 25925.95 | J49: =J48-H49+I49 -> 146156.98
A50: 46034 | B50: I | C50: 30 | D50: 102 | F50: VENTAS MORELIA ABASTOS | G50: 46035 | I50: 984.48 | J50: =J49-H50+I50 -> 147141.46
A51: 46034 | B51: I | C51: 73 | D51: 102 | F51: Vta.Tlmk Morelia Andrea Peña | G51: 46001 | I51: 13825 | J51: =J50-H51+I51 -> 160966.46
A52: 46034 | B52: I | C52: 73 | D52: 102 | F52: Vta.Tlmk Morelia Paola Lopez | G52: 46001 | I52: 300 | J52: =J51-H52+I52 -> 161266.46
A53: 46034 | B53: G | C53: 88 | D53: 613 | E53: 12 | F53: Jaime Jose de Jesus Alvo | H53: 60000 | J53: =J52-H53+I53 -> 101266.46
A54: 46034 | B54: G | C54: 88 | D54: 613 | E54: 13 | F54: Victor Samuel Alvo | H54: 60000 | J54: =J53-H54+I54 -> 41266.46
A55: 46034 | B55: G | C55: 32 | D55: 610 | E55: 14 | F55: Jaime Arce Torres | H55: 5000.01 | J55: =J54-H55+I55 -> 36266.45
A56: 46034 | B56: I | C56: 73 | D56: 102 | F56: Vta.Tlmk Morelia Manuel Alejandro | G56: 46018 | I56: 13017.54 | J56: =J55-H56+I56 -> 49283.99
A57: 46035 | B57: I | C57: 73 | D57: 102 | F57: Vta.Tlmk Morelia Norma Isela | G57: 46021 | I57: 1202 | J57: =J56-H57+I57 -> 50485.99
A58: 46035 | B58: I | C58: 73 | D58: 102 | F58: Vta.Tlmk Morelia Leonel Silva | G58: 46031 | I58: 19996.73 | J58: =J57-H58+I58 -> 70482.72
A59: 46035 | B59: I | C59: 30 | D59: 102 | F59: VENTAS MORELIA ABASTOS | I59: 7604.65 | J59: =J58-H59+I59 -> 78087.37
A60: 46036 | B60: I | C60: 30 | D60: 102 | F60: VENTAS MORELIA ABASTOS | G60: 46036 | I60: 2584.88 | J60: =J59-H60+I60 -> 80672.25
A61: 46036 | B61: I | C61: 30 | D61: 102 | F61: VENTAS MORELIA ABASTOS | G61: 46036 | I61: 4759.38 | J61: =J60-H61+I61 -> 85431.63
A62: 46036 | B62: I | C62: 73 | D62: 102 | F62: TRANS.VTA.TLMKT MORELIA CRISTINA LOPEZ | G62: 46036 | I62: 328.29 | J62: =J61-H62+I62 -> 85759.92
A63: 46036 | B63: I | C63: 32 | D63: 102 | F63: VENTAS MORELIA MADERO | G63: 46038 | I63: 480 | J63: =J62-H63+I63 -> 86239.92
A64: 46036 | B64: C | C64: 12 | D64: 613 | E64: 15 | F64: Super Servicio Garbri | H64: 34657.85 | J64: =J63-H64+I64 -> 51582.07
A65: 46037 | B65: I | D65: 102 | F65: Dep. Efectivo | I65: 6493.48 | J65: =J64-H65+I65 -> 58075.55
A66: 46037 | B66: I | C66: 73 | D66: 102 | F66: Vta.Tlmk Morelia Graciela Marina | G66: 46027 | I66: 7915.91 | J66: =J65-H66+I66 -> 65991.46
A67: 46037 | B67: I | C67: 73 | D67: 102 | F67: Vta.Tlmk Morelia Graciela Marina | G67: 46027 | I67: 988.92 | J67: =J66-H67+I67 -> 66980.38
A68: 46037 | B68: I | C68: 73 | D68: 102 | F68: Vta.Tlmk Morelia Graciela Marina | G68: 46034 | I68: 6869.87 | J68: =J67-H68+I68 -> 73850.25
A69: 46037 | B69: I | C69: 32 | D69: 102 | F69: VENTAS MORELIA MADERO | G69: 46038 | I69: 193 | J69: =J68-H69+I69 -> 74043.25
A70: 46037 | B70: I | C70: 73 | D70: 102 | F70: Vta.Tlmk Morelia Jose Ma. Leyva | G70: 46002 | I70: 11037.34 | J70: =J69-H70+I70 -> 85080.59
A71: 46037 | B71: I | C71: 73 | D71: 102 | F71: Vta.Tlmk Morelia Rosario Morales | G71: 46021 | I71: 25898 | J71: =J70-H71+I71 -> 110978.59
A72: 46037 | B72: TE | C72: - | D72: - | F72: TRASPASO ENTRE CTAS 5712 | H72: 110000 | J72: =J71-H72+I72 -> 978.59
A73: 46037 | B73: I | C73: 73 | D73: 102 | F73: Vta.Tlmk Morelia Anareli Almanza | G73: 46014 | I73: 17648 | J73: =J72-H73+I73 -> 18626.59
A74: 46037 | B74: I | C74: 73 | D74: 102 | F74: Vta.Tlmk Morelia Jose Soto | G74: 46022 | I74: 76984.92 | J74: =J73-H74+I74 -> 95611.51
A75: 46038 | B75: C | C75: 0 | D75: 510 | E75: 16 | F75: Deiman | H75: 7148.11 | J75: =J74-H75+I75 -> 88463.4
A76: 46038 | B76: C | C76: 0 | D76: 510 | E76: 17 | F76: Barquillos y Dulces De Eliz | H76: 31181.76 | J76: =J75-H76+I76 -> 57281.64
A77: 46038 | B77: C | C77: 0 | D77: 510 | E77: 18 | F77: Operadora de Productos Ban | H77: 38160 | J77: =J76-H77+I77 -> 19121.64
A78: 46038 | B78: G | C78: 30 | D78: 610 | E78: 19 | F78: Pension Nom03 | H78: 882.62 | J78: =J77-H78+I78 -> 18239.02
A79: 46039 | B79: I | C79: 32 | D79: 102 | F79: VENTAS MORELIA MADERO | G79: 46039 | I79: 1000 | J79: =J78-H79+I79 -> 19239.02
A80: 46039 | B80: I | C80: 32 | D80: 102 | F80: VENTAS MORELIA MADERO | G80: 46043 | I80: 657.5 | J80: =J79-H80+I80 -> 19896.52
A81: 46039 | B81: I | C81: 30 | D81: 102 | F81: VENTAS MORELIA ABASTOS | G81: 46043 | I81: 6636.73 | J81: =J80-H81+I81 -> 26533.25
A82: 46039 | B82: I | C82: 32 | D82: 102 | F82: VENTAS MORELIA MADERO | G82: 46043 | I82: 587.68 | J82: =J81-H82+I82 -> 27120.93
A83: 46041 | B83: I | C83: 30 | D83: 102 | F83: VENTAS MORELIA ABASTOS | G83: 46043 | I83: 1974 | J83: =J82-H83+I83 -> 29094.93
A84: 46041 | B84: I | C84: 73 | D84: 102 | F84: Vta.Tlmk Morelia Manuel Alejandro | G84: 46025 | I84: 7743.67 | J84: =J83-H84+I84 -> 36838.6
A85: 46041 | B85: I | C85: 73 | D85: 102 | F85: Vta.Tlmk Morelia Mary Carmen | G85: 46009 | I85: 22185 | J85: =J84-H85+I85 -> 59023.6
A86: 46041 | B86: I | C86: 73 | D86: 102 | F86: Vta.Tlmk Morelia Mary Carmen | G86: 45994 | I86: 20000 | J86: =J85-H86+I86 -> 79023.6
A87: 46041 | B87: I | C87: 73 | D87: 102 | F87: Vta.Tlmk Morelia Mary Carmen | G87: 45994 | I87: 11012 | J87: =J86-H87+I87 -> 90035.6
A88: 46041 | B88: I | C88: 73 | D88: 102 | F88: Vta.Tlmk Morelia Berenice Botello | G88: 46009 | I88: 29000 | J88: =J87-H88+I88 -> 119035.6
A89: 46041 | B89: G | C89: 02 | E89: 20 | F89: SAT | H89: 8806 | J89: =J88-H89+I89 -> 110229.6
A90: 46041 | B90: G | C90: 02 | E90: 21 | F90: SAT | H90: 13720 | J90: =J89-H90+I90 -> 96509.6
A91: 46041 | B91: G | C91: 02 | E91: 22 | F91: SAT | H91: 35271 | J91: =J90-H91+I91 -> 61238.6
A92: 46041 | B92: S | C92: 0 | D92: 510 | E92: 23 | F92: Empaques Biodegradables Biocup S de LR | H92: 28769.29 | J92: =J91-H92+I92 -> 32469.31
A93: 46041 | B93: C | C93: 0 | D93: 510 | E93: 24 | F93: Abarrotes del Centro Guerrero | H93: 27840 | J93: =J92-H93+I93 -> 4629.31
A94: 46041 | B94: DS | D94: 102 | I94: 28769.29 | J94: =J93-H94+I94 -> 33398.6
A95: 46041 | B95: I | C95: 73 | D95: 102 | F95: Vta.Tlmk Morelia Berenice Botello | G95: 46009 | I95: 11616 | J95: =J94-H95+I95 -> 45014.6
A96: 46042 | B96: I | C96: 73 | D96: 102 | F96: Vta.Tlmk Morelia Sonia Hernandez | G96: 45986 | I96: 105472.73 | J96: =J95-H96+I96 -> 150487.33
A97: 46042 | B97: I | C97: 73 | D97: 102 | F97: Vta.Tlmk Morelia Juan Gonzalez | G97: 45999 | I97: 68495.36 | J97: =J96-H97+I97 -> 218982.69
A98: 46042 | B98: I | C98: 73 | D98: 102 | F98: Vta.Tlmk Morelia Francisco Garcia | G98: 46024 | I98: 14306.41 | J98: =J97-H98+I98 -> 233289.1
A99: 46042 | B99: I | C99: 73 | D99: 102 | F99: Vta.Tlmk Morelia Leonel Silva | G99: 46038 | I99: 25584.92 | J99: =J98-H99+I99 -> 258874.02
A100: 46042 | B100: I | C100: 73 | D100: 102 | F100: Vta.Tlmk Morelia Leonel Silva | G100: 46038 | I100: 9559.53 | J100: =J99-H100+I100 -> 268433.55
...

Sheet BBVA 4885
A1: FECHA | B1: M | C1: S | D1: C | E1: # | F1: PROVEEDOR | G1: F VTA | H1: RETIRO | I1: DEPOSITO | J1: SALDO
A2: 46050 | B2: C | D2: 510 | E2: 1 | F2: DIF FACT LA GRANJA ORGANICA | H2: 290 | J2: 401.48 | K2: =J2+H2-I2 -> 691.48

Sheet BBVA 6721
A1: FECHA | B1: M | C1: S | D1: C | E1: # | F1: PROVEEDOR | G1: F VTA | H1: RETIRO | I1: DEPOSITO | J1: SALDO
A2: 46023 | B2: I | C2: 70 | D2: 102 | F2: Vta.Tlmk Ph Ma. Magdalena | G2: 45994 | I2: 92015.01 | J2: 95486.57 | K2: =J2+H2-I2 -> 3471.56
A3: 46023 | B3: I | C3: 73 | D3: 102 | F3: Vta.Tlmk Morelia Juan Jose Camacho | G3: 46021 | I3: 3600 | J3: =J2-H3+I3 -> 99086.57
A4: 46023 | B4: I | C4: 73 | D4: 102 | F4: Vta.Tlmk Morelia Juan Jose Camacho | G4: 46021 | I4: 1000 | J4: =J3-H4+I4 -> 100086.57
A5: 46024 | B5: I | C5: 70 | D5: 102 | F5: Vta.Tlmk Ph Diego Maestro | G5: 46000 | I5: 11248.84 | J5: =J4-H5+I5 -> 111335.41
A6: 46024 | B6: I | C6: 70 | D6: 102 | F6: Vta.Tlmk Ph Anahi Elizabeth | G6: 46002 | I6: 8000 | J6: =J5-H6+I6 -> 119335.41
A7: 46024 | B7: I | C7: 70 | D7: 102 | F7: Vta.Tlmk Ph Anahi Elizabeth | G7: 46002 | I7: 4414 | J7: =J6-H7+I7 -> 123749.41
A8: 46024 | B8: I | C8: 73 | D8: 102 | F8: Vta.Tlmk Morelia Ma. Maricela | G8: 46015 | I8: 7128.63 | J8: =J7-H8+I8 -> 130878.04
A9: 46024 | B9: I | C9: 70 | D9: 102 | F9: Vta.Tlmk Ph Luis Alberto Estrada | G9: 46008 | I9: 30097.18 | J9: =J8-H9+I9 -> 160975.22
A10: 46024 | B10: I | C10: 73 | D10: 102 | F10: Vta.Tlmk Morelia Oscas torres | G10: 45995 | I10: 15000 | J10: =J9-H10+I10 -> 175975.22
A11: 46024 | B11: I | C11: 73 | D11: 102 | F11: Vta.Tlmk Morelia Maribel Angel | G11: 46020 | I11: 18534.9 | J11: =J10-H11+I11 -> 194510.12
A12: 46024 | B12: I | C12: 73 | D12: 102 | F12: Vta.Tlmk Morelia Ruben Gomez | G12: 46007 | I12: 27511 | J12: =J11-H12+I12 -> 222021.12
A13: 46024 | B13: I | C13: 73 | D13: 102 | F13: Vta.Tlmk Morelia Martin suarez | G13: 45988 | I13: 80000 | J13: =J12-H13+I13 -> 302021.12
A14: 46024 | B14: I | C14: 73 | D14: 102 | F14: Vta.Tlmk Morelia Ruben Gomez | G14: 46013 | I14: 48828.9 | J14: =J13-H14+I14 -> 350850.02
A15: 46024 | B15: C | C15: 0 | D15: 510 | E15: 1 | F15: Dulceria de los Altos | H15: 257467.47 | J15: =J14-H15+I15 -> 93382.55
A16: 46024 | B16: TI | D16: - | F16: TRASPASO ENTRE CTAS 4176 | I16: 30000 | J16: =J15-H16+I16 -> 123382.55
A17: 46024 | B17: TI | D17: - | F17: TRASPASO ENTRE CTAS 6586 | I17: 20000 | J17: =J16-H17+I17 -> 143382.55
A18: 46024 | B18: C | C18: 10 | D18: 510 | E18: 2 | F18: Distribuidora de la Rosa SA de Cv | H18: 135438.42 | J18: =J17-H18+I18 -> 7944.13
A19: 46024 | B19: I | C19: 70 | D19: 102 | F19: Vta.Tlmk Ph Gloria Hernandez | G19: 46000 | I19: 6000 | J19: =J18-H19+I19 -> 13944.13
A20: 46024 | B20: I | C20: 70 | D20: 102 | F20: Vta.Tlmk Ph Gloria Hernandez | G20: 46000 | I20: 6000 | J20: =J19-H20+I20 -> 19944.13
A21: 46026 | B21: I | D21: 102 | F21: Dep. Efectivo | I21: 1500 | J21: =J20-H21+I21 -> 21444.13
A22: 46027 | B22: I | C22: 73 | D22: 102 | F22: Vta.Tlmk Morelia Ma. Maricela | G22: 46010 | I22: 19728.7 | J22: =J21-H22+I22 -> 41172.83
A23: 46027 | B23: I | C23: 70 | D23: 102 | F23: Vta.Tlmk Ph Dulceria de los altos | G23: 46024 | I23: 21210.01 | J23: =J22-H23+I23 -> 62382.84
A24: 46027 | B24: I | C24: 70 | D24: 102 | F24: Vta.Tlmk Ph Maria Guadalupe R | G24: 45995 | I24: 20000 | J24: =J23-H24+I24 -> 82382.84
A25: 46027 | B25: I | C25: 73 | D25: 102 | F25: Vta.Tlmk Morelia Maria d Lourdes | G25: 46004 | I25: 12811.86 | J25: =J24-H25+I25 -> 95194.7
A26: 46027 | B26: I | C26: 73 | D26: 102 | F26: Vta.Tlmk Morelia Maria d Lourdes | G26: 46021 | I26: 37921.74 | J26: =J25-H26+I26 -> 133116.44
A27: 46028 | B27: I | C27: 73 | D27: 102 | F27: Vta.Tlmk Morelia Marcelo Sandoval | G27: 46010 | I27: 60000 | J27: =J26-H27+I27 -> 193116.44
A28: 46028 | B28: I | C28: 73 | D28: 102 | F28: Vta.Tlmk Morelia Mayela Guevara | G28: 46009 | I28: 25353.44 | J28: =J27-H28+I28 -> 218469.88
A29: 46028 | B29: I | C29: 73 | D29: 102 | F29: Vta.Tlmk Morelia Oscas torres | G29: 45995 | I29: 13486.95 | J29: =J28-H29+I29 -> 231956.83
A30: 46028 | B30: I | C30: 73 | D30: 102 | F30: Vta.Tlmk Morelia Mayela Guevara | G30: 46002 | I30: 33116.83 | J30: =J29-H30+I30 -> 265073.66
A31: 46028 | B31: I | C31: 73 | D31: 102 | F31: Vta.Tlmk Morelia Mayela Guevara | G31: 46009 | I31: 1556.48 | J31: =J30-H31+I31 -> 266630.14
A32: 46028 | B32: I | C32: 73 | D32: 102 | F32: Vta.Tlmk Morelia oscas torres | G32: 45995 | I32: 5759 | J32: =J31-H32+I32 -> 272389.14
A33: 46028 | B33: I | C33: 73 | D33: 102 | F33: Vta.Tlmk Morelia Mayela Guevara | G33: 46002 | I33: 5000 | J33: =J32-H33+I33 -> 277389.14
... A40: 46028 | B40: I | C40: 70 | D40: 102 | F40: Vta.Tlmk Ph Gloria Hernandez | G40: 46000 | I40: 10000 | J40: =J39-H40+I40 -> 427031.57
A41: 46028 | B41: C | C41: 0 | D41: 510 | E41: 3 | F41: Dulfree Comercial | H41: 391176.16 | J41: =J40-H41+I41 -> 35855.41
A42: 46028 | B42: I | C42: 70 | D42: 102 | F42: Vta.Tlmk Ph Gloria Hernandez | G42: 46000 | I42: 10000 | J42: =J41-H42+I42 -> 45855.41
A43: 46028 | B43: C | C43: 0 | D43: 510 | E43: 4 | F43: Picao alimentos | H43: 31370.06 | J43: =J42-H43+I43 -> 14485.35
A44: 46028 | B44: I | C44: 70 | D44: 102 | F44: Vta.Tlmk Ph Gloria Hernandez | G44: 46000 | I44: 6000 | J44: =J43-H44+I44 -> 20485.35
A45: 46028 | B45: I | C45: 73 | D45: 102 | F45: Vta.Tlmk Morelia Patricia Paredes | G45: 46011 | I45: 10400 | J45: =J44-H45+I45 -> 30885.35
A46: 46029 | B46: I | C46: 70 | D46: 102 | F46: Vta.Tlmk Ph Anahi Elizabeth | G46: 46017 | I46: 9000 | J46: =J45-H46+I46 -> 39885.35
A47: 46029 | B47: I | C47: 73 | D47: 102 | F47: Vta.Tlmk Morelia Gerardo Molina | G47: 46011 | I47: 15634.5 | J47: =J46-H47+I47 -> 55519.85
A48: 46029 | B48: I | C48: 70 | D48: 102 | F48: Vta.Tlmk Ph Anahi Elizabeth | G48: 45995 | I48: 796 | J48: =J47-H48+I48 -> 56315.85
A49: 46029 | B49: I | C49: 73 | D49: 102 | F49: Vta.Tlmk Morelia Crisanto Butista | G49: 46018 | I49: 21381 | J49: =J48-H49+I49 -> 77696.85
A50: 46029 | B50: I | C50: 73 | D50: 102 | F50: Vta.Tlmk Morelia Ruben Gomez | G50: 46021 | I50: 30000 | J50: =J49-H50+I50 -> 107696.85
A51: 46029 | B51: I | C51: 73 | D51: 102 | F51: Vta.Tlmk Morelia Veronica Carrillo | G51: 46021 | I51: 25546 | J51: =J50-H51+I51 -> 133242.85
A52: 46029 | B52: I | C52: 73 | D52: 102 | F52: TRANSF.VTA.TLMKT MORELIA ARMANDO GEOVANI | G52: 46028 | I52: 2872 | J52: =J51-H52+I52 -> 136114.85
A53: 46029 | B53: C | C53: 0 | D53: 510 | E53: 5 | F53: Mega Alimentos | H53: 48252.84 | J53: =J52-H53+I53 -> 87862.01
A54: 46029 | B54: C | C54: 10 | D54: 510 | E54: 6 | F54: Abarrotes La Violeta | H54: 86827.03 | J54: =J53-H54+I54 -> 1034.98
A55: 46029 | B55: I | C55: 73 | D55: 102 | F55: Vta.Tlmk Morelia Claudia Garcia | G55: 45997 | I55: 40182 | J55: =J54-H55+I55 -> 41216.98
A56: 46030 | B56: I | C56: 70 | D56: 102 | F56: Vta.Tlmk Ph Gloria Hernandez | G56: 46000 | I56: 18000 | J56: =J55-H56+I56 -> 59216.98
A57: 46030 | B57: I | C57: 70 | D57: 102 | F57: Vta.Tlmk Ph Gloria Hernandez | G57: 46000 | I57: 1248 | J57: =J56-H57+I57 -> 60464.98
A58: 46030 | B58: I | C58: 73 | D58: 102 | F58: Vta.Tlmk Morelia Ruben Gomez | G58: 46021 | I58: 11816 | J58: =J57-H58+I58 -> 72280.98
A59: 46030 | B59: I | C59: 75 | D59: 102 | F59: Vta.Tlmk Canindo Rosalva Melgoza | G59: 46029 | I59: 3758.49 | J59: =J58-H59+I59 -> 76039.47
A60: 46030 | B60: TE | D60: - | F60: TRASPASO ENTRE CTAS 4176 | H60: 60000 | J60: =J59-H60+I60 -> 16039.47
A61: 46031 | B61: I | C61: 73 | D61: 102 | F61: Vta.Tlmk Morelia Patricia Paredes | G61: 46004 | I61: 7650 | J61: =J60-H61+I61 -> 23689.47
A62: 46031 | B62: I | C62: 70 | D62: 102 | F62: Vta.Tlmk Ph Victor Canales | G62: 45967 | I62: 13318 | J62: =J61-H62+I62 -> 37007.47
A63: 46031 | B63: I | D63: 102 | F63: Dep. Efectivo | I63: 848 | J63: =J62-H63+I63 -> 37855.47
A64: 46031 | B64: I | C64: 73 | D64: 102 | F64: Vta.Tlmk Morelia Lucas Pizano | G64: 46020 | I64: 3249.81 | J64: =J63-H64+I64 -> 41105.28
A65: 46031 | B65: I | C65: 70 | D65: 102 | F65: Vta.Tlmk Ph Antonio Elizondo | G65: 46008 | I65: 46714.42 | J65: =J64-H65+I65 -> 87819.7
A66: 46031 | B66: I | C66: 70 | D66: 102 | F66: Vta.Tlmk Ph Margarita Garcia | G66: 46002 | I66: 4066.32 | J66: =J65-H66+I66 -> 91886.02
A67: 46031 | B67: I | C67: 70 | D67: 102 | F67: Vta.Tlmk Ph Daniel Garcia | G67: 46009 | I67: 5776.45 | J67: =J66-H67+I67 -> 97662.47
A68: 46031 | B68: I | C68: 70 | D68: 102 | F68: Vta.Tlmk Ph Juana Chavez | G68: 46007 | I68: 87429.46 | J68: =J67-H68+I68 -> 185091.93
A69: 46031 | B69: I | C69: 70 | D69: 102 | F69: Vta.Tlmk Ph Ricardo Canales | G69: 46014 | I69: 12340.23 | J69: =J68-H69+I69 -> 197432.16
A70: 46031 | B70: I | C70: 73 | D70: 102 | F70: Vta.Tlmk Morelia Diego Guerrero | G70: 46000 | I70: 10000 | J70: =J69-H70+I70 -> 207432.16
A71: 46031 | B71: I | C71: 70 | D71: 102 | F71: Vta.Tlmk Ph Alfonso Canales | G71: 46014 | I71: 64208.36 | J71: =J70-H71+I71 -> 271640.52
A72: 46031 | B72: I | C72: 70 | D72: 102 | F72: Vta.Tlmk Ph Salvador Canales | G72: 46021 | I72: 49720.62 | J72: =J71-H72+I72 -> 321361.14
A73: 46031 | B73: I | C73: 70 | D73: 102 | F73: Vta.Tlmk Ph Elizabeth Jaime | G73: 46014 | I73: 11266.45 | J73: =J72-H73+I73 -> 332627.59
A74: 46031 | B74: I | C74: 70 | D74: 102 | F74: Vta.Tlmk Ph Eulogio Perez | G74: 46014 | I74: 14682.73 | J74: =J73-H74+I74 -> 347310.32
A75: 46031 | B75: I | C75: 70 | D75: 102 | F75: Vta.Tlmk Ph Jaime Romo | G75: 46014 | I75: 11743.31 | J75: =J74-H75+I75 -> 359053.63
... A91: 46031 | B91: I | C91: 73 | D91: 102 | F91: Vta.Tlmk Morelia Juan Jose Gomez | G91: 46027 | I91: 300 | J91: =J90-H91+I91 -> 993580.04
A92: 46031 | B92: C | C92: 0 | D92: 510 | E92: 7 | F92: Eduardo Cortes | H92: 83731.5 | J92: =J91-H92+I92 -> 909848.54
A93: 46032 | B93: I | C93: 75 | D93: 102 | F93: Vta.Tlmk Canindo Guadalupe Orozco | G93: 46022 | I93: 7120.97 | J93: =J92-H93+I93 -> 916969.51
A94: 46034 | B94: I | C94: 75 | D94: 102 | F94: Vta.tlmk Canindo Francisco Hernande | G94: 46003 | I94: 52600.46 | J94: =J93-H94+I94 -> 969569.97
A95: 46034 | B95: I | C95: 70 | D95: 102 | F95: Vta.Tlmk Ph Nueva Operadora | G95: 46030 | I95: 7088.47 | J95: =J94-H95+I95 -> 976658.44
A96: 46034 | B96: C | C96: 0 | D96: 510 | E96: 8 | F96: Marcas Nestle | H96: 288169.12 | J96: =J95-H96+I96 -> 688489.32
A97: 46034 | B97: C | C97: 0 | D97: 510 | E97: 9 | F97: Comercializadora Dulcera de Abastos | H97: 262567.2 | J97: =J96-H97+I97 -> 425922.12
A98: 46034 | B98: C | C98: 0 | D98: 510 | E98: 10 | F98: Hernan Manuel Valencia | H98: 239932.55 | J98: =J97-H98+I98 -> 185989.57
A99: 46034 | B99: C | C99: 0 | D99: 510 | E99: 11 | F99: Desechables Cece SA de CV | H99: 129999 | J99: =J98-H99+I99 -> 55990.57
A100: 46034 | B100: G | C100: 32 | D100: 612 | E100: 12 | F100: CFE | H100: 4735 | J100: =J99-H100+I100 -> 51255.57
A101: 46034 | B101: G | C101: 42 | D101: 612 | E101: 13 | F101: CFE | H101: 5956 | J101: =J100-H101+I101 -> 45299.57
A102: 46034 | B102: G | C102: 40 | D102: 612 | E102: 14 | F102: CFE | H102: 123 | J102: =J101-H102+I102 -> 45176.57
A103: 46034 | B103: G | C103: 50 | D103: 612 | E103: 15 | F103: CFE | H103: 6107 | J103: =J102-H103+I103 -> 39069.57
A104: 46035 | B104: I | C104: 10 | D104: 102 | F104: VENTAS PADRE HIDALGO | G104: 46030 | I104: 2200 | J104: =J103-H104+I104 -> 41269.57
A105: 46035 | B105: I | C105: 73 | D105: 102 | F105: Vta.Tlmk Morelia Marcelo Sandoval | G105: 46010 | I105: 42472 | J105: =J104-H105+I105 -> 83741.57
A106: 46035 | B106: I | C106: 73 | D106: 102 | F106: Vta.Tlmk Morelia Martin Suarez | G106: 45988 | I106: 32442.71 | J106: =J105-H106+I106 -> 116184.28
A107: 46035 | B107: I | D107: 102 | F107: Dep. Efectivo | I107: 5415.36 | J107: =J106-H107+I107 -> 121599.64
A108: 46035 | B108: I | C108: 73 | D108: 102 | F108: Vta.Tlmk Morelia Oscar Torres | G108: 46014 | I108: 17330 | J108: =J107-H108+I108 -> 138929.64
A109: 46035 | B109: I | C109: 73 | D109: 102 | F109: Vta.Tlmk Morelia Mayela Guevara | G109: 46002 | I109: 5000 | J109: =J108-H109+I109 -> 143929.64
A110: 46035 | B110: I | C110: 73 | D110: 102 | F110: Vta.Tlmk Morelia Elias Lemus | G110: 45988 | I110: 50670.1 | J110: =J109-H110+I110 -> 194599.74
A111: 46035 | B111: I | C111: 73 | D111: 102 | F111: Vta.Tlmk Morelia Elias Lemus | G111: 46030 | I111: 149817.73 | J111: =J110-H111+I111 -> 344417.47
A112: 46035 | B112: I | C112: 73 | D112: 102 | F112: VTA.TLMKT MORELIA JOSE ALEJANDRO | G112: 46025 | I112: 5156.71 | J112: =J111-H112+I112 -> 349574.18
A113: 46035 | B113: I | C113: 73 | D113: 102 | F113: Vta.Tlmk Morelia Karla Yissel | G113: 46007 | I113: 129925 | J113: =J112-H113+I113 -> 479499.18
A114: 46035 | B114: TI | D114: - | F114: TRASPASO ENTRE CTAS 6586 | I114: 170000 | J114: =J113-H114+I114 -> 649499.18
A115: 46035 | B115: C | C115: 30 | D115: 510 | E115: 16 | F115: Ferrero de Mexico SA de CV | H115: 644009.46 | J115: =J114-H115+I115 -> 5489.72
A116: 46036 | B116: I | C116: 73 | D116: 102 | F116: Vta.Tlmk Morelia Gerardo Molina | G116: 46018 | I116: 19643 | J116: =J115-H116+I116 -> 25132.72
A117: 46036 | B117: I | C117: 73 | D117: 102 | F117: Vta.Tlmk Morelia Maribel Angel | G117: 46028 | I117: 18784.7 | J117: =J116-H117+I117 -> 43917.42
A118: 46036 | B118: I | C118: 70 | D118: 102 | F118: Vta.Tlmk Ph Rosa Isela | G118: 46034 | I118: 9493 | J118: =J117-H118+I118 -> 53410.42
A119: 46036 | B119: I | C119: 70 | D119: 102 | F119: Vta.Tlmk Ph Jose Alberto Saldaña | G119: 46030 | I119: 48590 | J119: =J118-H119+I119 -> 102000.42
A120: 46036 | B120: I | C120: 73 | D120: 102 | F120: Vta.Tlmk Morelia Veronica Carrillo | G120: 46029 | I120: 19923 | J120: =J119-H120+I120 -> 121923.42
A121: 46036 | B121: I | C121: 70 | D121: 102 | F121: Vta.Tlmk Ph Ana Rosa Cerda | G121: 46020 | I121: 2340 | J121: =J120-H121+I121 -> 124263.42
...

Sheet BBVA 2182
A1: FECHA | B1: M | C1: S | D1: C | E1: # | F1: PROVEEDOR | G1: F VTA | H1: RETIRO | I1: DEPOSITO | J1: SALDO
A2: 46024 | B2: G | C2: 72 | D2: 612 | F2: PENALIZACION SDO PROM MIN | H2: 420 | J2: 92.8 | K2: =J2+H2-I2 -> 512.8
A3: 46024 | B3: G | C3: 72 | D3: 147 | F3: IVA | H3: 67.2 | J3: =J2-H3+I3 -> 25.6

Sheet BB 4166
A1: FECHA | B1: M | C1: S | D1: C | E1: # | F1: PROVEEDOR | G1: F VTA | H1: RETIRO | I1: DEPOSITO | J1: SALDO
A2: 46023 | B2: G | D2: 613 | F2: Compra - Disposicion por POS por (602.45) mxn en SERV TAVISA GASOL 31dic2025 RFC EST 161221BS3 Tarjeta 5161020004397545 Recibo # 4394923032322 | H2: 602.45 | J2: 136786.88 | K2: =J2+H2-I2 -> 137389.33
A3: 46023 | B3: G | D3: 613 | F3: Compra - Disposicion por POS por (463.00) mxn en PZA COBRO PANINDICUARO 31dic2025 RFC HMI 950125KG8 Tarjeta 5161020003551118 Recibo # 4394924032322 | H3: 463 | J3: =J2-H3+I3 -> 136323.88
A4: 46023 | B4: G | D4: 613 | F4: Compra - Disposicion por POS por (463.00) mxn en PZA COBRO PANINDICUARO 31dic2025 RFC HMI 950125KG8 Tarjeta 5161020003551118 Recibo # 4394924032322 | H4: 463 | J4: =J3-H4+I4 -> 135860.88
A5: 46023 | B5: G | D5: 613 | F5: Compra - Disposicion por POS por (1,000.00) mxn en LA QUEMADA GAS 31dic2025 RFC SQU 060616TQ1 Tarjeta 5161020003551084 Recibo # 4394926032322 | H5: 1000 | J5: =J4-H5+I5 -> 134860.88
A6: 46023 | B6: G | D6: 613 | F6: Compra - Disposicion por POS por (3,478.60) mxn en GASOL DEL VALLE 31dic2025 RFC GVZ 970421PJ7 Tarjeta 5161020003411909 Recibo # 4394927032322 | H6: 3478.6 | J6: =J5-H6+I6 -> 131382.28
A7: 46023 | B7: G | D7: 613 | F7: Compra - Disposicion por POS por (1,314.20) mxn en SUPER SERV GARBRI 31dic2025 RFC SSG 981118LR6 Tarjeta 5161020003551126 Recibo # 4394928032322 | H7: 1314.2 | J7: =J6-H7+I7 -> 130068.08
A8: 46023 | B8: G | D8: 613 | F8: Compra - Disposicion por POS por (1,568.80) mxn en SUPER SERV GARBRI 31dic2025 RFC SSG 981118LR6 Tarjeta 5161020003551126 Recibo # 4394929032322 | H8: 1568.8 | J8: =J7-H8+I8 -> 128499.28
A9: 46023 | B9: G | D9: 613 | F9: Compra - Disposicion por POS por (751.53) mxn en SUPER SERV GARBRI 31dic2025 RFC SSG 981118LR6 Tarjeta 5161020003884857 Recibo # 4394930032322 | H9: 751.53 | J9: =J8-H9+I9 -> 127747.75
A10: 46023 | B10: G | D10: 613 | F10: Compra - Disposicion por POS por (746.02) mxn en SUPER SERV GARBRI 31dic2025 RFC SSG 981118LR6 Tarjeta 5161020003884857 Recibo # 4394931032322 | H10: 746.02 | J10: =J9-H10+I10 -> 127001.73
A11: 46023 | B11: G | D11: 613 | F11: Compra - Disposicion por POS por (1,486.63) mxn en SUPER SERV GARBRI 31dic2025 RFC SSG 981118LR6 Tarjeta 5161020003551118 Recibo # 4394932032322 | H11: 1486.63 | J11: =J10-H11+I11 -> 125515.1
A12: 46023 | B12: G | D12: 613 | F12: Compra - Disposicion por POS por (379.93) mxn en LA QUEMADA GAS 31dic2025 RFC SQU 060616TQ1 Tarjeta 5161020003551084 Recibo # 4394933032322 | H12: 379.93 | J12: =J11-H12+I12 -> 125135.17
A13: 46024 | B13: G | D13: 613 | F13: Compra - Disposicion por POS por (3,161.18) mxn en SUPER SERV GARBRI 01ene2026 RFC SSG 981118LR6 Tarjeta 5161020003884857 Recibo # 4412406032322 | H13: 3161.18 | J13: =J12-H13+I13 -> 121973.99
A14: 46024 | B14: G | D14: 613 | F14: Compra - Disposicion por POS por (3,308.94) mxn en SUPER SERV GARBRI 01ene2026 RFC SSG 981118LR6 Tarjeta 5161020003551118 Recibo # 4412407032322 | H14: 3308.94 | J14: =J13-H14+I14 -> 118665.05
A15: 46024 | B15: I | C15: 51 | D15: 102 | F15: VENTAS RD CANINDO | G15: 46022 | I15: 10049.96 | J15: =J14-H15+I15 -> 128715.01
A16: 46024 | B16: I | C16: 51 | D16: 102 | F16: VENTAS RD CANINDO | G16: 46022 | I16: 10128.03 | J16: =J15-H16+I16 -> 138843.04
A17: 46024 | B17: I | C17: 51 | D17: 102 | F17: VENTAS RD CANINDO | G17: 46022 | I17: 14933.53 | J17: =J16-H17+I17 -> 153776.57
A18: 46024 | B18: I | C18: 51 | D18: 102 | F18: VENTAS RD CANINDO | G18: 46022 | I18: 9146.72 | J18: =J17-H18+I18 -> 162923.29
A19: 46024 | B19: G | D19: 610 | E19: 1 | F19: Nomina 01 | H19: 10613.6 | J19: =J18-H19+I19 -> 152309.69
A20: 46024 | B20: G | D20: 610 | E20: 2 | F20: Nomina 01 | H20: 7766.4 | J20: =J19-H20+I20 -> 144543.29
A21: 46024 | B21: TE | D21: - | F21: TRASPASO A BTE 7744 | H21: 100000 | J21: =J20-H21+I21 -> 44543.29
A22: 46024 | B22: G | D22: 612 | F22: Comision | H22: 0 | J22: =J21-H22+I22 -> 44543.29
A23: 46024 | B23: G | D23: 147 | F23: Iva | H23: 0 | J23: =J22-H23+I23 -> 44543.29
A24: 46024 | B24: TI | D24: - | F24: TRASPASO ENTRE CTAS 854 | I24: 50000 | J24: =J23-H24+I24 -> 94543.29
A25: 46024 | B25: G | D25: 610 | E25: 3 | F25: Nomina 01 | H25: 3884.6 | J25: =J24-H25+I25 -> 90658.69
A26: 46024 | B26: G | D26: 610 | E26: 4 | F26: Nomina 01 | H26: 6281.2 | J26: =J25-H26+I26 -> 84377.49
A27: 46024 | B27: TI | D27: - | F27: TRASPASO ENTRE CTAS 366 | I27: 35000 | J27: =J26-H27+I27 -> 119377.49
A28: 46024 | B28: TI | D28: - | F28: TRASPASO DE SNTDR 2169 | I28: 450000 | J28: =J27-H28+I28 -> 569377.49
A29: 46024 | B29: TI | D29: - | F29: TRASPASO DE SNTDR 1604 | I29: 430000 | J29: =J28-H29+I29 -> 999377.49
A30: 46025 | B30: G | C30: 72 | D30: 612 | F30: Administración de Tarjeta Adicional | H30: 200 | J30: =J29-H30+I30 -> 999177.49
A31: 46025 | B31: G | C31: 72 | D31: 147 | F31: IVA | H31: 32 | J31: =J30-H31+I31 -> 999145.49
A32: 46025 | B32: G | D32: 613 | F32: Compra - Disposicion por POS por (500.00) mxn en SERV TAVISA GASOL02ene2026 RFC EST 161221BS3 Tarjeta 5161020004397552 Recibo # 4432659032322 | H32: 500 | J32: =J31-H32+I32 -> 998645.49
A33: 46025 | B33: G | D33: 613 | F33: Compra - Disposicion por POS por (699.12) mxn en GASOL DEL VALLE 02ene2026 RFC GVZ 970421PJ7 Tarjeta 5161020003411883 Recibo # 4432660032322 | H33: 699.12 | J33: =J32-H33+I33 -> 997946.37
A34: 46025 | B34: G | D34: 613 | F34: Compra - Disposicion por POS por (2,480.93) mxn en GASOL DEL VALLE 02ene2026 RFC GVZ 970421PJ7 Tarjeta 5161020004397602 Recibo # 4432661032322 | H34: 2480.93 | J34: =J33-H34+I34 -> 995465.44
A35: 46025 | B35: G | D35: 613 | F35: Compra - Disposicion por POS por (1,144.03) mxn en SERV TAVISA GASOL 02ene2026 RFC EST 161221BS3 Tarjeta 5161020004397537 Recibo # 4432662032322 | H35: 1144.03 | J35: =J34-H35+I35 -> 994321.41
A36: 46025 | B36: G | D36: 613 | F36: Compra - Disposicion por POS por (1,420.87) mxn en SERV TAVISA GASOL 02ene2026 RFC EST 161221BS3 Tarjeta 5161020004397560 Recibo # 4432663032322 | H36: 1420.87 | J36: =J35-H36+I36 -> 992900.54
A37: 46025 | B37: G | D37: 613 | F37: Compra - Disposicion por POS por (730.03) mxn en SERV NORAMA 02ene2026 RFC SNO 971210G06 Tarjeta 5161020003411909 Recibo # 4432664032322 | H37: 730.03 | J37: =J36-H37+I37 -> 992170.51
A38: 46025 | B38: G | D38: 613 | F38: Compra - Disposicion por POS por (445.32) mxn en DIST GAS NOEL 02ene2026 RFC DGN 811026BU6 Tarjeta 5161020003551118 Recibo # 4432665032322 | H38: 445.32 | J38: =J37-H38+I38 -> 991725.19
A39: 46025 | B39: G | D39: 613 | F39: Compra - Disposicion por POS por (1,504.28) mxn en SERV TAVISA GASOL 02ene2026 RFC EST 161221BS3 Tarjeta 5161020004397560 Recibo # 4432666032322 | H39: 1504.28 | J39: =J38-H39+I39 -> 990220.91
A40: 46025 | B40: G | D40: 613 | F40: Compra - Disposicion por POS por (1,157.81) mxn en GASOL DEL VALLE 02ene2026 RFC GVZ 970421PJ7 Tarjeta 5161020004397636 Recibo # 4432667032322 | H40: 1157.81 | J40: =J39-H40+I40 -> 989063.1
A41: 46025 | B41: G | D41: 613 | F41: Compra - Disposicion por POS por (439.09) mxn en DIST GAS NOEL 02ene2026 RFC DGN 811026BU6 Tarjeta 5161020003551118 Recibo # 4432668032322 | H41: 439.09 | J41: =J40-H41+I41 -> 988624.01
A42: 46025 | B42: G | D42: 613 | F42: Compra - Disposicion por POS por (258.00) mxn en GASOL DEL VALLE 02ene2026 RFC GVZ 970421PJ7 Tarjeta 5161020004397602 Recibo # 4432669032322 | H42: 258 | J42: =J41-H42+I42 -> 988366.01
A43: 46025 | B43: G | D43: 613 | F43: Compra - Disposicion por POS por (1,001.95) mxn en SERV TAVISA GASOL 02ene2026 RFC EST 161221BS3 Tarjeta 5161020004397545 Recibo # 4432670032322 | H43: 1001.95 | J43: =J42-H43+I43 -> 987364.06
... A45: 46025 | B45: G | D45: 613 | F45: Compra - Disposicion por POS por (1,147.47) mxn en SERV TAVISA GASOL 02ene2026 RFC EST 161221BS3 Tarjeta 5161020004397545 Recibo # 4432672032322 | H45: 1147.47 | J45: =J44-H45+I45 -> 984892.29
A46: 46025 | B46: G | C46: 38 | D46: 613 | F46: Compra - Disposicion por POS por (8,920.46) mxn en 5161020003884972 PAYU *GOOGLE CLOUD Tarjeta Sub:0 Unit:0916024 Com:9518348 Recibo # 4432673032322 | H46: 8920.46 | J46: =J45-H46+I46 -> 975971.83
A47: 46026 | B47: G | D47: 613 | F47: Compra - Disposicion por POS por (629.98) mxn en SUPER SERV GARBRI 03ene2026 RFC SSG 981118LR6 Tarjeta 5161020004397511 Recibo # 4453872032322 | H47: 629.98 | J47: =J46-H47+I47 -> 975341.85
A48: 46026 | B48: G | D48: 613 | F48: Compra - Disposicion por POS por (1,572.00) mxn en SUPER SERV GARBRI 03ene2026 RFC SSG 981118LR6 Tarjeta 5161020003884865 Recibo # 4453873032322 | H48: 1572 | J48: =J47-H48+I48 -> 973769.85
A49: 46026 | B49: G | C49: 12 | D49: 613 | F49: Compra - Disposicion por POS por (251.00) mxn en PZA COBRO PANINDICUARO 03ene2026 RFC HMI 950125KG8 Tarjeta 5161020004397578 Recibo # 4453874032322 | H49: 251 | J49: =J48-H49+I49 -> 973518.85
A50: 46026 | B50: G | D50: 613 | F50: Compra - Disposicion por POS por (318.44) mxn en SUPER SERV GARBRI 03ene2026 RFC SSG 981118LR6 Tarjeta 5161020003884857 Recibo # 4453875032322 | H50: 318.44 | J50: =J49-H50+I50 -> 973200.41
A51: 46026 | B51: G | D51: 613 | F51: Compra - Disposicion por POS por (1,500.00) mxn en SUPER SERV GARBRI 03ene2026 RFC SSG 981118LR6 Tarjeta 5161020003551076 Recibo # 4453876032322 | H51: 1500 | J51: =J50-H51+I51 -> 971700.41
A52: 46026 | B52: G | D52: 613 | F52: Compra - Disposicion por POS por (1,394.76) mxn en SUPER SERV GARBRI 03ene2026 RFC SSG 981118LR6 Tarjeta 5161020003884881 Recibo # 4453877032322 | H52: 1394.76 | J52: =J51-H52+I52 -> 970305.65
A53: 46026 | B53: G | D53: 613 | F53: Compra - Disposicion por POS por (1,395.68) mxn en SERV TAVISA GASOL 03ene2026 RFC EST 161221BS3 Tarjeta 5161020004397560 Recibo # 4453878032322 | H53: 1395.68 | J53: =J52-H53+I53 -> 968909.97
A54: 46026 | B54: G | D54: 613 | F54: Compra - Disposicion por POS por (1,027.54) mxn en SERVICIO SOLCER 03ene2026 RFC SSO 990608F67 Tarjeta 5161020004397610 Recibo # 4453879032322 | H54: 1027.54 | J54: =J53-H54+I54 -> 967882.43
A55: 46026 | B55: G | D55: 613 | F55: Compra - Disposicion por POS por (1,144.64) mxn en SUPER SERV GARBRI 03ene2026 RFC SSG 981118LR6 Tarjeta 5161020003411891 Recibo # 4453880032322 | H55: 1144.64 | J55: =J54-H55+I55 -> 966737.79
A56: 46026 | B56: G | D56: 613 | F56: Compra - Disposicion por POS por (500.00) mxn en GASOL DEL VALLE 03ene2026 RFC GVZ 970421PJ7 Tarjeta 5161020003411909 Recibo # 4453881032322 | H56: 500 | J56: =J55-H56+I56 -> 966237.79
A57: 46026 | B57: G | D57: 613 | F57: Compra - Disposicion por POS por (480.38) mxn en SUPER SERV GARBRI 03ene2026 RFC SSG 981118LR6 Tarjeta 5161020003551134 Recibo # 4453882032322 | H57: 480.38 | J57: =J56-H57+I57 -> 965757.41
A58: 46026 | B58: G | C58: 12 | D58: 613 | F58: Compra - Disposicion por POS por (251.00) mxn en PZA COBRO PANINDICUARO 03ene2026 RFC HMI 950125KG8 Tarjeta 5161020004397578 Recibo # 4453874032322 | H58: 251 | J58: =J57-H58+I58 -> 965506.41
A59: 46026 | B59: G | D59: 613 | F59: Compra - Disposicion por POS por (1,510.74) mxn en SUPER SERV GARBRI 03ene2026 RFC SSG 981118LR6 Tarjeta 5161020003884840 Recibo # 4453884032322 | H59: 1510.74 | J59: =J58-H59+I59 -> 963995.67
A60: 46026 | B60: G | D60: 613 | F60: Compra - Disposicion por POS por (773.94) mxn en SUPER SERV GARBRI 03ene2026 RFC SSG 981118LR6 Tarjeta 5161020003884865 Recibo # 4453885032322 | H60: 773.94 | J60: =J59-H60+I60 -> 963221.73
A61: 46026 | B61: G | D61: 613 | F61: Compra - Disposicion por POS por (2,264.65) mxn en SUPER SERV GARBRI 03ene2026 RFC SSG 981118LR6 Tarjeta 5161020003884857 Recibo # 4453886032322 | H61: 2264.65 | J61: =J60-H61+I61 -> 960957.08
A62: 46026 | B62: G | D62: 613 | F62: Compra - Disposicion por POS por (867.15) mxn en SUPER SERV GARBRI 03ene2026 RFC SSG 981118LR6 Tarjeta 5161020003884949 Recibo # 4453887032322 | H62: 867.15 | J62: =J61-H62+I62 -> 960089.93
A63: 46026 | B63: G | D63: 613 | F63: Compra - Disposicion por POS por (1,098.81) mxn en SUPER SERV GARBRI 03ene2026 RFC SSG 981118LR6 Tarjeta 5161020003884915 Recibo # 4453888032322 | H63: 1098.81 | J63: =J62-H63+I63 -> 958991.12
A64: 46026 | B64: G | D64: 613 | F64: Compra - Disposicion por POS por (928.15) mxn en SUPER SERV GARBRI 03ene2026 RFC SSG 981118LR6 Tarjeta 5161020003884865 Recibo # 4453889032322 | H64: 928.15 | J64: =J63-H64+I64 -> 958062.97
A65: 46026 | B65: G | D65: 613 | F65: Compra - Disposicion por POS por (3,750.43) mxn en SUPER SERV GARBRI 03ene2026 RFC SSG 981118LR6 Tarjeta 5161020003551126 Recibo # 4453890032322 | H65: 3750.43 | J65: =J64-H65+I65 -> 954312.54
A66: 46027 | B66: C | C66: 0 | D66: 510 | E66: 5032 | F66: Grupo Industrial Sweets | H66: 432422.92 | J66: =J65-H66+I66 -> 521889.62
A67: 46027 | B67: C | C67: 0 | D67: 510 | E67: 5019 | F67: Procesadora de Alimentos Cale | H67: 304089.13 | J67: =J66-H67+I67 -> 217800.49
A68: 46027 | B68: C | C68: 0 | D68: 510 | E68: 5026 | F68: J&F Enterprice | H68: 121174.1 | J68: =J67-H68+I68 -> 96626.39
A69: 46027 | B69: C | C69: 0 | D69: 510 | E69: 5021 | F69: Confitados Finos Comercial | H69: 68557.07 | J69: =J68-H69+I69 -> 28069.32
A70: 46027 | B70: G | D70: 613 | F70: Compra - Disposicion por POS por (120.00) mxn en REFACC GONZA 04ene2026 RFC GOAI871216N61 Tarjeta 5161020003884840 Recibo # 4475628032322 | H70: 120 | J70: =J69-H70+I70 -> 27949.32
A71: 46027 | B71: G | D71: 613 | F71: Compra - Disposicion por POS por (406.20) mxn en SUPER SERV GARBRI 04ene2026 RFC SSG 981118LR6 Tarjeta 5161020003551134 Recibo # 4475629032322 | H71: 406.2 | J71: =J70-H71+I71 -> 27543.12
A72: 46027 | B72: G | D72: 613 | F72: Compra - Disposicion por POS por (5,810.00) mxn en REFACC GONZA 04ene2026 RFC GOAI871216N61 Tarjeta 5161020003884840 Recibo # 4475630032322 | H72: 5810 | J72: =J71-H72+I72 -> 21733.12
A73: 46027 | B73: G | D73: 613 | F73: Compra - Disposicion por POS por (924.05) mxn en LA QUEMADA GAS 04ene2026 RFC SQU 060616TQ1 Tarjeta 5161020003551084 Recibo # 4475631032322 | H73: 924.05 | J73: =J72-H73+I73 -> 20809.07
A74: 46027 | B74: G | D74: 613 | F74: Compra - Disposicion por POS por (282.51) mxn en SUPER SERV GARBRI 04ene2026 RFC SSG 981118LR6 Tarjeta 5161020003551134 Recibo # 4475632032322 | H74: 282.51 | J74: =J73-H74+I74 -> 20526.56
A75: 46027 | B75: G | D75: 613 | F75: Compra - Disposicion por POS por (500.00) mxn en SERV GAS LA QUEMADA 04ene2026 RFC SQU 060616TQ1 Tarjeta 5161020003551084 Recibo # 4475633032322 | H75: 500 | J75: =J74-H75+I75 -> 20026.56
A76: 46027 | B76: G | D76: 613 | F76: Compra - Disposicion por POS por (2,181.67) mxn en SUPER SERV GARBRI 04ene2026 RFC SSG 981118LR6 Tarjeta 5161020003884857 Recibo # 4475634032322 | H76: 2181.67 | J76: =J75-H76+I76 -> 17844.89
A77: 46027 | B77: I | C77: 51 | D77: 102 | F77: VENTAS RD CANINDO | G77: 46025 | I77: 11725.39 | J77: =J76-H77+I77 -> 29570.28
A78: 46027 | B78: I | C78: 51 | D78: 102 | F78: VENTAS RD CANINDO | G78: 46025 | I78: 19021.1 | J78: =J77-H78+I78 -> 48591.38
A79: 46027 | B79: I | C79: 51 | D79: 102 | F79: VENTAS RD CANINDO | G79: 46025 | I79: 13101.08 | J79: =J78-H79+I79 -> 61692.46
A80: 46027 | B80: I | C80: 51 | D80: 102 | F80: VENTAS RD CANINDO | G80: 46025 | I80: 12116.4 | J80: =J79-H80+I80 -> 73808.86
A81: 46027 | B81: I | C81: 51 | D81: 102 | F81: VENTAS RD CANINDO | G81: 46024 | I81: 18988.75 | J81: =J80-H81+I81 -> 92797.61
A82: 46027 | B82: I | C82: 51 | D82: 102 | F82: VENTAS RD CANINDO | G82: 46024 | I82: 24074.56 | J82: =J81-H82+I82 -> 116872.17
A83: 46027 | B83: I | C83: 51 | D83: 102 | F83: VENTAS RD CANINDO | G83: 46024 | I83: 26142.31 | J83: =J82-H83+I83 -> 143014.48
A84: 46027 | B84: I | C84: 51 | D84: 102 | F84: VENTAS RD CANINDO | G84: 46024 | I84: 20822.71 | J84: =J83-H84+I84 -> 163837.19
A85: 46027 | B85: TI | D85: - | F85: TRASPASO ENTRE CUENTAS DE BB 854 | I85: 145000 | J85: =J84-H85+I85 -> 308837.19
A86: 46027 | B86: TI | D86: - | F86: TRASPASO ENTRE CUENTAS DE BB 506 | I86: 210000 | J86: =J85-H86+I86 -> 518837.19
A87: 46028 | B87: C | C87: 0 | D87: 510 | E87: 5027 | F87: Nancy Karina Acosta Gutierrez | H87: 38305.04 | J87: =J86-H87+I87 -> 480532.15
A88: 46028 | B88: G | D88: 613 | F88: Compra - Disposicion por POS por (440.00) mxn en PZA COBRO OCOTLAN05ene2026 RFC HMI 950125KG8 Tarjeta 5161020003884840 | H88: 440 | J88: =J87-H88+I88 -> 480092.15
A89: 46028 | B89: G | D89: 613 | F89: Compra - Disposicion por POS por (906.15) mxn en GASOL DEL VALLE05ene2026 RFC GVZ 970421PJ7 Tarjeta 5161020004397636 | H89: 906.15 | J89: =J88-H89+I89 -> 479186
A90: 46028 | B90: G | D90: 613 | F90: Compra - Disposicion por POS por (899.07) mxn en GASOL DEL VALLE05ene2026 RFC GVZ 970421PJ7 Tarjeta 5161020003884907 | H90: 899.07 | J90: =J89-H90+I90 -> 478286.93
A91: 46028 | B91: G | D91: 613 | F91: Compra - Disposicion por POS por (250.02) mxn en GASOL LA QUEMADA05ene2026 RFC SQU 060616TQ1 Tarjeta 5161020003551084 | H91: 250.02 | J91: =J90-H91+I91 -> 478036.91
A92: 46028 | B92: G | D92: 613 | F92: Compra - Disposicion por POS por (160.00) mxn en PZA COBRO ECUANDUREO05ene2026 RFC HMI 950125KG8 Tarjeta 5161020003884840 | H92: 160 | J92: =J91-H92+I92 -> 477876.91
A93: 46028 | B93: G | D93: 613 | F93: Compra - Disposicion por POS por (700.00) mxn en GASOL RAMIREZ05ene2026 RFC CUBE591124EI0 Tarjeta 5161020004397586 | H93: 700 | J93: =J92-H93+I93 -> 477176.91
A94: 46028 | B94: G | D94: 613 | F94: Compra - Disposicion por POS por (68.00) mxn en GASOL DEL VALLE05ene2026 RFC GVZ 970421PJ7 Tarjeta 5161020004397636 | H94: 68 | J94: =J93-H94+I94 -> 477108.91
A95: 46028 | B95: G | D95: 613 | F95: Compra - Disposicion por POS por (810.55) mxn en SERV TAVISA GASOL05ene2026 RFC EST 161221BS3 Tarjeta 5161020004397545 | H95: 810.55 | J95: =J94-H95+I95 -> 476298.36
A96: 46028 | B96: G | D96: 613 | F96: Compra - Disposicion por POS por (658.41) mxn en GASOL DEL VALLE05ene2026 RFC GVZ 970421PJ7 Tarjeta 5161020003411883 | H96: 658.41 | J96: =J95-H96+I96 -> 475639.95
A97: 46028 | B97: G | D97: 613 | F97: Compra - Disposicion por POS por (2,454.00) mxn en SAM S CLUB MORELIA05ene2026 RFC NWM 9709244W4 Tarjeta 5161020004397552 | H97: 2454 | J97: =J96-H97+I97 -> 473185.95
A98: 46028 | B98: G | D98: 613 | F98: Compra - Disposicion por POS por (105.00) mxn en GASOL DEL VALLE05ene2026 RFC GVZ 970421PJ7 Tarjeta 5161020003884907 | H98: 105 | J98: =J97-H98+I98 -> 473080.95
A99: 46028 | B99: G | D99: 613 | F99: Compra - Disposicion por POS por (1,015.14) mxn en GASOL DEL VALLE05ene2026 RFC GVZ 970421PJ7 Tarjeta 5161020004397610 | H99: 1015.14 | J99: =J98-H99+I99 -> 472065.81
... A102: 46028 | B102: G | D102: 613 | F102: Compra - Disposicion por POS por (440.00) mxn en PZA COBRO OCOTLAN05ene2026 RFC HMI 950125KG8 Tarjeta 5161020003884840 | H102: 440 | J102: =J101-H102+I102 -> 469161.45
A103: 46028 | B103: I | C103: 51 | D103: 102 | F103: VENTAS CANINDO | G103: 38722 | I103: 22354.76 | J103: =J102-H103+I103 -> 491516.21
...

Sheet BB 854
A1: FECHA | B1: M | C1: S | D1: C | E1: # | F1: PROVEEDOR | G1: F VTA | H1: RETIRO | I1: DEPOSITO | J1: SALDO
A2: 46023 | B2: I | C2: 54 | D2: 102 | F2: venta zamora centro tarjeta | G2: 46022 | I2: 4445.59 | J2: 4987.04 | K2: =J2+H2-I2 -> 541.45
A3: 46023 | B3: G | D3: 612 | F3: Comision | H3: 71.11 | J3: =J2-H3+I3 -> 4915.93
A4: 46023 | B4: G | D4: 147 | F4: Iva | H4: 11.38 | J4: =J3-H4+I4 -> 4904.55
A5: 46023 | B5: I | C5: 54 | D5: 102 | F5: venta zamora centro tarjeta | G5: 46022 | I5: 6053.79 | J5: =J4-H5+I5 -> 10958.34
A6: 46023 | B6: G | D6: 612 | F6: Comision | H6: 115.03 | J6: =J5-H6+I6 -> 10843.31
A7: 46023 | B7: G | D7: 147 | F7: Iva | H7: 18.4 | J7: =J6-H7+I7 -> 10824.91
A8: 46024 | B8: I | C8: 54 | D8: 102 | F8: venta zamora centro | G8: 46022 | I8: 39415 | J8: =J7-H8+I8 -> 50239.91
A9: 46024 | B9: TE | D9: - | F9: TRASPASO ENTRE CTAS 4166 | H9: 50000 | J9: =J8-H9+I9 -> 239.91
A10: 46025 | B10: I | C10: 54 | D10: 102 | F10: venta zamora centro tarjeta | G10: 46024 | I10: 1282.81 | J10: =J9-H10+I10 -> 1522.72
A11: 46025 | B11: G | D11: 612 | F11: Comision | H11: 20.52 | J11: =J10-H11+I11 -> 1502.2
A12: 46025 | B12: G | D12: 147 | F12: Iva | H12: 3.28 | J12: =J11-H12+I12 -> 1498.92
A13: 46025 | B13: I | C13: 54 | D13: 102 | F13: venta zamora centro tarjeta | G13: 46024 | I13: 1232.08 | J13: =J12-H13+I13 -> 2731
A14: 46025 | B14: G | D14: 612 | F14: Comision | H14: 23.41 | J14: =J13-H14+I14 -> 2707.59
A15: 46025 | B15: G | D15: 147 | F15: Iva | H15: 3.75 | J15: =J14-H15+I15 -> 2703.84
A16: 46026 | B16: I | C16: 54 | D16: 102 | F16: venta zamora centro tarjeta | G16: 46025 | I16: 2844.87 | J16: =J15-H16+I16 -> 5548.71
A17: 46026 | B17: G | D17: 612 | F17: Comision | H17: 54.06 | J17: =J16-H17+I17 -> 5494.65
A18: 46026 | B18: G | D18: 147 | F18: Iva | H18: 8.65 | J18: =J17-H18+I18 -> 5486
A19: 46026 | B19: I | C19: 54 | D19: 102 | F19: venta zamora centro tarjeta | G19: 46025 | I19: 894.84 | J19: =J18-H19+I19 -> 6380.84
A20: 46026 | B20: G | D20: 612 | F20: Comision | H20: 14.31 | J20: =J19-H20+I20 -> 6366.53
A21: 46026 | B21: G | D21: 147 | F21: Iva | H21: 2.29 | J21: =J20-H21+I21 -> 6364.24
A22: 46027 | B22: I | C22: 54 | D22: 102 | F22: venta zamora centro tarjeta | G22: 46026 | I22: 1479.25 | J22: =J21-H22+I22 -> 7843.49
A23: 46027 | B23: G | D23: 612 | F23: Comision | H23: 23.67 | J23: =J22-H23+I23 -> 7819.82
A24: 46027 | B24: G | D24: 147 | F24: Iva | H24: 3.79 | J24: =J23-H24+I24 -> 7816.03
A25: 46027 | B25: I | C25: 54 | D25: 102 | F25: venta zamora centro | G25: 46026 | I25: 1032.31 | J25: =J24-H25+I25 -> 8848.34
A26: 46027 | B26: G | D26: 612 | F26: Comision | H26: 19.62 | J26: =J25-H26+I26 -> 8828.72
A27: 46027 | B27: G | D27: 147 | F27: Iva | H27: 3.14 | J27: =J26-H27+I27 -> 8825.58
A28: 46027 | B28: I | C28: 54 | D28: 102 | F28: venta zamora centro | G28: 46024 | I28: 37178.5 | J28: =J27-H28+I28 -> 46004.08
A29: 46027 | B29: I | C29: 54 | D29: 102 | F29: venta zamora centro | G29: 46025 | I29: 46778 | J29: =J28-H29+I29 -> 92782.08
A30: 46027 | B30: I | C30: 54 | D30: 102 | F30: vemta zamora centro | G30: 46026 | I30: 39030 | J30: =J29-H30+I30 -> 131812.08
A31: 46027 | B31: I | C31: 50 | D31: 102 | F31: VENTAS CANINDO | G31: 46032 | I31: 350 | J31: =J30-H31+I31 -> 132162.08
A32: 46027 | B32: I | C32: 50 | D32: 102 | F32: VENTAS CANINDO | G32: 46029 | I32: 5823.5 | J32: =J31-H32+I32 -> 137985.58
A33: 46027 | B33: I | C33: 50 | D33: 102 | F33: VENTAS CANINDO | G33: 46029 | I33: 2967.5 | J33: =J32-H33+I33 -> 140953.08
A34: 46027 | B34: I | C34: 50 | D34: 102 | F34: VENTAS CANINDO | G34: 46029 | I34: 1631.5 | J34: =J33-H34+I34 -> 142584.58
A35: 46027 | B35: I | C35: 50 | D35: 102 | F35: VENTAS CANINDO | G35: 46029 | I35: 526.5 | J35: =J34-H35+I35 -> 143111.08
A36: 46027 | B36: I | C36: 54 | D36: 102 | F36: VENTA ZAMORA CENTRO | I36: 6729.5 | J36: =J35-H36+I36 -> 149840.58
A37: 46027 | B37: TE | D37: - | F37: TRASPASO ENTRE CUENTAS DE BB 201 | H37: 145000 | J37: =J36-H37+I37 -> 4840.58
A38: 46028 | B38: I | C38: 54 | D38: 102 | F38: venta zamora centro tarjeta | G38: 46027 | I38: 3508.23 | J38: =J37-H38+I38 -> 8348.81
A39: 46028 | B39: G | D39: 612 | F39: Comision | H39: 56.13 | J39: =J38-H39+I39 -> 8292.68
A40: 46028 | B40: G | D40: 147 | F40: Iva | H40: 8.98 | J40: =J39-H40+I40 -> 8283.7
A41: 46028 | B41: I | C41: 54 | D41: 102 | F41: venta zamora centro tarjeta | G41: 46027 | I41: 6458 | J41: =J40-H41+I41 -> 14741.7
A42: 46028 | B42: G | D42: 612 | F42: Comision | H42: 122.69 | J42: =J41-H42+I42 -> 14619.01
A43: 46028 | B43: G | D43: 147 | F43: Iva | H43: 19.63 | J43: =J42-H43+I43 -> 14599.38
A44: 46028 | B44: TE | D44: - | F44: TRASPASO ENTRE CTAS 4166 | H44: 14000 | J44: =J43-H44+I44 -> 599.38
A45: 46029 | B45: I | C45: 54 | D45: 102 | F45: venta zamora centro tarjeta | G45: 46028 | I45: 2216.44 | J45: =J44-H45+I45 -> 2815.82
A46: 46029 | B46: G | D46: 612 | F46: Comision | H46: 35.46 | J46: =J45-H46+I46 -> 2780.36
A47: 46029 | B47: G | D47: 147 | F47: Iva | H47: 5.67 | J47: =J46-H47+I47 -> 2774.69
A48: 46029 | B48: I | C48: 54 | D48: 102 | F48: venta zamora centro tarjeta | G48: 46028 | I48: 3708.64 | J48: =J47-H48+I48 -> 6483.33
A49: 46029 | B49: G | D49: 612 | F49: Comision | H49: 70.46 | J49: =J48-H49+I49 -> 6412.87
A50: 46029 | B50: G | D50: 147 | F50: Iva | H50: 11.27 | J50: =J49-H50+I50 -> 6401.6
A51: 46029 | B51: I | C51: 54 | D51: 102 | F51: VENTA DE ZAMORA CENTRO | G51: 46028 | I51: 31755.5 | J51: =J50-H51+I51 -> 38157.1
A52: 46029 | B52: I | C52: 54 | D52: 102 | F52: VENTA DE ZAMORA CENTRO | G52: 46027 | I52: 66706 | J52: =J51-H52+I52 -> 104863.1
A53: 46030 | B53: I | C53: 54 | D53: 102 | F53: VENTA ZAMORA CENTRO TARJETA | G53: 46029 | I53: 12572.46 | J53: =J52-H53+I53 -> 117435.56
A54: 46030 | B54: G | D54: 612 | F54: Comision | H54: 238.88 | J54: =J53-H54+I54 -> 117196.68
A55: 46030 | B55: G | D55: 147 | F55: Iva | H55: 38.22 | J55: =J54-H55+I55 -> 117158.46
A56: 46030 | B56: I | C56: 54 | D56: 102 | F56: VENTA ZAMORA CENTRO TARJETA | G56: 46029 | I56: 1027.13 | J56: =J55-H56+I56 -> 118185.59
A57: 46030 | B57: G | D57: 612 | F57: Comision | H57: 16.43 | J57: =J56-H57+I57 -> 118169.16
A58: 46030 | B58: G | D58: 147 | F58: Iva | H58: 2.63 | J58: =J57-H58+I58 -> 118166.53
A59: 46030 | B59: TI | D59: - | F59: TRASPASO ENTRE CTAS 506 | I59: 100000 | J59: =J58-H59+I59 -> 218166.53
A60: 46030 | B60: TI | D60: - | F60: TRASPASO ENTRE CTAS 366 | I60: 195000 | J60: =J59-H60+I60 -> 413166.53
A61: 46030 | B61: C | C61: 10 | D61: 510 | E61: 1 | F61: Ferrero de Mexico | H61: 299973.55 | J61: =J60-H61+I61 -> 113192.98
A62: 46030 | B62: G | D62: 612 | F62: Comision | H62: 0 | J62: =J61-H62+I62 -> 113192.98
A63: 46030 | B63: G | D63: 147 | F63: Iva | H63: 0 | J63: =J62-H63+I63 -> 113192.98
A64: 46030 | B64: C | C64: 50 | D64: 510 | E64: 2 | F64: Ferrero de Mexico | H64: 76152.86 | J64: =J63-H64+I64 -> 37040.12
A65: 46030 | B65: G | D65: 612 | F65: Comision | H65: 0 | J65: =J64-H65+I65 -> 37040.12
A66: 46030 | B66: G | D66: 147 | F66: Iva | H66: 0 | J66: =J65-H66+I66 -> 37040.12
A67: 46031 | B67: I | C67: 54 | D67: 102 | F67: VENTA ZAMORA CENTRO TARJETA | G67: 46030 | I67: 5143.39 | J67: =J66-H67+I67 -> 42183.51
A68: 46031 | B68: G | D68: 612 | F68: Comision | H68: 97.72 | J68: =J67-H68+I68 -> 42085.79
A69: 46031 | B69: G | D69: 147 | F69: Iva | H69: 15.64 | J69: =J68-H69+I69 -> 42070.15
A70: 46031 | B70: I | C70: 54 | D70: 102 | F70: VENTA ZAMORA CENTRO TARJETA | G70: 46030 | I70: 720.04 | J70: =J69-H70+I70 -> 42790.19
A71: 46031 | B71: G | D71: 612 | F71: Comision | H71: 11.52 | J71: =J70-H71+I71 -> 42778.67
A72: 46031 | B72: G | D72: 147 | F72: Iva | H72: 1.84 | J72: =J71-H72+I72 -> 42776.83
A73: 46031 | B73: TE | F73: TRASPASO ENTRE CTAS 4166 | H73: 40000 | J73: =J72-H73+I73 -> 2776.83
A74: 46032 | B74: I | C74: 54 | D74: 102 | F74: VENTA ZAMORA CENTRO TARJETA | G74: 46031 | I74: 5446.1 | J74: =J73-H74+I74 -> 8222.93
A75: 46032 | B75: G | D75: 612 | F75: Comision | H75: 87.13 | J75: =J74-H75+I75 -> 8135.8
A76: 46032 | B76: G | D76: 147 | F76: Iva | H76: 13.94 | J76: =J75-H76+I76 -> 8121.86
A77: 46032 | B77: I | C77: 54 | D77: 102 | F77: VENTA ZAMORA CENTRO TARJETA | G77: 38726 | I77: 1484.2 | J77: =J76-H77+I77 -> 9606.06
A78: 46032 | B78: G | D78: 612 | F78: Comision | H78: 28.21 | J78: =J77-H78+I78 -> 9577.85
A79: 46032 | B79: G | D79: 147 | F79: Iva | H79: 4.51 | J79: =J78-H79+I79 -> 9573.34
A80: 46032 | B80: I | C80: 54 | D80: 102 | F80: VENTA ZANORA CENTRO TARJETA | G80: 46031 | I80: 22.33 | J80: =J79-H80+I80 -> 9595.67
A81: 46032 | B81: G | D81: 612 | F81: Comision | H81: 0.65 | J81: =J80-H81+I81 -> 9595.02
A82: 46032 | B82: G | D82: 147 | F82: Iva | H82: 0.1 | J82: =J81-H82+I82 -> 9594.92
A83: 46032 | B83: I | C83: 54 | D83: 102 | F83: VENTA ZAMORA CENTRO | G83: 46029 | I83: 43677.5 | J83: =J82-H83+I83 -> 53272.42
A84: 46032 | B84: I | C84: 54 | D84: 102 | F84: VENTA ZAMORA CENTRO | G84: 46031 | I84: 71733 | J84: =J83-H84+I84 -> 125005.42
A85: 46032 | B85: I | C85: 54 | D85: 102 | F85: VENTA ZAMORA CENTRO | G85: 46030 | I85: 67375 | J85: =J84-H85+I85 -> 192380.42
A86: 46032 | B86: TE | D86: - | F86: TRASPASO ENTRE CTAS 4166 | H86: 100000 | J86: =J85-H86+I86 -> 92380.42
A87: 46033 | B87: I | C87: 54 | D87: 102 | F87: VENTA ZAMORA CENTRO TARJETA | G87: 46032 | I87: 2939.13 | J87: =J86-H87+I87 -> 95319.55
A88: 46033 | B88: G | D88: 612 | F88: Comision | H88: 47.03 | J88: =J87-H88+I88 -> 95272.52
A89: 46033 | B89: G | D89: 147 | F89: Iva | H89: 7.52 | J89: =J88-H89+I89 -> 95265
A90: 46033 | B90: I | C90: 54 | D90: 102 | F90: VENTA ZAMORA CENTRO TARJETA | G90: 46032 | I90: 5168.59 | J90: =J89-H90+I90 -> 100433.59
A91: 46033 | B91: G | D91: 612 | F91: Comision | H91: 98.2 | J91: =J90-H91+I91 -> 100335.39
A92: 46033 | B92: G | D92: 147 | F92: Iva | H92: 15.71 | J92: =J91-H92+I92 -> 100319.68
A93: 46034 | B93: I | C93: 54 | D93: 102 | F93: VENTA ZAMORA CENTRO TARJETA | G93: 46033 | I93: 5403.96 | J93: =J92-H93+I93 -> 105723.64
A94: 46034 | B94: G | D94: 612 | F94: Comision | H94: 102.68 | J94: =J93-H94+I94 -> 105620.96
A95: 46034 | B95: G | D95: 147 | F95: Iva | H95: 16.43 | J95: =J94-H95+I95 -> 105604.53
A96: 46034 | B96: I | C96: 54 | D96: 102 | F96: VENTA ZAMORA CENTRO TARJETA | G96: 46033 | I96: 2100.66 | J96: =J95-H96+I96 -> 107705.19
A97: 46034 | B97: G | D97: 612 | F97: Comision | H97: 33.61 | J97: =J96-H97+I97 -> 107671.58
A98: 46034 | B98: G | D98: 147 | F98: Iva | H98: 5.38 | J98: =J97-H98+I98 -> 107666.2
A99: 46034 | B99: I | C99: 50 | D99: 102 | F99: VENTAS CANINDO | G99: 46039 | I99: 350 | J99: =J98-H99+I99 -> 108016.2
A100: 46034 | B100: I | C100: 50 | D100: 102 | F100: VENTAS CANINDO | G100: 46036 | I100: 5860.5 | J100: =J99-H100+I100 -> 113876.7
...

Sheet BB 506
A1: FECHA | B1: M | C1: S | D1: C | E1: # | F1: PROVEEDOR | G1: F VTA | H1: RETIRO | I1: DEPOSITO | J1: SALDO
A2: 46027 | B2: I | C2: 73 | D2: 102 | F2: Vta.Tlmk Morelia Dulceria la Estrella | G2: 46016 | I2: 3041 | J2: 8182.39 | K2: =J2+H2-I2 -> 5141.39
A3: 46027 | B3: I | C3: 73 | D3: 102 | F3: Vta.Tlmk Morelia abarrotes Ximena | G3: 46017 | I3: 710 | J3: =J2+I3-H3 -> 8892.39
A4: 46027 | B4: I | C4: 73 | D4: 102 | F4: Vta.Tlmk Morelia Judith Zavala | G4: 46017 | I4: 3502.5 | J4: =J3+I4-H4 -> 12394.89
A5: 46027 | B5: I | C5: 73 | D5: 102 | F5: Vta.Tlmk Morelia Abarrotes las Cruces | G5: 46017 | I5: 881.5 | J5: =J4+I5-H5 -> 13276.39
A6: 46027 | B6: I | C6: 73 | D6: 102 | F6: Vta.Tlmk Morelia Carlos Arjon | G6: 46017 | I6: 8400.5 | J6: =J5+I6-H6 -> 21676.89
A7: 46027 | B7: I | C7: 73 | D7: 102 | F7: Vta.Tlmk Morelia Abarrotes las Facias | G7: 46017 | I7: 488.5 | J7: =J6+I7-H7 -> 22165.39
A8: 46027 | B8: I | C8: 73 | D8: 102 | F8: Vta.Tlmk Morelia Abarrotes Manuel | G8: 46017 | I8: 533 | J8: =J7+I8-H8 -> 22698.39
A9: 46027 | B9: I | C9: 73 | D9: 102 | F9: VTA.TLMKT MORELIA DULCERIA PIRULI | G9: 46018 | I9: 949.5 | J9: =J8+I9-H9 -> 23647.89
A10: 46027 | B10: I | C10: 73 | D10: 102 | F10: VTA.TLMKT MORELIA DUL. AB. Y TORRES | G10: 46018 | I10: 9902 | J10: =J9+I10-H10 -> 33549.89
A11: 46027 | B11: I | C11: 73 | D11: 102 | F11: VTA.TLMKT MORELIA AB. EL ANGEL | G11: 46018 | I11: 1223 | J11: =J10+I11-H11 -> 34772.89
A12: 46027 | B12: I | C12: 73 | D12: 102 | F12: VTA.TLMKT MORELIA DULCERIA NENA | G12: 46018 | I12: 3243 | J12: =J11+I12-H12 -> 38015.89
A13: 46027 | B13: I | C13: 73 | D13: 102 | F13: VTA.TLMKT MORELIA ABARROTES EL CONTA | G13: 46018 | I13: 737 | J13: =J12+I13-H13 -> 38752.89
A14: 46027 | B14: I | C14: 73 | D14: 102 | F14: VTA.TLMKT MORELIA AB. EL HERMANO | G14: 46018 | I14: 1548.5 | J14: =J13+I14-H14 -> 40301.39
... A21: 46027 | B21: I | C21: 10 | D21: 102 | F21: VTA PADRE HIDALGO | G21: 46020 | I21: 16456.5 | J21: =J20+I21-H21 -> 177150.39
A22: 46027 | B22: I | C22: 32 | D22: 102 | F22: VENTAS MORELIA MADERO | I22: 28961.61 | J22: =J21+I22-H22 -> 206112
A23: 46027 | B23: I | C23: 32 | D23: 102 | F23: VENTAS MORELIA MADERO | I23: 14143.5 | J23: =J22+I23-H23 -> 220255.5
A24: 46027 | B24: I | C24: 32 | D24: 102 | F24: VENTAS MORELIA MADERO | I24: 17708 | J24: =J23+I24-H24 -> 237963.5
A25: 46027 | B25: I | C25: 32 | D25: 102 | F25: VENTAS MORELIA MADERO | I25: 17629.5 | J25: =J24+I25-H25 -> 255593
A26: 46027 | B26: I | C26: 32 | D26: 102 | F26: VENTAS MORELIA MADERO | I26: 14138.5 | J26: =J25+I26-H26 -> 269731.5
A27: 46027 | B27: I | C27: 32 | D27: 102 | F27: VENTAS MORELIA MADERO | G27: 46015 | I27: 107443.5 | J27: =J26+I27-H27 -> 377175
A28: 46027 | B28: I | C28: 32 | D28: 102 | F28: VENTAS MORELIA MADERO | G28: 46017 | I28: 54664 | J28: =J27+I28-H28 -> 431839
A29: 46027 | B29: I | C29: 32 | D29: 102 | F29: VENTAS MORELIA MADERO | G29: 46018 | I29: 23621.16 | J29: =J28+I29-H29 -> 455460.16
A30: 46027 | B30: I | C30: 32 | D30: 102 | F30: VENTAS MORELIA MADERO | G30: 46019 | I30: 15355.5 | J30: =J29+I30-H30 -> 470815.66
A31: 46027 | B31: I | C31: 32 | D31: 102 | F31: VENTAS MORELIA MADERO | G31: 46020 | I31: 19100 | J31: =J30+I31-H31 -> 489915.66
A32: 46027 | B32: I | C32: 73 | D32: 102 | F32: VTA.TLMKT MORELIA NORMA GARCIA | G32: 46014 | I32: 36635.5 | J32: =J31+I32-H32 -> 526551.16
A33: 46027 | B33: I | C33: 30 | D33: 102 | F33: VENTAS MORELIA ABASTOS | G33: 46021 | I33: 13188 | J33: =J32+I33-H33 -> 539739.16
A34: 46027 | B34: I | C34: 30 | D34: 102 | F34: VENTAS MORELIA ABASTOS | G34: 46021 | I34: 12735.5 | J34: =J33+I34-H34 -> 552474.66
A35: 46027 | B35: I | C35: 30 | D35: 102 | F35: VENTAS MORELIA ABASTOS | G35: 46021 | I35: 3846 | J35: =J34+I35-H35 -> 556320.66
A36: 46027 | B36: I | C36: 30 | D36: 102 | F36: VENTAS MORELIA ABASTOS | G36: 46021 | I36: 6535 | J36: =J35+I36-H36 -> 562855.66
A37: 46027 | B37: I | C37: 32 | D37: 102 | F37: VENTAS MORELIA MADERO | G37: 46001 | I37: 9769 | J37: =J36+I37-H37 -> 572624.66
A38: 46027 | B38: I | C38: 32 | D38: 102 | F38: VENTAS MORELIA MADERO | G38: 46002 | I38: 1458.5 | J38: =J37+I38-H38 -> 574083.16
... A53: 46027 | B53: I | C53: 30 | D53: 102 | F53: VENTAS MORELIA ABASTOS | G53: 46004 | I53: 42594.38 | J53: =J52+I53-H53 -> 753344.54
A54: 46027 | B54: I | D54: 102 | F54: Dep. Efectivo | I54: 105370 | J54: =J53+I54-H54 -> 858714.54
A55: 46027 | B55: I | C55: 30 | D55: 102 | F55: VENTAS MORELIA ABASTOS | G55: 46021 | I55: 239976.8 | J55: =J54+I55-H55 -> 1098691.3
A56: 46027 | B56: I | C56: 30 | D56: 102 | F56: VENTAS MORELIA ABASTOS | G56: 46022 | I56: 219260 | J56: =J55+I56-H56 -> 1317951.3
A57: 46027 | B57: TE | D57: - | F57: TRASPASO ENTRE CUENTAS | H57: 210000 | J57: =J56+I57-H57 -> 1107951.3
A58: 46027 | B58: C | C58: 30 | D58: 510 | E58: 1 | F58: DISTRIBUIDORA DE LA ROSA | H58: 1026892.1 | J58: =J57+I58-H58 -> 81059.27
A59: 46027 | B59: G | D59: 612 | F59: Comision | H59: 0 | J59: =J58+I59-H59 -> 81059.27
A60: 46027 | B60: G | D60: 147 | F60: Iva | H60: 0 | J60: =J59+I60-H60 -> 81059.27
A61: 46027 | B61: C | C61: 50 | D61: 510 | E61: 2 | F61: COMERCIALIZAODORA ANAHUAC MEXI | H61: 37545.77 | J61: =J60+I61-H61 -> 43513.5
A62: 46027 | B62: G | D62: 612 | F62: Comision | H62: 0 | J62: =J61+I62-H62 -> 43513.5
A63: 46027 | B63: G | D63: 147 | F63: Iva | H63: 0 | J63: =J62+I63-H63 -> 43513.5
A64: 46027 | B64: C | C64: 30 | D64: 510 | E64: 3 | F64: COMERCIALIZAODORA ANAHUAC MEXI | H64: 37050.28 | J64: =J63+I64-H64 -> 6463.22
A65: 46027 | B65: G | D65: 612 | F65: Comision | H65: 0 | J65: =J64+I65-H65 -> 6463.22
A66: 46027 | B66: G | D66: 147 | F66: Iva | H66: 0 | J66: =J65+I66-H66 -> 6463.22
A67: 46028 | B67: I | C67: 30 | D67: 102 | F67: VENTAS MORELIA ABASTOS | G67: 46022 | I67: 73780.87 | J67: =J66+I67-H67 -> 80244.09
A68: 46028 | B68: I | C68: 30 | D68: 102 | F68: VENTAS MORELIA ABASTOS | G68: 46011 | I68: 12835 | J68: =J67+I68-H68 -> 93079.09
A69: 46028 | B69: I | C69: 30 | D69: 102 | F69: VENTAS MORELIA ABASTOS | G69: 45659 | I69: 373259.69 | J69: =J68+I69-H69 -> 466338.78
A70: 46028 | B70: I | C70: 30 | D70: 102 | F70: VENTAS MORELIA ABASTOS | G70: 45660 | I70: 172733 | J70: =J69+I70-H70 -> 639071.78
A71: 46028 | B71: I | C71: 73 | D71: 102 | F71: VTA.TLMKT MORELIA COMPLEMNETO DULCERIA CONFETI | G71: 46018 | I71: 200 | J71: =J70+I71-H71 -> 639271.78
A72: 46028 | B72: I | C72: 73 | D72: 102 | F72: VTA.TLMKT MORELIA VERONICA VILLA | G72: 46014 | I72: 5254.5 | J72: =J71+I72-H72 -> 644526.28
A73: 46028 | B73: I | C73: 73 | D73: 102 | F73: VTA.TLMKT MORELIA MARY CARMEN ALMANZA | G73: 46018 | I73: 9325.5 | J73: =J72+I73-H73 -> 653851.78
A74: 46028 | B74: I | C74: 73 | D74: 102 | F74: VTA.TLMKT MORELIA ARMANDO GUZMAN | G74: 46018 | I74: 9872 | J74: =J73+I74-H74 -> 663723.78
A75: 46028 | B75: I | C75: 73 | D75: 102 | F75: VTA.TLMKT MORELIA DULCERI LULU | G75: 46018 | I75: 1772 | J75: =J74+I75-H75 -> 665495.78
A76: 46028 | B76: I | C76: 73 | D76: 102 | F76: VTA.TLMKT MORELIA MARIA DEL ROSARIO | G76: 46018 | I76: 5486.5 | J76: =J75+I76-H76 -> 670982.28
A77: 46028 | B77: I | C77: 73 | D77: 102 | F77: VTA.TLMKT MORELIA SUPER CHAPULTEPEC | G77: 46018 | I77: 586 | J77: =J76+I77-H77 -> 671568.28
A78: 46028 | B78: I | C78: 73 | D78: 102 | F78: VTA.TLMKT MORELIA AB. LA NUEVA | G78: 46018 | I78: 1572.5 | J78: =J77+I78-H78 -> 673140.78
... A82: 46028 | B82: I | C82: 73 | D82: 102 | F82: VTA.TLMKT MORELIA AB. ESMERALDA | G82: 46020 | I82: 740 | J82: =J81+I82-H82 -> 675743.78
A83: 46028 | B83: I | C83: 73 | D83: 102 | F83: VTA.TLMKT MORELIA AB. ROSAS DE GUADALUPE | G83: 2912/2025 | I83: 1541.5 | J83: =J82+I83-H83 -> 677285.28
A84: 46028 | B84: I | C84: 73 | D84: 102 | F84: VTA.TLMKT MORELIA ROSA EVELIA | G84: 46020 | I84: 4650 | J84: =J83+I84-H84 -> 681935.28
A85: 46028 | B85: I | C85: 73 | D85: 102 | F85: VTA.TLMKT MORELIA AB. RODRIGUEZ | G85: 46020 | I85: 2070 | J85: =J84+I85-H85 -> 684005.28
A86: 46028 | B86: I | C86: 73 | D86: 102 | F86: VTA.TLMKT MORELIA AB. GEMI | G86: 46020 | I86: 445 | J86: =J85+I86-H86 -> 684450.28
A87: 46028 | B87: I | C87: 73 | D87: 102 | F87: VTA.TLMKT MORELIA AB. MAXI | G87: 46020 | I87: 569 | J87: =J86+I87-H87 -> 685019.28
A88: 46028 | B88: I | C88: 73 | D88: 102 | F88: VTA.TLMKT MORELIA AB. PRISCILA | G88: 46020 | I88: 1216 | J88: =J87+I88-H88 -> 686235.28
A89: 46028 | B89: I | C89: 73 | D89: 102 | F89: VTA.TLMKT MORELIA AB. DANI | G89: 46020 | I89: 416 | J89: =J88+I89-H89 -> 686651.28
A90: 46028 | B90: I | C90: 73 | D90: 102 | F90: VTA.TLMKT MORELIA AB. MEMIN | G90: 46020 | I90: 319 | J90: =J89+I90-H90 -> 686970.28
A91: 46028 | B91: I | C91: 73 | D91: 102 | F91: VTA.TLMKT MORELIA AB. PLATA | G91: 46020 | I91: 415.5 | J91: =J90+I91-H91 -> 687385.78
A92: 46028 | B92: I | C92: 73 | D92: 102 | F92: VTA.TLMKT MORELIA AB. DANI | G92: 46020 | I92: 416 | J92: =J91+I92-H92 -> 687801.78
A93: 46028 | B93: I | C93: 73 | D93: 102 | F93: VTA.TLMKT MORELIAALEX | G93: 46020 | I93: 867.5 | J93: =J92+I93-H93 -> 688669.28
A94: 46028 | B94: I | C94: 73 | D94: 102 | F94: VTA.TLMKT MORELIA VERONICA VILLA | G94: 46021 | I94: 3075 | J94: =J93+I94-H94 -> 691744.28
A95: 46028 | B95: I | C95: 73 | D95: 102 | F95: VTA.TLMKT MORELIA ESTER LOPEZ | G95: 46022 | I95: 466 | J95: =J94+I95-H95 -> 692210.28
... A106: 46028 | B106: I | C106: 30 | D106: 102 | F106: VENTAS MORELIA ABASTOS | G106: 45665 | I106: 5850.68 | J106: =J105+I106-H106 -> 740881.96
A107: 46028 | B107: TE | D107: - | F107: TRASPASO ENTRE CTAS 4166 | H107: 740000 | J107: =J106+I107-H107 -> 881.96
A108: 46030 | B108: I | C108: 73 | D108: 102 | F108: Vta.Tlmk Morelia Elva Quezada | G108: 46018 | I108: 77557 | J108: =J107+I108-H108 -> 78438.96
A109: 46030 | B109: I | C109: 73 | D109: 102 | F109: Vta.Tlmk Morelia Andrea Parra | G109: 46011 | I109: 24713.23 | J109: =J108+I109-H109 -> 103152.19
A110: 46030 | B110: TE | D110: - | F110: TRASPASO ENTRE CTAS 854 | H110: 100000 | J110: =J109+I110-H110 -> 3152.19
A111: 46031 | B111: I | C111: 32 | D111: 102 | F111: VENTAS MORELIA MADERO | G111: 46010 | I111: 52838.5 | J111: =J110+I111-H111 -> 55990.69
A112: 46031 | B112: I | C112: 32 | D112: 102 | F112: VENTAS MORELIA MADERO | G112: 46006 | I112: 4077 | J112: =J111+I112-H112 -> 60067.69
A113: 46031 | B113: I | D113: 102 | F113: Dep. Efectivo | I113: 750 | J113: =J112+I113-H113 -> 60817.69
A114: 46031 | B114: I | C114: 30 | D114: 102 | F114: VENTAS MORELIA ABASTOS | G114: 46026 | I114: 229355 | J114: =J113+I114-H114 -> 290172.69
A115: 46031 | B115: I | C115: 30 | D115: 102 | F115: VENTAS MORELIA ABASTOS | G115: 46027 | I115: 320000 | J115: =J114+I115-H115 -> 610172.69
A116: 46031 | B116: I | C116: 10 | D116: 102 | F116: VTA PADRE HIDALGO | G116: 46045 | I116: 28816 | J116: =J115+I116-H116 -> 638988.69
A117: 46031 | B117: I | D117: 102 | F117: Dep. Efectivo | I117: 20743.5 | J117: =J116+I117-H117 -> 659732.19
A118: 46031 | B118: I | C118: 10 | D118: 102 | F118: VTA PADRE HIDALGO | G118: 46045 | I118: 18143.5 | J118: =J117+I118-H118 -> 677875.69
A119: 46031 | B119: I | C119: 30 | D119: 102 | F119: VENTAS MORELIA ABASTOS | G119: 46028 | I119: 202000 | J119: =J118+I119-H119 -> 879875.69
A120: 46031 | B120: G | F120: Recibo # 285757009370 | H120: 40 | J120: =J119+I120-H120 -> 879835.69
A121: 46031 | B121: I | C121: 73 | D121: 102 | F121: VTA JOSEPH MORELIA DULCERIA EL BOMBON | G121: 46009 | I121: 157276.5 | J121: =J120+I121-H121 -> 1037112.2
A122: 46031 | B122: I | C122: 30 | D122: 102 | F122: VENTAS MORELIA ABASTOS | G122: 46027 | I122: 113700 | J122: =J121+I122-H122 -> 1150812.2
A123: 46031 | B123: I | D123: 102 | F123: Dep. Efectivo | I123: 15312 | J123: =J122+I123-H123 -> 1166124.2
A124: 46031 | B124: I | C124: 10 | D124: 102 | F124: VTA PADRE HIDALGO | G124: 46021 | I124: 24070 | J124: =J123+I124-H124 -> 1190194.2
A125: 46031 | B125: I | D125: 102 | F125: Dep. Efectivo | I125: 10143 | J125: =J124+I125-H125 -> 1200337.2
A126: 46031 | B126: I | D126: 102 | F126: Dep. Efectivo | I126: 12735.5 | J126: =J125+I126-H126 -> 1213072.7
A127: 46031 | B127: I | C127: 10 | D127: 102 | F127: VTA PADRE HIDALGO | G127: 46025 | I127: 19808.5 | J127: =J126+I127-H127 -> 1232881.2
A128: 46031 | B128: I | C128: 40 | D128: 102 | F128: VTA 8 ESQUINAS | G128: 46027 | I128: 14496 | J128: =J127+I128-H128 -> 1247377.2
A129: 46031 | B129: I | C129: 32 | D129: 102 | F129: VENTAS MORELIA MADERO | G129: 46021 | I129: 68481.63 | J129: =J128+I129-H129 -> 1315858.8
A130: 46031 | B130: I | C130: 32 | D130: 102 | F130: VENTAS MORELIA MADERO | G130: 46022 | I130: 60447 | J130: =J129+I130-H130 -> 1376305.8
A131: 46031 | B131: I | C131: 32 | D131: 102 | F131: VENTAS MORELIA MADERO | G131: 46024 | I131: 57095 | J131: =J130+I131-H131 -> 1433400.8
A132: 46031 | B132: I | C132: 32 | D132: 102 | F132: VENTAS MORELIA MADERO | G132: 46025 | I132: 29797.5 | J132: =J131+I132-H132 -> 1463198.3
A133: 46031 | B133: I | C133: 32 | D133: 102 | F133: VENTAS MORELIA MADERO | G133: 46026 | I133: 57269 | J133: =J132+I133-H133 -> 1520467.3
...

Sheet SNTDR 1604
A1: FECHA | B1: M | C1: S | D1: C | E1: # | F1: PROVEEDOR | G1: F VTA | H1: RETIRO | I1: DEPOSITO | J1: SALDO
A2: 46024 | B2: G | C2: 72 | D2: 612 | F2: ADMISINTRACION RENTA | H2: 520 | J2: 963.62 | K2: =J2+H2-I2 -> 1483.62
A3: 46024 | B3: G | C3: 72 | D3: 147 | F3: IVA | H3: 83.2 | J3: =J2-H3+I3 -> 880.42
A4: 46024 | B4: I | C4: 32 | D4: 102 | F4: VENTAS MORELIA MADERO | G4: 46022 | I4: 22083.81 | J4: =J3-H4+I4 -> 22964.23
A5: 46024 | B5: I | C5: 30 | D5: 102 | F5: VENTAS MORELIA ABASTOS | G5: 46022 | I5: 36394.87 | J5: =J4-H5+I5 -> 59359.1
A6: 46024 | B6: I | C6: 32 | D6: 102 | F6: VENTAS MORELIA MADERO | G6: 46022 | I6: 14721.13 | J6: =J5-H6+I6 -> 74080.23
A7: 46024 | B7: I | C7: 30 | D7: 102 | F7: VENTAS MORELIA ABASTOS | G7: 46022 | I7: 8256.25 | J7: =J6-H7+I7 -> 82336.48
A8: 46024 | B8: I | C8: 30 | D8: 102 | F8: VENTAS MORELIA ABASTOS | G8: 46022 | I8: 24209.86 | J8: =J7-H8+I8 -> 106546.34
A9: 46024 | B9: G | C9: 32 | D9: 612 | F9: Comision | H9: 386.58 | J9: =J8-H9+I9 -> 106159.76
A10: 46024 | B10: G | C10: 32 | D10: 147 | F10: Iva | H10: 61.85 | J10: =J9-H10+I10 -> 106097.91
A11: 46024 | B11: G | D11: 612 | F11: Renta Terminal TPV | H11: 200 | J11: =J10-H11+I11 -> 105897.91
A12: 46024 | B12: G | D12: 147 | F12: Iva | H12: 32 | J12: =J11-H12+I12 -> 105865.91
A13: 46024 | B13: G | C13: 30 | D13: 612 | F13: Comision | H13: 617.29 | J13: =J12-H13+I13 -> 105248.62
A14: 46024 | B14: G | C14: 30 | D14: 147 | F14: Iva | H14: 98.77 | J14: =J13-H14+I14 -> 105149.85
A15: 46024 | B15: G | D15: 612 | F15: Cuota Afiliacion | H15: 299 | J15: =J14-H15+I15 -> 104850.85
A16: 46024 | B16: G | D16: 147 | F16: Iva | H16: 47.84 | J16: =J15-H16+I16 -> 104803.01
A17: 46024 | B17: G | C17: 32 | D17: 612 | F17: Comision | H17: 242.19 | J17: =J16-H17+I17 -> 104560.82
A18: 46024 | B18: G | C18: 32 | D18: 147 | F18: Iva | H18: 38.75 | J18: =J17-H18+I18 -> 104522.07
A19: 46024 | B19: G | D19: 612 | F19: Renta Terminal TPV | H19: 200 | J19: =J18-H19+I19 -> 104322.07
A20: 46024 | B20: G | D20: 147 | F20: Iva | H20: 32 | J20: =J19-H20+I20 -> 104290.07
A21: 46024 | B21: G | D21: 612 | F21: Cuota Afiliacion | H21: 299 | J21: =J20-H21+I21 -> 103991.07
A22: 46024 | B22: G | D22: 147 | F22: Iva | H22: 47.84 | J22: =J21-H22+I22 -> 103943.23
A23: 46024 | B23: G | C23: 30 | D23: 612 | F23: Comision | H23: 161.09 | J23: =J22-H23+I23 -> 103782.14
A24: 46024 | B24: G | C24: 30 | D24: 147 | F24: Iva | H24: 25.77 | J24: =J23-H24+I24 -> 103756.37
A25: 46024 | B25: G | D25: 612 | F25: Renta Terminal TPV | H25: 200 | J25: =J24-H25+I25 -> 103556.37
A26: 46024 | B26: G | D26: 147 | F26: Iva | H26: 32 | J26: =J25-H26+I26 -> 103524.37
A27: 46024 | B27: G | C27: 30 | D27: 612 | F27: Comision | H27: 440.9 | J27: =J26-H27+I27 -> 103083.47
A28: 46024 | B28: G | C28: 30 | D28: 147 | F28: Iva | H28: 70.54 | J28: =J27-H28+I28 -> 103012.93
A29: 46024 | B29: G | D29: 612 | F29: Cuota Afiliacion | H29: 299 | J29: =J28-H29+I29 -> 102713.93
A30: 46024 | B30: G | D30: 147 | F30: Iva | H30: 47.84 | J30: =J29-H30+I30 -> 102666.09
A31: 46024 | B31: I | C31: 42 | D31: 102 | F31: VENTAS LA PIEDAD ABASTOS | I31: 22069.4 | J31: =J30-H31+I31 -> 124735.49
A32: 46024 | B32: I | C32: 42 | D32: 102 | F32: VENTAS LA PIEDAD ABASTOS | I32: 21580.72 | J32: =J31-H32+I32 -> 146316.21
A33: 46024 | B33: I | C33: 42 | D33: 102 | F33: VENTAS LA PIEDAD ABASTOS | I33: 66855.04 | J33: =J32-H33+I33 -> 213171.25
A34: 46024 | B34: I | D34: 102 | F34: Dep. Efectivo | I34: 110969.91 | J34: =J33-H34+I34 -> 324141.16
A35: 46024 | B35: I | D35: 102 | F35: Dep. Efectivo | I35: 15737.93 | J35: =J34-H35+I35 -> 339879.09
A36: 46024 | B36: I | C36: 42 | D36: 102 | F36: VENTAS LA PIEDAD ABASTOS | I36: 92361.32 | J36: =J35-H36+I36 -> 432240.41
A37: 46024 | B37: TE | D37: - | F37: TRASPASO A BB 4166 | H37: 430000 | J37: =J36-H37+I37 -> 2240.41
A38: 46027 | B38: I | C38: 32 | D38: 102 | F38: VENATS MORELIA MADERO | G38: 46024 | I38: 12627.75 | J38: =J37-H38+I38 -> 14868.16
A39: 46027 | B39: I | C39: 32 | D39: 102 | F39: VENTAS MORELIA MADERO | G39: 45660 | I39: 11953.11 | J39: =J38-H39+I39 -> 26821.27
A40: 46027 | B40: I | C40: 30 | D40: 102 | F40: VENTAS MORELIA ABASTOS | G40: 45659 | I40: 25118.66 | J40: =J39-H40+I40 -> 51939.93
A41: 46027 | B41: I | C41: 30 | D41: 102 | F41: VENTAS MORELIA ABASTOS | G41: 45660 | I41: 11158.89 | J41: =J40-H41+I41 -> 63098.82
A42: 46027 | B42: I | C42: 30 | D42: 102 | F42: VENTAS MORELIA ABASTOS | G42: 45661 | I42: 28252.29 | J42: =J41-H42+I42 -> 91351.11
A43: 46027 | B43: I | C43: 32 | D43: 102 | F43: VENTAS MORELIA MADERO | G43: 46024 | I43: 4871.19 | J43: =J42-H43+I43 -> 96222.3
A44: 46027 | B44: I | C44: 32 | D44: 102 | F44: VENTAS MORELIA MADERO | G44: 45661 | I44: 22622.07 | J44: =J43-H44+I44 -> 118844.37
A45: 46027 | B45: I | C45: 30 | D45: 102 | F45: VENTAS MORELIA ABASTOS | G45: 45659 | I45: 34010.18 | J45: =J44-H45+I45 -> 152854.55
A46: 46027 | B46: I | C46: 30 | D46: 102 | F46: VENTAS MORELIA ABASTOS | G46: 45660 | I46: 141.09 | J46: =J45-H46+I46 -> 152995.64
A47: 46027 | B47: I | C47: 30 | D47: 102 | F47: VENTAS MORELIA ABASTOS | G47: 45659 | I47: 16641.76 | J47: =J46-H47+I47 -> 169637.4
A48: 46027 | B48: I | C48: 30 | D48: 102 | F48: VENTAS MORELIA ABASTOS | G48: 45660 | I48: 36749.53 | J48: =J47-H48+I48 -> 206386.93
A49: 46027 | B49: I | C49: 30 | D49: 102 | F49: VENTAS MORELIA ABASTOS | G49: 45661 | I49: 44306.73 | J49: =J48-H49+I49 -> 250693.66
A50: 46027 | B50: G | C50: 32 | D50: 612 | F50: Comision | H50: 207.15 | J50: =J49-H50+I50 -> 250486.51
A51: 46027 | B51: G | C51: 32 | D51: 147 | F51: Iva | H51: 33.14 | J51: =J50-H51+I51 -> 250453.37
A52: 46027 | B52: G | C52: 32 | D52: 612 | F52: Comision | H52: 198.21 | J52: =J51-H52+I52 -> 250255.16
A53: 46027 | B53: G | C53: 32 | D53: 147 | F53: Iva | H53: 31.71 | J53: =J52-H53+I53 -> 250223.45
A54: 46027 | B54: G | C54: 30 | D54: 612 | F54: Comision | H54: 469.41 | J54: =J53-H54+I54 -> 249754.04
A55: 46027 | B55: G | C55: 30 | D55: 147 | F55: Iva | H55: 75.11 | J55: =J54-H55+I55 -> 249678.93
A56: 46027 | B56: G | C56: 30 | D56: 612 | F56: Comision | H56: 189.87 | J56: =J55-H56+I56 -> 249489.06
A57: 46027 | B57: G | C57: 30 | D57: 147 | F57: Iva | H57: 30.38 | J57: =J56-H57+I57 -> 249458.68
A58: 46027 | B58: G | C58: 30 | D58: 612 | F58: Comision | H58: 497.95 | J58: =J57-H58+I58 -> 248960.73
A59: 46027 | B59: G | C59: 30 | D59: 147 | F59: Iva | H59: 79.67 | J59: =J58-H59+I59 -> 248881.06
A60: 46027 | B60: G | C60: 32 | D60: 612 | F60: Comision | H60: 81.96 | J60: =J59-H60+I60 -> 248799.1
A61: 46027 | B61: G | C61: 32 | D61: 147 | F61: Iva | H61: 13.11 | J61: =J60-H61+I61 -> 248785.99
... A73: 46027 | B73: G | C73: 30 | D73: 147 | F73: Iva | H73: 122.3 | J73: =J72-H73+I73 -> 245643.16
A74: 46027 | B74: I | D74: 102 | F74: Dep. Efectivo | I74: 40565.5 | J74: =J73-H74+I74 -> 286208.66
A75: 46027 | B75: I | C75: 30 | D75: 102 | F75: VENTAS MORELIA ABASTOS | G75: 46025 | I75: 5678.5 | J75: =J74-H75+I75 -> 291887.16
A76: 46027 | B76: I | C76: 30 | D76: 102 | F76: VENTAS MORELIA ABASTOS | G76: 46025 | I76: 4386.4 | J76: =J75-H76+I76 -> 296273.56
A77: 46027 | B77: I | C77: 30 | D77: 102 | F77: VENTAS MORELIA ABASTOS | G77: 46043 | I77: 350 | J77: =J76-H77+I77 -> 296623.56
A78: 46027 | B78: C | D78: 510 | E78: 1 | F78: Comercializadora Gonac SA de Cv | H78: 58383.84 | J78: =J77-H78+I78 -> 238239.72
A79: 46027 | B79: C | D79: 510 | E79: 2 | F79: Comercializadora Gonac SA de Cv | H79: 83344.89 | J79: =J78-H79+I79 -> 154894.83
A80: 46027 | B80: TE | D80: - | F80: TRASPASO A BBVA 5712 | H80: 150000 | J80: =J79-H80+I80 -> 4894.83
A81: 46028 | B81: I | C81: 32 | D81: 102 | F81: VENTAS MORELIA MADERO | G81: 46027 | I81: 13220.37 | J81: =J80-H81+I81 -> 18115.2
A82: 46028 | B82: I | C82: 32 | D82: 102 | F82: VENTAS MORELIA MADERO | G82: 46027 | I82: 26997.15 | J82: =J81-H82+I82 -> 45112.35
A83: 46028 | B83: I | C83: 30 | D83: 102 | F83: VENTAS MORELIA ABASTOS | G83: 46027 | I83: 26832.21 | J83: =J82-H83+I83 -> 71944.56
A84: 46028 | B84: I | C84: 30 | D84: 102 | F84: VENTAS MORELIA ABASTOS | G84: 45662 | I84: 37589.67 | J84: =J83-H84+I84 -> 109534.23
A85: 46028 | B85: G | C85: 32 | D85: 612 | F85: Comision | H85: 212.96 | J85: =J84-H85+I85 -> 109321.27
A86: 46028 | B86: G | C86: 32 | D86: 147 | F86: Iva | H86: 34.07 | J86: =J85-H86+I86 -> 109287.2
A87: 46028 | B87: G | C87: 30 | D87: 612 | F87: Comision | H87: 441.3 | J87: =J86-H87+I87 -> 108845.9
A88: 46028 | B88: G | C88: 30 | D88: 147 | F88: Iva | H88: 70.61 | J88: =J87-H88+I88 -> 108775.29
A89: 46028 | B89: G | C89: 32 | D89: 612 | F89: Comision | H89: 468.85 | J89: =J88-H89+I89 -> 108306.44
A90: 46028 | B90: G | C90: 32 | D90: 147 | F90: Iva | H90: 75.02 | J90: =J89-H90+I90 -> 108231.42
A91: 46028 | B91: G | C91: 30 | D91: 612 | F91: Comision | H91: 683.39 | J91: =J90-H91+I91 -> 107548.03
A92: 46028 | B92: G | C92: 30 | D92: 147 | F92: Iva | H92: 109.34 | J92: =J91-H92+I92 -> 107438.69
A93: 46028 | B93: I | D93: 102 | F93: Dep. Efectivo | I93: 50718.55 | J93: =J92-H93+I93 -> 158157.24
A94: 46028 | B94: I | D94: 102 | F94: Dep. Efectivo | I94: 18977.57 | J94: =J93-H94+I94 -> 177134.81
A95: 46028 | B95: TE | D95: - | F95: TRASPASO A BBVA 5712 (es a stder 2169) | H95: 177000 | J95: =J94-H95+I95 -> 134.81
A96: 46029 | B96: I | C96: 32 | D96: 102 | F96: VENTAS MORELIA MADERO | G96: 45663 | I96: 9886.59 | J96: =J95-H96+I96 -> 10021.4
A97: 46029 | B97: I | C97: 30 | D97: 102 | F97: VENTAS MORELIA ABASTOS | G97: 45663 | I97: 5785.15 | J97: =J96-H97+I97 -> 15806.55
A98: 46029 | B98: I | C98: 32 | D98: 102 | F98: VENTAS MORELIA MADERO | G98: 46028 | I98: 10648.01 | J98: =J97-H98+I98 -> 26454.56
A99: 46029 | B99: I | C99: 30 | D99: 102 | F99: VENTAS MORELIA ABASTOS | G99: 45663 | I99: 22824.4 | J99: =J98-H99+I99 -> 49278.96
A100: 46029 | B100: G | C100: 32 | D100: 612 | F100: Comision | H100: 173.73 | J100: =J99-H100+I100 -> 49105.23
A101: 46029 | B101: G | C101: 32 | D101: 147 | F101: Iva | H101: 27.8 | J101: =J100-H101+I101 -> 49077.43
A102: 46029 | B102: G | C102: 30 | D102: 612 | F102: Comision | H102: 113.7 | J102: =J101-H102+I102 -> 48963.73
A103: 46029 | B103: G | C103: 30 | D103: 147 | F103: Iva | H103: 18.19 | J103: =J102-H103+I103 -> 48945.54
A104: 46029 | B104: G | C104: 32 | D104: 612 | F104: Comision | H104: 179.29 | J104: =J103-H104+I104 -> 48766.25
A105: 46029 | B105: G | C105: 32 | D105: 147 | F105: Iva | H105: 28.69 | J105: =J104-H105+I105 -> 48737.56
A106: 46029 | B106: G | C106: 30 | D106: 612 | F106: Comision | H106: 415.4 | J106: =J105-H106+I106 -> 48322.16
A107: 46029 | B107: G | C107: 30 | D107: 147 | F107: Iva | H107: 66.46 | J107: =J106-H107+I107 -> 48255.7
A108: 46029 | B108: TE | D108: - | F108: TRASPASO A BBVA 5712 | H108: 45000 | J108: =J107-H108+I108 -> 3255.7
A109: 46030 | B109: I | C109: 32 | D109: 102 | F109: VENTAS MORELIA MADERO | G109: 46029 | I109: 23245.84 | J109: =J108-H109+I109 -> 26501.54
A110: 46030 | B110: I | C110: 30 | D110: 102 | F110: VENTAS MORELIA ABASTOS | G110: 46029 | I110: 5630.53 | J110: =J109-H110+I110 -> 32132.07
A111: 46030 | B111: I | C111: 30 | D111: 102 | F111: VENTAS MORELIA ABASTOS | G111: 46029 | I111: 19670.23 | J111: =J110-H111+I111 -> 51802.3
...

Sheet SNTDR 1621
A1: FECHA | B1: M | C1: S | D1: C | E1: # | F1: PROVEEDOR | G1: F VTA | H1: RETIRO | I1: DEPOSITO | J1: SALDO
A2: 46024 | B2: G | C2: 72 | D2: 612 | F2: ADMISINTRACION RENTA | H2: 103.05 | J2: 16.49 | K2: =J2+H2-I2 -> 119.54
A3: 46024 | B3: G | C3: 72 | D3: 147 | F3: IVA | H3: 16.49 | J3: =J2-H3+I3 -> 0
A4: 46050 | B4: I | D4: 102 | F4: PAGO MULTISERVICOS 2001 FAC 541 | I4: 18437.44 | J4: =J3-H4+I4 -> 18437.44
A5: 46050 | B5: G | C5: 72 | D5: 612 | F5: ADMISINTRACION RENTA | H5: 416.95 | J5: =J4-H5+I5 -> 18020.49
A6: 46050 | B6: G | C6: 72 | D6: 147 | F6: IVA | H6: 66.71 | J6: =J5-H6+I6 -> 17953.78
A7: 46052 | B7: I | D7: 102 | F7: PAGO MULTISERVICOS 2001 FAC 542 | I7: 6400.8 | J7: =J6-H7+I7 -> 24354.58
A8: 46052 | B8: TE | D8: - | F8: TRASPASO ENTRE CTAS 2169 | H8: 20000 | J8: =J7-H8+I8 -> 4354.58

Sheet SNTDR 5565
A1: FECHA | B1: M | C1: S | D1: C | E1: # | F1: PROVEEDOR | G1: F VTA | H1: RETIRO | I1: DEPOSITO | J1: SALDO
A2: 46024 | B2: G | D2: 612 | F2: ADMINISTRACION RENTA | H2: 520 | J2: 74298.25 | K2: =J2+H2-I2 -> 74818.25
A3: 46024 | B3: G | D3: 147 | F3: I V A POR COMISION | H3: 83.2 | J3: =J2-H3+I3 -> 74215.05

Sheet CAJA GENERAL  
A1: FECHA | B1: M | C1: S | D1: CTA | E1: FOLIO | F1: DESCRIPCION | G1: DESCRIPCION | H1: EGRESO | I1: INGRESO | K1: ARQUEO | L1: DIF
A2: 46024 | B2: I | C2: OTROS | D2: 102 | E2: 20534 | F2: Jose Mendez | I2: 500 | J2: 1490350.2 | K2: =J2+H2-I2 -> 1489850.2
A3: 46024 | B3: I | C3: 20 | D3: 102 | E3: 20533 | F3: Ventas RD PH 31/12 | I3: 101336 | J3: =J2+I3-H3 -> 1591686.2
A4: 46024 | B4: I | C4: OTROS | D4: 102 | E4: 20532 | F4: Caja ]MKT | I4: 13665 | J4: =J3+I4-H4 -> 1605351.2
A5: 46024 | B5: G | C5: 12 | D5: 613 | E5: 83450 | F5: G Logistica viaticos | G5: Viaticos Varios | H5: 17050 | J5: =J4+I5-H5 -> 1588301.2
A6: 46024 | B6: G | C6: 12 | D6: 613 | E6: 83449 | F6: G Logisitica comisiones | G6: comisiones varias | H6: 64899 | J6: =J5+I6-H6 -> 1523402.2
A7: 46024 | B7: G | C7: 07 | D7: 613 | E7: 83448 | F7: G Fernanda MKT | G7: transporte personal staff para cabalgata | H7: 300 | J7: =J6+I7-H7 -> 1523102.2
A8: 46024 | B8: G | D8: 613 | E8: 83447 | F8: G Yazmin Sarai Gomez | G8: Capital marca Divisa Sem 42 | H8: 350 | J8: =J7+I8-H8 -> 1522752.2
A9: 46024 | B9: G | D9: 613 | E9: 83446 | F9: G Dulce Maria Alatorre | G9: Capital marca Divisa Sem 42 | H9: 350 | J9: =J8+I9-H9 -> 1522402.2
A10: 46024 | B10: G | C10: 10 | D10: 613 | E10: 83445 | F10: G Fatima villareal | G10: Capital marca Divisa Sem 42 | H10: 350 | J10: =J9+I10-H10 -> 1522052.2
A11: 46024 | B11: G | C11: 10 | D11: 613 | E11: 83444 | F11: G Estefania Muñoz Ventura | G11: Capital marca anahuac Sem 12 | H11: 350 | J11: =J10+I11-H11 -> 1521702.2
A12: 46024 | B12: G | C12: 40 | D12: 613 | E12: 83443 | F12: G Angelica Maria Muñoz | G12: Capital marca anahuac Sem 12 | H12: 350 | J12: =J11+I12-H12 -> 1521352.2
A13: 46024 | B13: G | D13: 613 | E13: 83442 | F13: G Miriam Judith Rodriguez | G13: Capital marca Divisa Sem 42 | H13: 350 | J13: =J12+I13-H13 -> 1521002.2
A14: 46024 | B14: G | D14: 613 | E14: 83441 | F14: G Marco Antopnio Avalos | G14: Capital marca Divisa Sem 42 | H14: 350 | J14: =J13+I14-H14 -> 1520652.2
A15: 46024 | B15: G | C15: 20 | D15: 613 | E15: 83440 | F15: G Victgorino Urbano | G15: Comision Periodo 26 | H15: 5705.79 | J15: =J14+I15-H15 -> 1514946.4
A16: 46024 | B16: G | C16: 20 | D16: 613 | E16: 83439 | F16: G Victor Alfonso Mata | G16: Comision Periodo 26 | H16: 913.32 | J16: =J15+I16-H16 -> 1514033.1
A17: 46024 | B17: G | C17: 20 | D17: 613 | E17: 83438 | F17: G Joaquin Hurtado | G17: Comision Periodo 26 | H17: 5623 | J17: =J16+I17-H17 -> 1508410.1
A18: 46024 | B18: G | C18: 20 | D18: 613 | E18: 83437 | F18: G Victo Hugo Garcia | G18: Comision Periodo 26 | H18: 5790 | J18: =J17+I18-H18 -> 1502620.1
A19: 46024 | B19: G | C19: 20 | D19: 613 | E19: 83436 | F19: G Mariano Martinez Patlan | G19: Comision Periodo 26 | H19: 7406.5 | J19: =J18+I19-H19 -> 1495213.6
A20: 46024 | B20: G | C20: 11 | D20: 613 | E20: 83435 | F20: G Maria Candelaria | G20: Comision Periodo 26 | H20: 2704.65 | J20: =J19+I20-H20 -> 1492508.9
A21: 46024 | B21: G | C21: 11 | D21: 613 | E21: 83434 | F21: G Patrciai Chavarria | G21: Comision Periodo 26 | H21: 2383.34 | J21: =J20+I21-H21 -> 1490125.6
A22: 46024 | B22: G | C22: 20 | D22: 613 | E22: 83433 | F22: G Angel Alberto Vazquez | G22: Comision Periodo 26 | H22: 6801.2 | J22: =J21+I22-H22 -> 1483324.4
A23: 46024 | B23: G | C23: 01 | D23: 610 | E23: 83432 | F23: G Sistemas | G23: Nomina 01 | H23: 6598.5 | J23: =J22+I23-H23 -> 1476725.9
A24: 46024 | B24: G | C24: 11 | D24: 610 | E24: 83431 | F24: G rutas Vecinales | G24: Nomina 01 | H24: 3586 | J24: =J23+I24-H24 -> 1473139.9
A25: 46024 | B25: G | C25: 05 | D25: 610 | E25: 83430 | F25: G RRHH | G25: Nomina 01 | H25: 3719 | J25: =J24+I25-H25 -> 1469420.9
A26: 46024 | B26: G | C26: 08 | D26: 610 | E26: 83429 | F26: G Promotoras | G26: Nomina 01 | H26: 819 | J26: =J25+I26-H26 -> 1468601.9
... A40: 46024 | B40: G | C40: 40 | D40: 610 | E40: 83415 | F40: g Suc 8 esquinas | G40: Nomina 01 | H40: 9242.5 | J40: =J39+I40-H40 -> 1375445.9
A41: 46024 | B41: G | C41: 54 | D41: 613 | E41: 83414 | F41: G Tania RH | G41: comida para inventario damaso | H41: 2500 | J41: =J40+I41-H41 -> 1372945.9 | K41: 1372323.2 | L41: =K41-J41 -> -622.68
A42: 46025 | B42: I | C42: 52 | D42: 102 | E42: 20536 | F42: Ventas RD Morelia | I42: 24070 | J42: =J41+I42-H42 -> 1397015.9
A43: 46025 | B43: I | C43: 20 | D43: 102 | E43: 20535 | F43: Ventas RD PH 02/01 | I43: 125959 | J43: =J42+I43-H43 -> 1522974.9
A44: 46025 | B44: C | C44: 30 | D44: 510 | E44: 83465 | F44: MORELIA DEL DIA 08-09-2025 | G44: BOTANAS PAU | H44: 4440 | J44: =J43+I44-H44 -> 1518534.9
A45: 46025 | B45: C | C45: 30 | D45: 510 | E45: 83463 | F45: MORELIA DEL DIA 08-09-2025 | G45: ISMAEL RIVERA | H45: 27843.66 | J45: =J44+I45-H45 -> 1490691.2
A46: 46025 | B46: C | C46: 30 | D46: 510 | E46: 83462 | F46: MORELIA DEL DIA 08-09-2025 | G46: BOTANAS PAU | H46: 2292 | J46: =J45+I46-H46 -> 1488399.2
A47: 46025 | B47: G | C47: 33 | D47: 613 | E47: 83461 | F47: MORELIA DEL DIA 08-09-2025 | G47: VIATICOS RRHH | H47: 141.53 | J47: =J46+I47-H47 -> 1488257.7
A48: 46025 | B48: G | C48: 33 | D48: 613 | E48: 83460 | F48: MORELIA DEL DIA 08-09-2025 | G48: PASTEL AIDE | H48: 420 | J48: =J47+I48-H48 -> 1487837.7
A49: 46025 | B49: G | C49: 33 | D49: 613 | E49: 83459 | F49: MORELIA DEL DIA 08-09-2025 | G49: CONSUMO STAFF | H49: 179.29 | J49: =J48+I49-H49 -> 1487658.4
A50: 46025 | B50: G | C50: 30 | D50: 613 | E50: 83458 | F50: MORELIA DEL DIA 08-09-2025 | G50: CONSUMO TIENDA | H50: 47.92 | J50: =J49+I50-H50 -> 1487610.5
A51: 46025 | B51: G | C51: 76 | D51: 613 | E51: 83457 | F51: MORELIA DEL DIA 08-09-2025 | G51: TIEMPO AIRE LOGISTICA | H51: 101 | J51: =J50+I51-H51 -> 1487509.5
A52: 46025 | B52: G | C52: 30 | D52: 610 | E52: 83456 | F52: MORELIA DEL DIA 08-09-2025 | G52: PAGO NOMINA LUIS FLORES | H52: 1200 | J52: =J51+I52-H52 -> 1486309.5
A53: 46025 | B53: G | C53: 76 | D53: 613 | E53: 83453 | F53: MORELIA DEL DIA 08-09-2025 | G53: CARRETAS PATZCUARO | H53: 3900 | J53: =J52+I53-H53 -> 1482409.5
A54: 46025 | B54: G | C54: 38 | D54: 613 | E54: 83466 | F54: G Gpe Macias | G54: compra de roscas | H54: 4720 | J54: =J53+I54-H54 -> 1477689.5
A55: 46025 | B55: C | C55: 50 | D55: 510 | E55: 83464 | F55: C Piñatas Martin | G55: erm piñatas | H55: 229885 | J55: =J54+I55-H55 -> 1247804.5
... A58: 46025 | B58: G | C58: 0 | D58: 613 | E58: 83452 | F58: G Jose Leonardo Logistica | G58: Maniobras descarga Cedis | H58: 3884.4 | J58: =J57+I58-H58 -> 1240170.1
A59: 46025 | B59: G | C59: 38 | D59: 613 | E59: 83451 | F59: G Jose Luis Cabrere | G59: puertas baños oficinas | H59: 15000 | J59: =J58+I59-H59 -> 1225170.1 | K59: 1224549.7 | L59: =K59-J59 -> -620.38
A60: 46027 | B60: I | C60: 20 | D60: 20 | E60: 20557 | F60: VENTA RUTA RD 22 DEL DIA 05-01-2026 | I60: 23714 | J60: =J59+I60-H60 -> 1248884.1
A61: 46027 | B61: I | C61: 20 | D61: 102 | E61: 20556 | F61: VENTA RUTA RD 21 DEL DIA 05-01-2026 | I61: 18294.5 | J61: =J60+I61-H61 -> 1267178.6
A62: 46027 | B62: I | C62: 20 | D62: 102 | E62: 20555 | F62: VENTA RUTA RD DEL DIA 05-01-2026 | I62: 18914 | J62: =J61+I62-H62 -> 1286092.6
A63: 46027 | B63: I | C63: 20 | D63: 102 | E63: 20554 | F63: VENTA RUTA RD DEL DIA 05-01-2026 | I63: 22920 | J63: =J62+I63-H63 -> 1309012.6
A64: 46027 | B64: I | C64: 20 | D64: 102 | E64: 20553 | F64: VENTA RUTA RD DEL DIA 05-01-2026 | I64: 25762.5 | J64: =J63+I64-H64 -> 1334775.1
A65: 46027 | B65: I | C65: 20 | D65: 102 | E65: 20552 | F65: VENTA RD RUTA 27 DEL DIA 05-01-2026 | I65: 22021 | J65: =J64+I65-H65 -> 1356796.1 | K65: 31010.68 | L65: =K65-I65 -> 8989.68
A66: 46027 | B66: I | C66: 11 | D66: 102 | E66: 20551 | F66: Ventas Ruta Vecinal 31/12 | I66: 30537 | J66: =J65+I66-H66 -> 1387333.1
A67: 46027 | B67: I | C67: 52 | D67: 102 | E67: 20550 | F67: Ventas RD Morelia 31/12 | I67: 10143 | J67: =J66+I67-H67 -> 1397476.1
A68: 46027 | B68: I | C68: 10 | D68: 102 | E68: 20549 | F68: Ventas Suc PH Tarjetas sabado 27/12 | I68: 38202 | J68: =J67+I68-H68 -> 1435678.1
A69: 46027 | B69: I | C69: 40 | D69: 102 | E69: 20548 | F69: Ventas Suc 8esq caja 48 31/12 | I69: 2228 | J69: =J68+I69-H69 -> 1437906.1
A70: 46027 | B70: I | C70: 10 | D70: 102 | E70: 20547 | F70: Ventas Suc PH creditos sabado 27/12 | I70: 13740 | J70: =J69+I70-H70 -> 1451646.1
A71: 46027 | B71: I | C71: 11 | D71: 102 | E71: 20546 | F71: Ventas Ruta Vecinal 31/12 | I71: 40950 | J71: =J70+I71-H71 -> 1492596.1
A72: 46027 | B72: I | C72: 51 | D72: 102 | E72: 20545 | F72: ventas Rd Canindo 31/12 | I72: 44258.5 | J72: =J71+I72-H72 -> 1536854.6
A73: 46027 | B73: I | C73: 51 | D73: 102 | E73: 20544 | F73: Ventas RD Canindo 30/12 | I73: 85985.5 | J73: =J72+I73-H73 -> 1622840.1
A74: 46027 | B74: I | C74: 52 | D74: 102 | E74: 20543 | F74: Ventas RD Morelia 29/12 | I74: 17708 | J74: =J73+I74-H74 -> 1640548.1
A75: 46027 | B75: I | C75: 40 | D75: 102 | E75: 20542 | F75: Ventas Suc 8esq Caja 48 30/12 | I75: 1726 | J75: =J74+I75-H75 -> 1642274.1
A76: 46027 | B76: I | C76: 40 | D76: 102 | E76: 20541 | F76: Ventas Suc 8esq Tarjetas viernes 26/01 | I76: 29497.5 | J76: =J75+I76-H76 -> 1671771.6
A77: 46027 | B77: I | C77: 51 | D77: 102 | E77: 20540 | F77: Ventas RD Canindo 29/12 | I77: 99013 | J77: =J76+I77-H77 -> 1770784.6
... A80: 46027 | B80: I | C80: OTROS | D80: 102 | E80: 20537 | F80: Crisitan Alfonso | I80: 250 | J80: =J79+I80-H80 -> 1958689.6
A81: 46027 | B81: C | C81: 30 | D81: 510 | E81: 83507 | F81: MORELIA DEL DIA 10-09-2025 | G81: RICO PAY | H81: 1800 | J81: =J80+I81-H81 -> 1956889.6
A82: 46027 | B82: C | C82: 30 | D82: 510 | E82: 83506 | F82: MORELIA DEL DIA 10-09-2025 | G82: BOTANAS PAU | H82: 3420 | J82: =J81+I82-H82 -> 1953469.6
A83: 46027 | B83: C | C83: 30 | D83: 510 | E83: 83505 | F83: MORELIA DEL DIA 10-09-2025 | G83: ISMAEL RIVERA | H83: 2646 | J83: =J82+I83-H83 -> 1950823.6
A84: 46027 | B84: C | C84: 30 | D84: 510 | E84: 83504 | F84: MORELIA DEL DIA 10-09-2025 | G84: FERNANDO GUTIERREZ | H84: 7490 | J84: =J83+I84-H84 -> 1943333.6
A85: 46027 | B85: C | C85: 30 | D85: 510 | E85: 83503 | F85: MORELIA DEL DIA 10-09-2025 | G85: FERNANDO GUTIERREZ | H85: 2660 | J85: =J84+I85-H85 -> 1940673.6
A86: 46027 | B86: G | C86: 30 | D86: 613 | E86: 83502 | F86: MORELIA DEL DIA 10-09-2025 | G86: VIATICOS AARON | H86: 160.57 | J86: =J85+I86-H86 -> 1940513
A87: 46027 | B87: G | C87: 33 | D87: 613 | E87: 83501 | F87: MORELIA DEL DIA 10-09-2025 | G87: RECARGA STAFF | H87: 101 | J87: =J86+I87-H87 -> 1940412
A88: 46027 | B88: G | C88: 73 | D88: 613 | E88: 83500 | F88: MORELIA DEL DIA 10-09-2025 | G88: FLETE DESCARGA TLMK | H88: 200 | J88: =J87+I88-H88 -> 1940212
A89: 46027 | B89: G | C89: 76 | D89: 613 | E89: 83499 | F89: MORELIA DEL DIA 10-09-2025 | G89: COMIDAS TLMK INCIDNTE | H89: 500 | J89: =J88+I89-H89 -> 1939712
A90: 46027 | B90: C | C90: 30 | D90: 510 | E90: 83498 | F90: MORELIA DEL DIA 09-09-2025 | G90: BOTANAS PAU | H90: 7366 | J90: =J89+I90-H90 -> 1932346
A91: 46027 | B91: C | C91: 30 | D91: 510 | E91: 83497 | F91: MORELIA DEL DIA 09-09-2025 | G91: FERNANDO GUITIERREZ | H91: 2660 | J91: =J90+I91-H91 -> 1929686
A92: 46027 | B92: C | C92: 30 | D92: 510 | E92: 83496 | F92: MORELIA DEL DIA 09-09-2025 | G92: CUERITOS ZACAPU | H92: 10090 | J92: =J91+I92-H92 -> 1919596
... A115: 46027 | B115: G | C115: 54 | D115: 613 | E115: 83474 | F115: g Suc Damaso | G115: Bono por apoyo a inventario | H115: 8000 | J115: =J114+I115-H115 -> 1814893.5
A116: 46027 | B116: G | D116: 613 | E116: 83473 | F116: G Jose Leonardo Logistica | G116: caseta gdl la rosa | H116: 300 | J116: =J115+I116-H116 -> 1814593.5
A117: 46027 | B117: G | C117: 61 | D117: 613 | E117: 83472 | F117: G Guillermo Lopez | G117: peaje casetas memo | H117: 1500 | J117: =J116+I117-H117 -> 1813093.5
A118: 46027 | B118: G | C118: 70 | D118: 613 | E118: 83471 | F118: G Jose Leonardo Logistica | G118: Estacionamiento ruta leon | H118: 50 | J118: =J117+I118-H118 -> 1813043.5
A119: 46027 | B119: G | C119: 70 | D119: 613 | E119: 83470 | F119: G Jose Leonardo Logistica | G119: Estacionamiento mercado leon | H119: 50 | J119: =J118+I119-H119 -> 1812993.5
A120: 46027 | B120: G | C120: 12 | D120: 613 | E120: 83469 | F120: G Jose Leonardo Logistica | G120: Cepillo Y Franelas para unidades | H120: 200 | J120: =J119+I120-H120 -> 1812793.5
A121: 46027 | B121: G | C121: 12 | D121: 613 | E121: 83468 | F121: G Jose Leonardo Logistica | G121: jabon | H121: 45 | J121: =J120+I121-H121 -> 1812748.5
A122: 46027 | B122: G | C122: 0 | D122: 613 | E122: 83467 | F122: G Jose Leonardo Logistica | G122: recoleccion basura cedis | H122: 100 | J122: =J121+I122-H122 -> 1812648.5 | K122: 1812183.7 | L122: =K122-J122 -> -464.76
A123: 46028 | B123: I | C123: 20 | D123: 102 | E123: 20561 | F123: VENTA RD RUTA 26 DEL DIA 06-01-2026 | I123: 23612 | J123: =J122+I123-H123 -> 1836260.5
A124: 46028 | B124: I | C124: 20 | D124: 102 | E124: 20560 | F124: VENTA RUTA 21 DEL DIA 06-01-2025 | I124: 18508 | J124: =J123+I124-H124 -> 1854768.5
A125: 46028 | B125: I | C125: 20 | D125: 102 | E125: 20559 | F125: VENTA RUTA RD 22 DEL DIA 06-01-2026 | I125: 17091 | J125: =J124+I125-H125 -> 1871859.5
A126: 46028 | B126: I | C126: 20 | D126: 102 | E126: 20558 | F126: VENTA RUTA RD 27 DEL DIA 06-01-2026 | I126: 25891 | J126: =J125+I126-H126 -> 1897750.5
A127: 46028 | B127: G | D127: 613 | E127: 83531 | F127: INFLADO DE PELOTAS | G127: PAGO 32 COSTALES INFLADOS DE PELOTAS A $100 | H127: 3200 | J127: =J126+I127-H127 -> 1894550.5
A128: 46028 | B128: C | C128: 0 | D128: 510 | E128: 83530 | F128: MIGUEL RUS | G128: REM GAMA HUBIN | H128: 237293.3 | J128: =J127+I128-H128 -> 1657257.2
A129: 46028 | B129: G | C129: 51 | D129: 610 | E129: 83529 | F129: JESUS GUTIERREZ | G129: RENTA SUC CANINDO MES ENERO 2026 | H129: 16606.67 | J129: =J128+I129-H129 -> 1640650.5
A130: 46028 | B130: G | C130: 50 | D130: 610 | E130: 83528 | F130: JESUS GUTIERREZ | G130: RENTA BODEGA CANINDO MES ENERO 2026 | H130: 33213.16 | J130: =J129+I130-H130 -> 1607437.3
A131: 46028 | B131: G | C131: 75 | D131: 610 | E131: 83527 | F131: JESUS GUTIERREZ | G131: RENTA BODEGA CANINDO MES ENERO 2026 | H131: 33213.16 | J131: =J130+I131-H131 -> 1574224.2
A132: 46028 | B132: C | C132: 10 | D132: 510 | E132: 83526 | F132: JUAN SANCHEZ | G132: REM TARICO | H132: 15532 | J132: =J131+I132-H132 -> 1558692.2
A133: 46028 | B133: C | C133: 42 | D133: 510 | E133: 83525 | F133: LUPITA | G133: REM CUERITOS LUPITA | H133: 6420 | J133: =J132+I133-H133 -> 1552272.2
A134: 46028 | B134: C | C134: 10 | D134: 510 | E134: 83524 | F134: LUPITA | G134: REM CUERITOS LUPITA | H134: 17400 | J134: =J133+I134-H134 -> 1534872.2
A135: 46028 | B135: C | C135: 90 | D135: 510 | E135: 83523 | F135: LUPITA | G135: REM CUERITOS LUPITA | H135: 1050 | J135: =J134+I135-H135 -> 1533822.2
A136: 46028 | B136: C | C136: 40 | D136: 510 | E136: 83522 | F136: LUPITA | G136: REM CUERITOS LUPITA | H136: 6210 | J136: =J135+I136-H136 -> 1527612.2
A137: 46028 | B137: C | C137: 0 | D137: 510 | E137: 83521 | F137: RAUL | G137: REM PLASTICORTES | H137: 36500 | J137: =J136+I137-H137 -> 1491112.2
A138: 46028 | B138: C | C138: 42 | D138: 510 | E138: 83520 | F138: DON TOÑO | G138: REM PIÑATAS TOÑO | H138: 1128 | J138: =J137+I138-H138 -> 1489984.2
A139: 46028 | B139: C | C139: 40 | D139: 510 | E139: 83519 | F139: PIÑATAS TOÑO | G139: REM PIÑATAS TOÑO | H139: 1610 | J139: =J138+I139-H139 -> 1488374.2
...

Sheet FACTORAJE
A1: FECHA | B1: M | C1: S | D1: C | E1: # | F1: PROVEEDOR | G1: F VTA | H1: RETIRO | I1: DEPOSITO | J1: SALDO
A2: 46052 | B2: CF | E2: 1003014 | F2: BOLSAS DE LOS ALTOS, S. DE R.L. DE C.V. | H2: 18283.05
A3: 46052 | B3: CF | E3: 1003015 | F3: BOLSAS DE LOS ALTOS, S. DE R.L. DE C.V. | H3: 22325
A4: 46052 | B4: CF | E4: 1003016 | F4: BOLSAS DE LOS ALTOS, S. DE R.L. DE C.V. | H4: 24906.62
A5: 46052 | B5: CF | E5: 1003017 | F5: BOLSAS DE LOS ALTOS, S. DE R.L. DE C.V. | H5: 9786
A6: 46052 | B6: CF | E6: 1003018 | F6: BOLSAS DE LOS ALTOS, S. DE R.L. DE C.V. | H6: 25513.48
A7: 46052 | B7: CF | E7: 1003019 | F7: BOLSAS DE LOS ALTOS, S. DE R.L. DE C.V. | H7: 295201.33
A8: 46052 | B8: CF | E8: 1003020 | F8: BOLSAS DE LOS ALTOS, S. DE R.L. DE C.V. | H8: 237444.6
A9: 46052 | B9: CF | E9: 1003021 | F9: BOLSAS DE LOS ALTOS, S. DE R.L. DE C.V. | H9: 198682.29
A10: 46052 | B10: CF | E10: 1003029 | F10: BOLSAS DE LOS ALTOS, S. DE R.L. DE C.V. | H10: 8562
A11: 46052 | B11: CF | E11: 1003042 | F11: BOLSAS DE LOS ALTOS, S. DE R.L. DE C.V. | H11: 13500.02
A12: 46052 | B12: CF | E12: 1003048 | F12: BOLSAS DE LOS ALTOS, S. DE R.L. DE C.V. | H12: 4050.01
A13: 46052 | B13: CF | E13: 1003051 | F13: BOLSAS DE LOS ALTOS, S. DE R.L. DE C.V. | H13: 18162.79

Sheet TOTAL MOV
A1: FECHA | B1: M | C1: S | D1: C | E1: # | F1: PROVEEDOR | G1: F VTA | H1: RETIRO | I1: DEPOSITO | J1: BANCOS
A2: 46023 | B2: G | D2: 613 | F2: Compra - Disposicion por POS por (3,478.60) mxn en GASOL DEL VALLE 31dic2025 RFC GVZ 970421PJ7 Tarjeta 5161020003411909 Recibo # 4394927032322 | H2: 3478.6 | J2: BB 4166
A3: 46023 | B3: G | D3: 613 | F3: Compra - Disposicion por POS por (1,568.80) mxn en SUPER SERV GARBRI 31dic2025 RFC SSG 981118LR6 Tarjeta 5161020003551126 Recibo # 4394929032322 | H3: 1568.8 | J3: BB 4166 | K3: ID | L3: BB 4166 | M3: =SUMIFS($I$2:$I$6636,$B$2:$B$6636,$K$3,$J$2:$J$6636,L3)+SUMIFS($H$2:$H$6636,$B$2:$B$6636,$K$3,$J$2:$J$6636,L3) -> 0
A4: 46023 | B4: G | D4: 613 | F4: Compra - Disposicion por POS por (1,486.63) mxn en SUPER SERV GARBRI 31dic2025 RFC SSG 981118LR6 Tarjeta 5161020003551118 Recibo # 4394932032322 | H4: 1486.63 | J4: BB 4166 | L4: BBVA 5712 | M4: =SUMIFS($I$2:$I$6636,$B$2:$B$6636,$K$3,$J$2:$J$6636,L4)+SUMIFS($H$2:$H$6636,$B$2:$B$6636,$K$3,$J$2:$J$6636,L4) -> 95716.65
A5: 46023 | B5: G | D5: 613 | F5: Compra - Disposicion por POS por (1,314.20) mxn en SUPER SERV GARBRI 31dic2025 RFC SSG 981118LR6 Tarjeta 5161020003551126 Recibo # 4394928032322 | H5: 1314.2 | J5: BB 4166 | L5: CAJA GRL | M5: =SUMIFS($I$2:$I$6636,$B$2:$B$6636,$K$3,$J$2:$J$6636,L5)+SUMIFS($H$2:$H$6636,$B$2:$B$6636,$K$3,$J$2:$J$6636,L5) -> 0
A6: 46023 | B6: G | D6: 613 | F6: Compra - Disposicion por POS por (1,000.00) mxn en LA QUEMADA GAS 31dic2025 RFC SQU 060616TQ1 Tarjeta 5161020003551084 Recibo # 4394926032322 | H6: 1000 | J6: BB 4166 | L6: BB 506 | M6: =SUMIFS($I$2:$I$6636,$B$2:$B$6636,$K$3,$J$2:$J$6636,L6)+SUMIFS($H$2:$H$6636,$B$2:$B$6636,$K$3,$J$2:$J$6636,L6) -> 0
A7: 46023 | B7: G | D7: 613 | F7: Compra - Disposicion por POS por (751.53) mxn en SUPER SERV GARBRI 31dic2025 RFC SSG 981118LR6 Tarjeta 5161020003884857 Recibo # 4394930032322 | H7: 751.53 | J7: BB 4166 | L7: BTE 7744 | M7: =SUMIFS($I$2:$I$6636,$B$2:$B$6636,$K$3,$J$2:$J$6636,L7)+SUMIFS($H$2:$H$6636,$B$2:$B$6636,$K$3,$J$2:$J$6636,L7) -> 0
A8: 46023 | B8: G | D8: 613 | F8: Compra - Disposicion por POS por (746.02) mxn en SUPER SERV GARBRI 31dic2025 RFC SSG 981118LR6 Tarjeta 5161020003884857 Recibo # 4394931032322 | H8: 746.02 | J8: BB 4166 | L8: BBVA 6721 | M8: =SUMIFS($I$2:$I$6636,$B$2:$B$6636,$K$3,$J$2:$J$6636,L8)+SUMIFS($H$2:$H$6636,$B$2:$B$6636,$K$3,$J$2:$J$6636,L8) -> 0
A9: 46023 | B9: G | D9: 613 | F9: Compra - Disposicion por POS por (602.45) mxn en SERV TAVISA GASOL 31dic2025 RFC EST 161221BS3 Tarjeta 5161020004397545 Recibo # 4394923032322 | H9: 602.45 | J9: BB 4166 | L9: BTE 7133 | M9: =SUMIFS($I$2:$I$6636,$B$2:$B$6636,$K$3,$J$2:$J$6636,L9)+SUMIFS($H$2:$H$6636,$B$2:$B$6636,$K$3,$J$2:$J$6636,L9) -> 0
A10: 46023 | B10: G | D10: 613 | F10: Compra - Disposicion por POS por (463.00) mxn en PZA COBRO PANINDICUARO 31dic2025 RFC HMI 950125KG8 Tarjeta 5161020003551118 Recibo # 4394924032322 | H10: 463 | J10: BB 4166 | L10: STD 1604 | M10: =SUMIFS($I$2:$I$6636,$B$2:$B$6636,$K$3,$J$2:$J$6636,L10)+SUMIFS($H$2:$H$6636,$B$2:$B$6636,$K$3,$J$2:$J$6636,L10) -> 0
A11: 46023 | B11: G | D11: 613 | F11: Compra - Disposicion por POS por (463.00) mxn en PZA COBRO PANINDICUARO 31dic2025 RFC HMI 950125KG8 Tarjeta 5161020003551118 Recibo # 4394924032322 | H11: 463 | J11: BB 4166 | L11: STD 2169 | M11: =SUMIFS($I$2:$I$6636,$B$2:$B$6636,$K$3,$J$2:$J$6636,L11)+SUMIFS($H$2:$H$6636,$B$2:$B$6636,$K$3,$J$2:$J$6636,L11) -> 0
A12: 46023 | B12: G | D12: 613 | F12: Compra - Disposicion por POS por (379.93) mxn en LA QUEMADA GAS 31dic2025 RFC SQU 060616TQ1 Tarjeta 5161020003551084 Recibo # 4394933032322 | H12: 379.93 | J12: BB 4166 | L12: BB 854 | M12: =SUMIFS($I$2:$I$6636,$B$2:$B$6636,$K$3,$J$2:$J$6636,L12)+SUMIFS($H$2:$H$6636,$B$2:$B$6636,$K$3,$J$2:$J$6636,L12) -> 0
A13: 46023 | B13: G | D13: 612 | F13: Comision | H13: 115.03 | J13: BB 854 | L13: BB 3660 | M13: =SUMIFS($I$2:$I$6636,$B$2:$B$6636,$K$3,$J$2:$J$6636,L13)+SUMIFS($H$2:$H$6636,$B$2:$B$6636,$K$3,$J$2:$J$6636,L13) -> 0
A14: 46023 | B14: G | D14: 612 | F14: Comision | H14: 71.11 | J14: BB 854 | L14: BBVA 6586 | M14: =SUMIFS($I$2:$I$6636,$B$2:$B$6636,$K$3,$J$2:$J$6636,L14)+SUMIFS($H$2:$H$6636,$B$2:$B$6636,$K$3,$J$2:$J$6636,L14) -> 32016
A15: 46023 | B15: G | D15: 147 | F15: Iva | H15: 18.4 | J15: BB 854 | L15: BTE 3041 | M15: =SUMIFS($I$2:$I$6636,$B$2:$B$6636,$K$3,$J$2:$J$6636,L15)+SUMIFS($H$2:$H$6636,$B$2:$B$6636,$K$3,$J$2:$J$6636,L15) -> 0
A16: 46023 | B16: G | D16: 147 | F16: Iva | H16: 11.38 | J16: BB 854 | L16: BBVA 4176 | M16: =SUMIFS($I$2:$I$6636,$B$2:$B$6636,$K$3,$J$2:$J$6636,L16)+SUMIFS($H$2:$H$6636,$B$2:$B$6636,$K$3,$J$2:$J$6636,L16) -> 0
A17: 46023 | B17: I | C17: 70 | D17: 102 | F17: Vta.Tlmk Ph Ma. Magdalena | G17: 45994 | I17: 92015.01 | J17: BBVA 6721 | L17: BNMX 1463 | M17: =SUMIFS($I$2:$I$6636,$B$2:$B$6636,$K$3,$J$2:$J$6636,L17)+SUMIFS($H$2:$H$6636,$B$2:$B$6636,$K$3,$J$2:$J$6636,L17) -> 0
A18: 46023 | B18: I | C18: 54 | D18: 102 | F18: venta zamora centro tarjeta | G18: 46022 | I18: 6053.79 | J18: BB 854 | L18: STD 1621 | M18: =SUMIFS($I$2:$I$6636,$B$2:$B$6636,$K$3,$J$2:$J$6636,L18)+SUMIFS($H$2:$H$6636,$B$2:$B$6636,$K$3,$J$2:$J$6636,L18) -> 0
A19: 46023 | B19: I | C19: 54 | D19: 102 | F19: venta zamora centro tarjeta | G19: 46022 | I19: 4445.59 | J19: BB 854 | L19: BBVA 2182 | M19: =SUMIFS($I$2:$I$6636,$B$2:$B$6636,$K$3,$J$2:$J$6636,L19)+SUMIFS($H$2:$H$6636,$B$2:$B$6636,$K$3,$J$2:$J$6636,L19) -> 0
A20: 46023 | B20: I | C20: 73 | D20: 102 | F20: Vta.Tlmk Morelia Juan Jose Camacho | G20: 46021 | I20: 3600 | J20: BBVA 6721 | L20: BBVA 4885 | M20: =SUMIFS($I$2:$I$6636,$B$2:$B$6636,$K$3,$J$2:$J$6636,L20)+SUMIFS($H$2:$H$6636,$B$2:$B$6636,$K$3,$J$2:$J$6636,L20) -> 0
A21: 46023 | B21: I | C21: 73 | D21: 102 | F21: Vta.Tlmk Morelia Juan Jose Camacho | G21: 46021 | I21: 1000 | J21: BBVA 6721
A22: 46024 | B22: TE | D22: - | F22: TRASPASO A BB 4166 | H22: 450000 | J22: STDR 2169
A23: 46024 | B23: TE | D23: - | F23: TRASPASO A BB 4166 | H23: 430000 | J23: STDR 1604
A24: 46024 | B24: C | C24: 0 | D24: 510 | E24: 1 | F24: Dulceria de los Altos | H24: 257467.47 | J24: BBVA 6721
A25: 46024 | B25: C | C25: 50 | D25: 510 | E25: 11 | F25: Distribuidora de la Rosa | H25: 227932.43 | J25: BTE 7744
A26: 46024 | B26: TE | D26: - | F26: TRASPASO ENTRE CTAS 7744 | H26: 200000 | J26: BTE 7133
A27: 46024 | B27: C | C27: 30 | D27: 510 | E27: 1 | F27: Hersheys Mexico | H27: 146226.19 | J27: BBVA 6586
A28: 46024 | B28: C | C28: 10 | D28: 510 | E28: 2 | F28: Distribuidora de la Rosa SA de Cv | H28: 135438.42 | J28: BBVA 6721
A29: 46024 | B29: TE | D29: - | F29: TRASPASO A BTE 7744 | H29: 100000 | J29: BB 4166
A30: 46024 | B30: G | C30: 30 | D30: 610 | E30: 9 | F30: Nomina 01 | H30: 68393.2 | J30: BTE 7744
A31: 46024 | B31: G | C31: 10 | D31: 610 | E31: 4 | F31: Nomina 01 | H31: 65098.2 | J31: BTE 7744
A32: 46024 | B32: G | C32: 12 | D32: 613 | E32: 83449 | F32: G Logisitica comisiones | G32: comisiones varias | H32: 64899 | J32: CAJA GRL
A33: 46024 | B33: G | C33: 50 | D33: 610 | E33: 7 | F33: Nomina 01 | H33: 55317.8 | J33: BTE 7744
A34: 46024 | B34: TE | D34: - | F34: TRASPASO ENTRE CTAS 4166 | H34: 50000 | J34: BB 854
A35: 46024 | B35: G | C35: 0 | D35: 610 | E35: 6 | F35: Nomina 01 | H35: 43745.2 | J35: BTE 7744
A36: 46024 | B36: G | C36: 40 | D36: 610 | E36: 2 | F36: Nomina 01 | H36: 35088.8 | J36: STDR 2169
A37: 46024 | B37: TE | D37: - | F37: TRASPASO ENTRE CTAS 4166 | H37: 35000 | J37: BB 3660
A38: 46024 | B38: G | C38: 4 | D38: 610 | E38: 83419 | F38: G Direccion | G38: Nomina 01 | H38: 33150 | J38: CAJA GRL
A39: 46024 | B39: G | C39: 32 | D39: 610 | E39: 10 | F39: Nomina 01 | H39: 31170.8 | J39: BTE 7744
A40: 46024 | B40: TE | D40: - | F40: TRASPASO ENTRE CTAS 6721 | H40: 30000 | J40: BBVA 4176
A41: 46024 | B41: G | D41: 610 | E41: 1 | F41: Nomina 01 | H41: 29045 | J41: BTE 7744
A42: 46024 | B42: G | C42: 20 | D42: 610 | E42: 5 | F42: Nomina 01 | H42: 28296.2 | J42: BTE 7744
A43: 46024 | B43: TE | D43: - | F43: TRASPASO ENTRE CTAS 6721 | H43: 20000 | J43: BBVA 6586
A44: 46024 | B44: G | C44: 12 | D44: 613 | E44: 1 | F44: Toyocamiones SA de Cv | H44: 19400 | J44: BBVA 5712
A45: 46024 | B45: G | C45: 42 | D45: 610 | E45: 3 | F45: Nomina 01 | H45: 18889.6 | J45: STDR 2169
A46: 46024 | B46: G | C46: 12 | D46: 613 | E46: 83450 | F46: G Logistica viaticos | G46: Viaticos Varios | H46: 17050 | J46: CAJA GRL
A47: 46024 | B47: G | C47: 10 | D47: 610 | E47: 3 | F47: CFE | H47: 16551 | J47: BBVA 5712
A48: 46024 | B48: G | C48: 04 | D48: 610 | E48: 83420 | F48: G Finanzas | G48: Nomina 01 | H48: 13920 | J48: CAJA GRL
A49: 46024 | B49: G | C49: 10 | D49: 610 | E49: 83425 | F49: G Suc PH | G49: Nomina 01 | H49: 11558.5 | J49: CAJA GRL
A50: 46024 | B50: G | C50: 54 | D50: 610 | E50: 8 | F50: Nomina 01 | H50: 10742.8 | J50: BTE 7744
A51: 46024 | B51: G | D51: 610 | E51: 1 | F51: Nomina 01 | H51: 10613.6 | J51: BB 4166
A52: 46024 | B52: G | C52: 40 | D52: 610 | E52: 83415 | F52: g Suc 8 esquinas | G52: Nomina 01 | H52: 9242.5 | J52: CAJA GRL
A53: 46024 | B53: G | C53: 90 | D53: 610 | E53: 2 | F53: Nomina 01 | H53: 8221.4 | J53: BTE 7744
A54: 46024 | B54: G | D54: 610 | E54: 2 | F54: Nomina 01 | H54: 7766.4 | J54: BB 4166
A55: 46024 | B55: G | C55: 20 | D55: 613 | E55: 83436 | F55: G Mariano Martinez Patlan | G55: Comision Periodo 26 | H55: 7406.5 | J55: CAJA GRL
A56: 46024 | B56: G | C56: 20 | D56: 613 | E56: 83433 | F56: G Angel Alberto Vazquez | G56: Comision Periodo 26 | H56: 6801.2 | J56: CAJA GRL
A57: 46024 | B57: G | C57: 01 | D57: 610 | E57: 83432 | F57: G Sistemas | G57: Nomina 01 | H57: 6598.5 | J57: CAJA GRL
A58: 46024 | B58: G | D58: 610 | E58: 4 | F58: Nomina 01 | H58: 6281.2 | J58: BB 4166
A59: 46024 | B59: G | C59: 20 | D59: 613 | E59: 83437 | F59: G Victo Hugo Garcia | G59: Comision Periodo 26 | H59: 5790 | J59: CAJA GRL
A60: 46024 | B60: G | C60: 20 | D60: 613 | E60: 83440 | F60: G Victgorino Urbano | G60: Comision Periodo 26 | H60: 5705.79 | J60: CAJA GRL
A61: 46024 | B61: G | C61: 20 | D61: 613 | E61: 83438 | F61: G Joaquin Hurtado | G61: Comision Periodo 26 | H61: 5623 | J61: CAJA GRL
A62: 46024 | B62: C | C62: 50 | D62: 510 | E62: 2 | F62: Jose Alfonso Gonzalez | H62: 4557.6 | J62: BBVA 5712
A63: 46024 | B63: G | C63: 16 | D63: 610 | E63: 83427 | F63: G PH Staff | G63: Nomina 01 | H63: 4314 | J63: CAJA GRL
A64: 46024 | B64: G | C64: 42 | D64: 610 | E64: 83421 | F64: G Suc LPA | G64: Nomina 01 | H64: 3914.5 | J64: CAJA GRL
A65: 46024 | B65: G | D65: 610 | E65: 3 | F65: Nomina 01 | H65: 3884.6 | J65: BB 4166
A66: 46024 | B66: G | C66: 72 | D66: 612 | F66: SEGUROS BANORTE SA DE CV GRUPO FINANCIERA CARGO COBRANZA DOMICILIADA | H66: 3790 | J66: BTE 7744
A67: 46024 | B67: G | C67: 05 | D67: 610 | E67: 83430 | F67: G RRHH | G67: Nomina 01 | H67: 3719 | J67: CAJA GRL
A68: 46024 | B68: G | C68: 11 | D68: 610 | E68: 83431 | F68: G rutas Vecinales | G68: Nomina 01 | H68: 3586 | J68: CAJA GRL
A69: 46024 | B69: G | C69: 0 | D69: 610 | E69: 83416 | F69: G Cedis | G69: Nomina 01 | H69: 3461 | J69: CAJA GRL
A70: 46024 | B70: G | C70: 70 | D70: 610 | E70: 83428 | F70: G PH Tlmkt | G70: Nomina 01 | H70: 3360.5 | J70: CAJA GRL
A71: 46024 | B71: G | D71: 613 | F71: Compra - Disposicion por POS por (3,308.94) mxn en SUPER SERV GARBRI 01ene2026 RFC SSG 981118LR6 Tarjeta 5161020003551118 Recibo # 4412407032322 | H71: 3308.94 | J71: BB 4166
